Workbook
Name afadrei: Investitionsplan!$H$38
Name afaeins: Investitionsplan!$D$38
Name afavier: Investitionsplan!$J$38
Name afazwei: Investitionsplan!$F$38
Name gj: 'Infos vor dem Start'!$A$13
Name gwg: Parameter!$A$12
Name gwgeins: Investitionsplan!$D$35
Name kapges: 'Infos vor dem Start'!$A$19
Name Monat: 'Infos vor dem Start'!$A$11
Name rechnung: 'Infos vor dem Start'!$A$15
Name USt: Parameter!$A$2
Name USt1neu: Parameter!$B$2
Name USteins: Parameter!$B$2
Name USterm: Parameter!$A$3
Name UStermeins: Parameter!$B$3
Name VSt: Parameter!$A$4
Name VSteins: Parameter!$B$4
Name VSterm: Parameter!$A$5
Name VStermeins: Parameter!$B$5
Name VStWE: Parameter!$A$6
Name VStWEeins: Parameter!$B$6

Sheet Infos vor dem Start
A1: Sehr geehrte Gründerin, sehr geehrter Gründer,
A3: vielen Dank, dass Sie das Finanztool der IHK Köln benutzen! Zunächst ein paar Informationen zur Bedienung:
A4: Wenn Sie nicht im Januar gründen, beginnen Sie bitte mit Ihren Eintragungen im ersten Jahr mit dem Monat, in dem Sie starten möchten. Insgesamt stehen vier Jahre als Planungshorizont zur Verfügung, davon sollten mindestens drei Jahre monatsgenau geplant werden. Tragen Sie Ihren ersten Monat zudem in das Eingabefeld weiter unten ein.
B6: Zellen, in die Sie Werte eintragen können, sind grün gekennzeichnet. Alle anderen Zellen sind schreibgeschützt.
B8: Einige Zellen haben wir mit Erläuterungen versehen - diese erkennen Sie an dem roten Dreieck rechts oben. Sie können sie lesen, wenn Sie mit dem Mauszeiger auf die entsprechende Zelle gehen.
A10: Außerdem bitten wir Sie um einige Angaben, um Ihnen die Arbeit zu erleichtern:
A11: 9 | B11: Ihr erster Gründungsmonat: Bitte geben Sie "1" ein für Januar, "2" für Februar usw. Beginnen Sie Ihre Einträge in der Tabelle bitte auch im entsprechenden Monat. Bitte lassen Sie dieses Feld nicht leer!
A13: 2026 | B13: Ihr Gründungsjahr: bitte ändern, falls abweichend
A15: x | B15: Wenn Sie gegen Rechnung liefern oder leisten, tragen Sie hier bitte ein "x" ein - der Zahlungseingang wird dann im nächsten Monat berücksichtigt. Bei Zug-um-Zug-Geschäften (Barzahlung, Vorkasse, Lastschrift o.ä.) lassen Sie das Feld bitte leer.
A17: x | B17: Wenn Sie Umsatzsteuer in Rechnung stellen werden, tragen Sie hier bitte ein "x" ein, sonst lassen Sie das Feld bitte leer. Die Berechnungen gehen nicht von einer Dauerfristverlängerung aus.
B19: Wenn Sie eine Kapitalgesellschaft (AG, GmbH, UG (haftungsbeschränkt) oder Ltd.) gründen, tragen Sie hier bitte ein "x" ein, sonst lassen Sie das Feld bitte leer.
A21: Wir stellen Ihnen hiermit unentgeltlich eine passwortgeschützte Datei in Excel zum Download zur Verfügung. Alle Änderungen daran,
A22: inbesondere Passwortaufhebung, Seiteneinrichtung und Konvertierungen in andere Formate erfolgen auf eigenes Risiko.
A23: Für alle daraus resultierenden Folgen, wie Ungenauigkeiten und Fehler der Anwendung, übernehmen wir keine Haftung.
A24: Wenn Sie Fragen, Wünsche oder andere Anliegen haben oder uns einfach mitteilen möchten, was Ihnen noch fehlt, schreiben Sie uns unter
A25: finanztool@koeln.ihk.de
A26: Bei Ihrem Vorhaben wünschen wir Ihnen viel Erfolg!
A28: Industrie- und Handelskammer zu Köln
A29: Ihr Team Beratung und Service

Sheet Umsatzplan Dienstleistungen
A1: Geplante Dienstleistungsumsätze | C1: =IF('Infos vor dem Start'!A17="x","EUR pro Leistungseinheit (netto)","EUR pro Leistungseinheit (brutto)") -> EUR pro Leistungseinheit (netto) | G1: Januar | H1: Februar | I1: März | J1: April | K1: Mai | L1: Juni | M1: Juli | N1: August | O1: September | P1: Oktober | Q1: November | R1: Dezember | S1: =+gj -> 2026 | T1: =+G1 -> Januar | U1: =+H1 -> Februar | V1: =+I1 -> März | W1: =+J1 -> April | X1: =+K1 -> Mai | Y1: =+L1 -> Juni | Z1: =+M1 -> Juli | AA1: =+N1 -> August | ... AE1: =+R1 -> Dezember | AF1: =+gj+1 -> 2027 | AG1: =+T1 -> Januar | AH1: =+U1 -> Februar | AI1: =+V1 -> März | AJ1: =+W1 -> April | AK1: =+X1 -> Mai | AL1: =+Y1 -> Juni | AM1: =+Z1 -> Juli | AN1: =+AA1 -> August | ... AR1: =+AE1 -> Dezember | AS1: =+gj+2 -> 2028 | AT1: =+AG1 -> Januar | AU1: =+AH1 -> Februar | AV1: =+AI1 -> März | AW1: =+AJ1 -> April | AX1: =+AK1 -> Mai | AY1: =+AL1 -> Juni | AZ1: =+AM1 -> Juli | BA1: =+AN1 -> August | ... BE1: =+AR1 -> Dezember | BF1: =+gj+3 -> 2029
C2: =+gj -> 2026 | D2: =+C2+1 -> 2027 | E2: =+D2+1 -> 2028 | F2: =+E2+1 -> 2029
A3: Paket 1 | C3: 18000 | G3: 0 | H3: 0 | I3: 0 | J3: 0 | K3: 0 | L3: 0 | M3: 0 | N3: 0 | O3: 0 | P3: 0 | Q3: 0 | R3: 1 | S3: =SUM(G3:R3) -> 1 | T3: =P3 -> 0 | U3: =T3*1.05 -> 0 | V3: =U3*1.05 -> 0 | W3: =V3*1.05 -> 0 | X3: =W3*1.05 -> 0 | Y3: =X3*1.05 -> 0 | Z3: =Y3*1.05 -> 0 | AA3: =Z3*1.05 -> 0 | AB3: =AA3*1.05 -> 0 | ... AE3: =AD3*1.05 -> 0 | AF3: =SUM(T3:AE3) -> 0 | AG3: =AC3 -> 0 | AH3: =AG3*1.05 -> 0 | AI3: =AH3*1.05 -> 0 | AJ3: =AI3*1.05 -> 0 | AK3: =AJ3*1.05 -> 0 | AL3: =AK3*1.05 -> 0 | AM3: =AL3*1.05 -> 0 | AN3: =AM3*1.05 -> 0 | AO3: 0 | AP3: 0 | AQ3: 0 | AR3: 0 | AS3: =SUM(AG3:AR3) -> 0 | BF3: =SUM(AT3:BE3) -> 0
A4: Paket 2 | C4: 29500 | G4: 0 | H4: 0 | I4: 0 | J4: 0 | K4: 0 | L4: 0 | M4: 0 | N4: 0 | O4: 0 | P4: 0 | Q4: 0 | R4: 0 | S4: =SUM(G4:R4) -> 0 | T4: =P4 -> 0 | U4: =T4*1.05 -> 0 | V4: =U4*1.05 -> 0 | W4: =V4*1.05 -> 0 | X4: =W4*1.05 -> 0 | Y4: =X4*1.05 -> 0 | Z4: =Y4*1.05 -> 0 | AA4: =Z4*1.05 -> 0 | AB4: =AA4*1.05 -> 0 | ... AE4: =AD4*1.05 -> 0 | AF4: =SUM(T4:AE4) -> 0 | AG4: =AC4 -> 0 | AH4: =AG4*1.05 -> 0 | AI4: =AH4*1.05 -> 0 | AJ4: =AI4*1.05 -> 0 | AK4: =AJ4*1.05 -> 0 | AL4: =AK4*1.05 -> 0 | AM4: =AL4*1.05 -> 0 | AN4: =AM4*1.05 -> 0 | AO4: 0 | AP4: 0 | AQ4: 0 | AR4: 0 | AS4: =SUM(AG4:AR4) -> 0 | BF4: =SUM(AT4:BE4) -> 0
A5: Paket 3 | C5: 14000 | G5: 0 | H5: 0 | I5: 0 | J5: 0 | K5: 0 | L5: 0 | M5: 0 | N5: 0 | O5: 0 | P5: 1 | Q5: 0 | R5: 0 | S5: =SUM(G5:R5) -> 1 | T5: =P5 -> 1 | U5: =T5*1.05 -> 1.05 | V5: =U5*1.05 -> 1.1025 | W5: =V5*1.05 -> 1.157625 | X5: =W5*1.05 -> 1.2155063 | Y5: =X5*1.05 -> 1.2762816 | Z5: =Y5*1.05 -> 1.3400956 | AA5: =Z5*1.05 -> 1.4071004 | AB5: =AA5*1.05 -> 1.4774554 | ... AE5: =AD5*1.05 -> 1.7103394 | AF5: =SUM(T5:AE5) -> 15.917127 | AG5: =AC5 -> 1.5513282 | AH5: =AG5*1.05 -> 1.6288946 | AI5: =AH5*1.05 -> 1.7103394 | AJ5: =AI5*1.05 -> 1.7958563 | AK5: =AJ5*1.05 -> 1.8856491 | AL5: =AK5*1.05 -> 1.9799316 | AM5: =AL5*1.05 -> 2.0789282 | AN5: =AM5*1.05 -> 2.1828746 | AO5: 0 | AP5: 0 | AQ5: 0 | AR5: 0 | AS5: =SUM(AG5:AR5) -> 14.813802 | BF5: =SUM(AT5:BE5) -> 0
G6: 0 | H6: 0 | I6: 0 | J6: 0 | K6: 0 | L6: 0 | M6: 0 | N6: 0 | O6: 0 | P6: 0 | Q6: 0 | R6: 0 | S6: =SUM(G6:R6) -> 0 | T6: =P6 -> 0 | U6: =T6*1.1 -> 0 | V6: =U6*1.1 -> 0 | W6: =V6*1.1 -> 0 | X6: =W6*1.1 -> 0 | Y6: =X6*1.1 -> 0 | Z6: =Y6*1.1 -> 0 | AA6: =Z6*1.1 -> 0 | AB6: =AA6*1.1 -> 0 | ... AE6: =AD6*1.1 -> 0 | AF6: =SUM(T6:AE6) -> 0 | AG6: =AC6 -> 0 | AH6: =AG6*1.05 -> 0 | AI6: =AH6*1.05 -> 0 | AJ6: =AI6*1.05 -> 0 | AK6: =AJ6*1.05 -> 0 | AL6: =AK6*1.05 -> 0 | AM6: =AL6*1.05 -> 0 | AN6: =AM6*1.05 -> 0 | AO6: 0 | AP6: 0 | AQ6: 0 | AR6: 0 | AS6: =SUM(AG6:AR6) -> 0 | BF6: =SUM(AT6:BE6) -> 0
G7: 0 | H7: 0 | I7: 0 | J7: 0 | K7: 0 | L7: 0 | M7: 0 | N7: 0 | O7: 0 | P7: 0 | Q7: 0 | R7: 0 | S7: =SUM(G7:R7) -> 0 | T7: =P7 -> 0 | U7: =T7*1.1 -> 0 | V7: =U7*1.1 -> 0 | W7: =V7*1.1 -> 0 | X7: =W7*1.1 -> 0 | Y7: =X7*1.1 -> 0 | Z7: =Y7*1.1 -> 0 | AA7: =Z7*1.1 -> 0 | AB7: =AA7*1.1 -> 0 | ... AE7: =AD7*1.1 -> 0 | AF7: =SUM(T7:AE7) -> 0 | AG7: =AC7 -> 0 | AH7: =AG7*1.05 -> 0 | AI7: =AH7*1.05 -> 0 | AJ7: =AI7*1.05 -> 0 | AK7: =AJ7*1.05 -> 0 | AL7: =AK7*1.05 -> 0 | AM7: =AL7*1.05 -> 0 | AN7: =AM7*1.05 -> 0 | AO7: 0 | AP7: 0 | AQ7: 0 | AR7: 0 | AS7: =SUM(AG7:AR7) -> 0 | BF7: =SUM(AT7:BE7) -> 0
G8: 0 | H8: 0 | I8: 0 | J8: 0 | K8: 0 | L8: 0 | M8: 0 | N8: 0 | O8: 0 | P8: 0 | Q8: 0 | R8: 0 | S8: =SUM(G8:R8) -> 0 | T8: =R8 -> 0 | U8: =S8 -> 0 | V8: =T8 -> 0 | W8: =U8 -> 0 | X8: =V8 -> 0 | Y8: =W8 -> 0 | Z8: =X8 -> 0 | AA8: =Y8 -> 0 | ... AE8: =AC8 -> 0 | AF8: =SUM(T8:AE8) -> 0 | AG8: 0 | AH8: 0 | AI8: 0 | AJ8: 0 | AK8: 0 | AL8: 0 | AM8: 0 | AN8: 0 | AO8: 0 | AP8: 0 | AQ8: 0 | AR8: 0 | AS8: =SUM(AG8:AR8) -> 0 | BF8: =SUM(AT8:BE8) -> 0
S9: =SUM(G9:R9) -> 0 | AF9: =SUM(T9:AE9) -> 0 | AS9: =SUM(AG9:AR9) -> 0 | BF9: =SUM(AT9:BE9) -> 0
S10: =SUM(G10:R10) -> 0 | AF10: =SUM(T10:AE10) -> 0 | AS10: =SUM(AG10:AR10) -> 0 | BF10: =SUM(AT10:BE10) -> 0
S11: =SUM(G11:R11) -> 0 | AF11: =SUM(T11:AE11) -> 0 | AS11: =SUM(AG11:AR11) -> 0 | BF11: =SUM(AT11:BE11) -> 0
S12: =SUM(G12:R12) -> 0 | AF12: =SUM(T12:AE12) -> 0 | AS12: =SUM(AG12:AR12) -> 0 | BF12: =SUM(AT12:BE12) -> 0
S13: =SUM(G13:R13) -> 0 | AF13: =SUM(T13:AE13) -> 0 | AS13: =SUM(AG13:AR13) -> 0 | BF13: =SUM(AT13:BE13) -> 0
S14: =SUM(G14:R14) -> 0 | AF14: =SUM(T14:AE14) -> 0 | AS14: =SUM(AG14:AR14) -> 0 | BF14: =SUM(AT14:BE14) -> 0
S15: =SUM(G15:R15) -> 0 | AF15: =SUM(T15:AE15) -> 0 | AS15: =SUM(AG15:AR15) -> 0 | BF15: =SUM(AT15:BE15) -> 0
S16: =SUM(G16:R16) -> 0 | AF16: =SUM(T16:AE16) -> 0 | AS16: =SUM(AG16:AR16) -> 0 | BF16: =SUM(AT16:BE16) -> 0
S17: =SUM(G17:R17) -> 0 | AF17: =SUM(T17:AE17) -> 0 | AS17: =SUM(AG17:AR17) -> 0 | BF17: =SUM(AT17:BE17) -> 0
S18: =SUM(G18:R18) -> 0 | AF18: =SUM(T18:AE18) -> 0 | AS18: =SUM(AG18:AR18) -> 0 | BF18: =SUM(AT18:BE18) -> 0
S19: =SUM(G19:R19) -> 0 | AF19: =SUM(T19:AE19) -> 0 | AS19: =SUM(AG19:AR19) -> 0 | BF19: =SUM(AT19:BE19) -> 0
S20: =SUM(G20:R20) -> 0 | AF20: =SUM(T20:AE20) -> 0 | AS20: =SUM(AG20:AR20) -> 0 | BF20: =SUM(AT20:BE20) -> 0
... S22: =SUM(G22:R22) -> 0 | AF22: =SUM(T22:AE22) -> 0 | AS22: =SUM(AG22:AR22) -> 0 | BF22: =SUM(AT22:BE22) -> 0
G23: =SUM(G3:G22) -> 0 | H23: =SUM(H3:H22) -> 0 | I23: =SUM(I3:I22) -> 0 | J23: =SUM(J3:J22) -> 0 | K23: =SUM(K3:K22) -> 0 | L23: =SUM(L3:L22) -> 0 | M23: =SUM(M3:M22) -> 0 | N23: =SUM(N3:N22) -> 0 | ... BF23: =SUM(BF3:BF22) -> 0
A24: =+A3 -> Paket 1 | G24: =+G3*$C3 -> 0 | H24: =+H3*$C3 -> 0 | I24: =+I3*$C3 -> 0 | J24: =+J3*$C3 -> 0 | K24: =+K3*$C3 -> 0 | L24: =+L3*$C3 -> 0 | M24: =+M3*$C3 -> 0 | N24: =+N3*$C3 -> 0 | ... R24: =+R3*$C3 -> 18000 | S24: =SUM(G24:R24) -> 18000 | T24: =+T3*$D3 -> 0 | U24: =+U3*$D3 -> 0 | V24: =+V3*$D3 -> 0 | W24: =+W3*$D3 -> 0 | X24: =+X3*$D3 -> 0 | Y24: =+Y3*$D3 -> 0 | Z24: =+Z3*$D3 -> 0 | AA24: =+AA3*$D3 -> 0 | ... AE24: =+AE3*$D3 -> 0 | AF24: =SUM(T24:AE24) -> 0 | AG24: =+AG3*$E3 -> 0 | AH24: =+AH3*$E3 -> 0 | AI24: =+AI3*$E3 -> 0 | AJ24: =+AJ3*$E3 -> 0 | AK24: =+AK3*$E3 -> 0 | AL24: =+AL3*$E3 -> 0 | AM24: =+AM3*$E3 -> 0 | AN24: =+AN3*$E3 -> 0 | ... AR24: =+AR3*$E3 -> 0 | AS24: =SUM(AG24:AR24) -> 0 | AT24: =+AT3*$F3 -> 0 | AU24: =+AU3*$F3 -> 0 | AV24: =+AV3*$F3 -> 0 | AW24: =+AW3*$F3 -> 0 | AX24: =+AX3*$F3 -> 0 | AY24: =+AY3*$F3 -> 0 | AZ24: =+AZ3*$F3 -> 0 | BA24: =+BA3*$F3 -> 0 | ... BE24: =+BE3*$F3 -> 0 | BF24: =SUM(AT24:BE24) -> 0
A25: =+A4 -> Paket 2 | G25: =+G4*$C4 -> 0 | H25: =+H4*$C4 -> 0 | I25: =+I4*$C4 -> 0 | J25: =+J4*$C4 -> 0 | K25: =+K4*$C4 -> 0 | L25: =+L4*$C4 -> 0 | M25: =+M4*$C4 -> 0 | N25: =+N4*$C4 -> 0 | ... R25: =+R4*$C4 -> 0 | S25: =SUM(G25:R25) -> 0 | T25: =+T4*$D4 -> 0 | U25: =+U4*$D4 -> 0 | V25: =+V4*$D4 -> 0 | W25: =+W4*$D4 -> 0 | X25: =+X4*$D4 -> 0 | Y25: =+Y4*$D4 -> 0 | Z25: =+Z4*$D4 -> 0 | AA25: =+AA4*$D4 -> 0 | ... AE25: =+AE4*$D4 -> 0 | AF25: =SUM(T25:AE25) -> 0 | AG25: =+AG4*$E4 -> 0 | AH25: =+AH4*$E4 -> 0 | AI25: =+AI4*$E4 -> 0 | AJ25: =+AJ4*$E4 -> 0 | AK25: =+AK4*$E4 -> 0 | AL25: =+AL4*$E4 -> 0 | AM25: =+AM4*$E4 -> 0 | AN25: =+AN4*$E4 -> 0 | ... AR25: =+AR4*$E4 -> 0 | AS25: =SUM(AG25:AR25) -> 0 | AT25: =+AT4*$F4 -> 0 | AU25: =+AU4*$F4 -> 0 | AV25: =+AV4*$F4 -> 0 | AW25: =+AW4*$F4 -> 0 | AX25: =+AX4*$F4 -> 0 | AY25: =+AY4*$F4 -> 0 | AZ25: =+AZ4*$F4 -> 0 | BA25: =+BA4*$F4 -> 0 | ... BE25: =+BE4*$F4 -> 0 | BF25: =SUM(AT25:BE25) -> 0
A26: =+A5 -> Paket 3 | G26: =+G5*$C5 -> 0 | H26: =+H5*$C5 -> 0 | I26: =+I5*$C5 -> 0 | J26: =+J5*$C5 -> 0 | K26: =+K5*$C5 -> 0 | L26: =+L5*$C5 -> 0 | M26: =+M5*$C5 -> 0 | N26: =+N5*$C5 -> 0 | ... R26: =+R5*$C5 -> 0 | S26: =SUM(G26:R26) -> 14000 | T26: =+T5*$D5 -> 0 | U26: =+U5*$D5 -> 0 | V26: =+V5*$D5 -> 0 | W26: =+W5*$D5 -> 0 | X26: =+X5*$D5 -> 0 | Y26: =+Y5*$D5 -> 0 | Z26: =+Z5*$D5 -> 0 | AA26: =+AA5*$D5 -> 0 | ... AE26: =+AE5*$D5 -> 0 | AF26: =SUM(T26:AE26) -> 0 | AG26: =+AG5*$E5 -> 0 | AH26: =+AH5*$E5 -> 0 | AI26: =+AI5*$E5 -> 0 | AJ26: =+AJ5*$E5 -> 0 | AK26: =+AK5*$E5 -> 0 | AL26: =+AL5*$E5 -> 0 | AM26: =+AM5*$E5 -> 0 | AN26: =+AN5*$E5 -> 0 | ... AR26: =+AR5*$E5 -> 0 | AS26: =SUM(AG26:AR26) -> 0 | AT26: =+AT5*$F5 -> 0 | AU26: =+AU5*$F5 -> 0 | AV26: =+AV5*$F5 -> 0 | AW26: =+AW5*$F5 -> 0 | AX26: =+AX5*$F5 -> 0 | AY26: =+AY5*$F5 -> 0 | AZ26: =+AZ5*$F5 -> 0 | BA26: =+BA5*$F5 -> 0 | ... BE26: =+BE5*$F5 -> 0 | BF26: =SUM(AT26:BE26) -> 0
A27: =+A6 -> 0 | G27: =+G6*$C6 -> 0 | H27: =+H6*$C6 -> 0 | I27: =+I6*$C6 -> 0 | J27: =+J6*$C6 -> 0 | K27: =+K6*$C6 -> 0 | L27: =+L6*$C6 -> 0 | M27: =+M6*$C6 -> 0 | N27: =+N6*$C6 -> 0 | ... R27: =+R6*$C6 -> 0 | S27: =SUM(G27:R27) -> 0 | T27: =+T6*$D6 -> 0 | U27: =+U6*$D6 -> 0 | V27: =+V6*$D6 -> 0 | W27: =+W6*$D6 -> 0 | X27: =+X6*$D6 -> 0 | Y27: =+Y6*$D6 -> 0 | Z27: =+Z6*$D6 -> 0 | AA27: =+AA6*$D6 -> 0 | ... AE27: =+AE6*$D6 -> 0 | AF27: =SUM(T27:AE27) -> 0 | AG27: =+AG6*$E6 -> 0 | AH27: =+AH6*$E6 -> 0 | AI27: =+AI6*$E6 -> 0 | AJ27: =+AJ6*$E6 -> 0 | AK27: =+AK6*$E6 -> 0 | AL27: =+AL6*$E6 -> 0 | AM27: =+AM6*$E6 -> 0 | AN27: =+AN6*$E6 -> 0 | ... AR27: =+AR6*$E6 -> 0 | AS27: =SUM(AG27:AR27) -> 0 | AT27: =+AT6*$F6 -> 0 | AU27: =+AU6*$F6 -> 0 | AV27: =+AV6*$F6 -> 0 | AW27: =+AW6*$F6 -> 0 | AX27: =+AX6*$F6 -> 0 | AY27: =+AY6*$F6 -> 0 | AZ27: =+AZ6*$F6 -> 0 | BA27: =+BA6*$F6 -> 0 | ... BE27: =+BE6*$F6 -> 0 | BF27: =SUM(AT27:BE27) -> 0
A28: =+A7 -> 0 | G28: =+G7*$C7 -> 0 | H28: =+H7*$C7 -> 0 | I28: =+I7*$C7 -> 0 | J28: =+J7*$C7 -> 0 | K28: =+K7*$C7 -> 0 | L28: =+L7*$C7 -> 0 | M28: =+M7*$C7 -> 0 | N28: =+N7*$C7 -> 0 | ... R28: =+R7*$C7 -> 0 | S28: =SUM(G28:R28) -> 0 | T28: =+T7*$D7 -> 0 | U28: =+U7*$D7 -> 0 | V28: =+V7*$D7 -> 0 | W28: =+W7*$D7 -> 0 | X28: =+X7*$D7 -> 0 | Y28: =+Y7*$D7 -> 0 | Z28: =+Z7*$D7 -> 0 | AA28: =+AA7*$D7 -> 0 | ... AE28: =+AE7*$D7 -> 0 | AF28: =SUM(T28:AE28) -> 0 | AG28: =+AG7*$E7 -> 0 | AH28: =+AH7*$E7 -> 0 | AI28: =+AI7*$E7 -> 0 | AJ28: =+AJ7*$E7 -> 0 | AK28: =+AK7*$E7 -> 0 | AL28: =+AL7*$E7 -> 0 | AM28: =+AM7*$E7 -> 0 | AN28: =+AN7*$E7 -> 0 | ... AR28: =+AR7*$E7 -> 0 | AS28: =SUM(AG28:AR28) -> 0 | AT28: =+AT7*$F7 -> 0 | AU28: =+AU7*$F7 -> 0 | AV28: =+AV7*$F7 -> 0 | AW28: =+AW7*$F7 -> 0 | AX28: =+AX7*$F7 -> 0 | AY28: =+AY7*$F7 -> 0 | AZ28: =+AZ7*$F7 -> 0 | BA28: =+BA7*$F7 -> 0 | ... BE28: =+BE7*$F7 -> 0 | BF28: =SUM(AT28:BE28) -> 0
A29: =+A8 -> 0 | G29: =+G8*$C8 -> 0 | H29: =+H8*$C8 -> 0 | I29: =+I8*$C8 -> 0 | J29: =+J8*$C8 -> 0 | K29: =+K8*$C8 -> 0 | L29: =+L8*$C8 -> 0 | M29: =+M8*$C8 -> 0 | N29: =+N8*$C8 -> 0 | ... R29: =+R8*$C8 -> 0 | S29: =SUM(G29:R29) -> 0 | T29: =+T8*$D8 -> 0 | U29: =+U8*$D8 -> 0 | V29: =+V8*$D8 -> 0 | W29: =+W8*$D8 -> 0 | X29: =+X8*$D8 -> 0 | Y29: =+Y8*$D8 -> 0 | Z29: =+Z8*$D8 -> 0 | AA29: =+AA8*$D8 -> 0 | ... AE29: =+AE8*$D8 -> 0 | AF29: =SUM(T29:AE29) -> 0 | AG29: =+AG8*$E8 -> 0 | AH29: =+AH8*$E8 -> 0 | AI29: =+AI8*$E8 -> 0 | AJ29: =+AJ8*$E8 -> 0 | AK29: =+AK8*$E8 -> 0 | AL29: =+AL8*$E8 -> 0 | AM29: =+AM8*$E8 -> 0 | AN29: =+AN8*$E8 -> 0 | ... AR29: =+AR8*$E8 -> 0 | AS29: =SUM(AG29:AR29) -> 0 | AT29: =+AT8*$F8 -> 0 | AU29: =+AU8*$F8 -> 0 | AV29: =+AV8*$F8 -> 0 | AW29: =+AW8*$F8 -> 0 | AX29: =+AX8*$F8 -> 0 | AY29: =+AY8*$F8 -> 0 | AZ29: =+AZ8*$F8 -> 0 | BA29: =+BA8*$F8 -> 0 | ... BE29: =+BE8*$F8 -> 0 | BF29: =SUM(AT29:BE29) -> 0
A30: =+A9 -> 0 | G30: =+G9*$C9 -> 0 | H30: =+H9*$C9 -> 0 | I30: =+I9*$C9 -> 0 | J30: =+J9*$C9 -> 0 | K30: =+K9*$C9 -> 0 | L30: =+L9*$C9 -> 0 | M30: =+M9*$C9 -> 0 | N30: =+N9*$C9 -> 0 | ... R30: =+R9*$C9 -> 0 | S30: =SUM(G30:R30) -> 0 | T30: =+T9*$D9 -> 0 | U30: =+U9*$D9 -> 0 | V30: =+V9*$D9 -> 0 | W30: =+W9*$D9 -> 0 | X30: =+X9*$D9 -> 0 | Y30: =+Y9*$D9 -> 0 | Z30: =+Z9*$D9 -> 0 | AA30: =+AA9*$D9 -> 0 | ... AE30: =+AE9*$D9 -> 0 | AF30: =SUM(T30:AE30) -> 0 | AG30: =+AG9*$E9 -> 0 | AH30: =+AH9*$E9 -> 0 | AI30: =+AI9*$E9 -> 0 | AJ30: =+AJ9*$E9 -> 0 | AK30: =+AK9*$E9 -> 0 | AL30: =+AL9*$E9 -> 0 | AM30: =+AM9*$E9 -> 0 | AN30: =+AN9*$E9 -> 0 | ... AR30: =+AR9*$E9 -> 0 | AS30: =SUM(AG30:AR30) -> 0 | AT30: =+AT9*$F9 -> 0 | AU30: =+AU9*$F9 -> 0 | AV30: =+AV9*$F9 -> 0 | AW30: =+AW9*$F9 -> 0 | AX30: =+AX9*$F9 -> 0 | AY30: =+AY9*$F9 -> 0 | AZ30: =+AZ9*$F9 -> 0 | BA30: =+BA9*$F9 -> 0 | ... BE30: =+BE9*$F9 -> 0 | BF30: =SUM(AT30:BE30) -> 0
A31: =+A10 -> 0 | G31: =+G10*$C10 -> 0 | H31: =+H10*$C10 -> 0 | I31: =+I10*$C10 -> 0 | J31: =+J10*$C10 -> 0 | K31: =+K10*$C10 -> 0 | L31: =+L10*$C10 -> 0 | M31: =+M10*$C10 -> 0 | N31: =+N10*$C10 -> 0 | ... R31: =+R10*$C10 -> 0 | S31: =SUM(G31:R31) -> 0 | T31: =+T10*$D10 -> 0 | U31: =+U10*$D10 -> 0 | V31: =+V10*$D10 -> 0 | W31: =+W10*$D10 -> 0 | X31: =+X10*$D10 -> 0 | Y31: =+Y10*$D10 -> 0 | Z31: =+Z10*$D10 -> 0 | AA31: =+AA10*$D10 -> 0 | ... AE31: =+AE10*$D10 -> 0 | AF31: =SUM(T31:AE31) -> 0 | AG31: =+AG10*$E10 -> 0 | AH31: =+AH10*$E10 -> 0 | AI31: =+AI10*$E10 -> 0 | AJ31: =+AJ10*$E10 -> 0 | AK31: =+AK10*$E10 -> 0 | AL31: =+AL10*$E10 -> 0 | AM31: =+AM10*$E10 -> 0 | AN31: =+AN10*$E10 -> 0 | ... AR31: =+AR10*$E10 -> 0 | AS31: =SUM(AG31:AR31) -> 0 | AT31: =+AT10*$F10 -> 0 | AU31: =+AU10*$F10 -> 0 | AV31: =+AV10*$F10 -> 0 | AW31: =+AW10*$F10 -> 0 | AX31: =+AX10*$F10 -> 0 | AY31: =+AY10*$F10 -> 0 | AZ31: =+AZ10*$F10 -> 0 | BA31: =+BA10*$F10 -> 0 | ... BE31: =+BE10*$F10 -> 0 | BF31: =SUM(AT31:BE31) -> 0
A32: =+A11 -> 0 | G32: =+G11*$C11 -> 0 | H32: =+H11*$C11 -> 0 | I32: =+I11*$C11 -> 0 | J32: =+J11*$C11 -> 0 | K32: =+K11*$C11 -> 0 | L32: =+L11*$C11 -> 0 | M32: =+M11*$C11 -> 0 | N32: =+N11*$C11 -> 0 | ... R32: =+R11*$C11 -> 0 | S32: =SUM(G32:R32) -> 0 | T32: =+T11*$D11 -> 0 | U32: =+U11*$D11 -> 0 | V32: =+V11*$D11 -> 0 | W32: =+W11*$D11 -> 0 | X32: =+X11*$D11 -> 0 | Y32: =+Y11*$D11 -> 0 | Z32: =+Z11*$D11 -> 0 | AA32: =+AA11*$D11 -> 0 | ... AE32: =+AE11*$D11 -> 0 | AF32: =SUM(T32:AE32) -> 0 | AG32: =+AG11*$E11 -> 0 | AH32: =+AH11*$E11 -> 0 | AI32: =+AI11*$E11 -> 0 | AJ32: =+AJ11*$E11 -> 0 | AK32: =+AK11*$E11 -> 0 | AL32: =+AL11*$E11 -> 0 | AM32: =+AM11*$E11 -> 0 | AN32: =+AN11*$E11 -> 0 | ... AR32: =+AR11*$E11 -> 0 | AS32: =SUM(AG32:AR32) -> 0 | AT32: =+AT11*$F11 -> 0 | AU32: =+AU11*$F11 -> 0 | AV32: =+AV11*$F11 -> 0 | AW32: =+AW11*$F11 -> 0 | AX32: =+AX11*$F11 -> 0 | AY32: =+AY11*$F11 -> 0 | AZ32: =+AZ11*$F11 -> 0 | BA32: =+BA11*$F11 -> 0 | ... BE32: =+BE11*$F11 -> 0 | BF32: =SUM(AT32:BE32) -> 0
A33: =+A12 -> 0 | G33: =+G12*$C12 -> 0 | H33: =+H12*$C12 -> 0 | I33: =+I12*$C12 -> 0 | J33: =+J12*$C12 -> 0 | K33: =+K12*$C12 -> 0 | L33: =+L12*$C12 -> 0 | M33: =+M12*$C12 -> 0 | N33: =+N12*$C12 -> 0 | ... R33: =+R12*$C12 -> 0 | S33: =SUM(G33:R33) -> 0 | T33: =+T12*$D12 -> 0 | U33: =+U12*$D12 -> 0 | V33: =+V12*$D12 -> 0 | W33: =+W12*$D12 -> 0 | X33: =+X12*$D12 -> 0 | Y33: =+Y12*$D12 -> 0 | Z33: =+Z12*$D12 -> 0 | AA33: =+AA12*$D12 -> 0 | ... AE33: =+AE12*$D12 -> 0 | AF33: =SUM(T33:AE33) -> 0 | AG33: =+AG12*$E12 -> 0 | AH33: =+AH12*$E12 -> 0 | AI33: =+AI12*$E12 -> 0 | AJ33: =+AJ12*$E12 -> 0 | AK33: =+AK12*$E12 -> 0 | AL33: =+AL12*$E12 -> 0 | AM33: =+AM12*$E12 -> 0 | AN33: =+AN12*$E12 -> 0 | ... AR33: =+AR12*$E12 -> 0 | AS33: =SUM(AG33:AR33) -> 0 | AT33: =+AT12*$F12 -> 0 | AU33: =+AU12*$F12 -> 0 | AV33: =+AV12*$F12 -> 0 | AW33: =+AW12*$F12 -> 0 | AX33: =+AX12*$F12 -> 0 | AY33: =+AY12*$F12 -> 0 | AZ33: =+AZ12*$F12 -> 0 | BA33: =+BA12*$F12 -> 0 | ... BE33: =+BE12*$F12 -> 0 | BF33: =SUM(AT33:BE33) -> 0
A34: =+A13 -> 0 | G34: =+G13*$C13 -> 0 | H34: =+H13*$C13 -> 0 | I34: =+I13*$C13 -> 0 | J34: =+J13*$C13 -> 0 | K34: =+K13*$C13 -> 0 | L34: =+L13*$C13 -> 0 | M34: =+M13*$C13 -> 0 | N34: =+N13*$C13 -> 0 | ... R34: =+R13*$C13 -> 0 | S34: =SUM(G34:R34) -> 0 | T34: =+T13*$D13 -> 0 | U34: =+U13*$D13 -> 0 | V34: =+V13*$D13 -> 0 | W34: =+W13*$D13 -> 0 | X34: =+X13*$D13 -> 0 | Y34: =+Y13*$D13 -> 0 | Z34: =+Z13*$D13 -> 0 | AA34: =+AA13*$D13 -> 0 | ... AE34: =+AE13*$D13 -> 0 | AF34: =SUM(T34:AE34) -> 0 | AG34: =+AG13*$E13 -> 0 | AH34: =+AH13*$E13 -> 0 | AI34: =+AI13*$E13 -> 0 | AJ34: =+AJ13*$E13 -> 0 | AK34: =+AK13*$E13 -> 0 | AL34: =+AL13*$E13 -> 0 | AM34: =+AM13*$E13 -> 0 | AN34: =+AN13*$E13 -> 0 | ... AR34: =+AR13*$E13 -> 0 | AS34: =SUM(AG34:AR34) -> 0 | AT34: =+AT13*$F13 -> 0 | AU34: =+AU13*$F13 -> 0 | AV34: =+AV13*$F13 -> 0 | AW34: =+AW13*$F13 -> 0 | AX34: =+AX13*$F13 -> 0 | AY34: =+AY13*$F13 -> 0 | AZ34: =+AZ13*$F13 -> 0 | BA34: =+BA13*$F13 -> 0 | ... BE34: =+BE13*$F13 -> 0 | BF34: =SUM(AT34:BE34) -> 0
A35: =+A14 -> 0 | G35: =+G14*$C14 -> 0 | H35: =+H14*$C14 -> 0 | I35: =+I14*$C14 -> 0 | J35: =+J14*$C14 -> 0 | K35: =+K14*$C14 -> 0 | L35: =+L14*$C14 -> 0 | M35: =+M14*$C14 -> 0 | N35: =+N14*$C14 -> 0 | ... R35: =+R14*$C14 -> 0 | S35: =SUM(G35:R35) -> 0 | T35: =+T14*$D14 -> 0 | U35: =+U14*$D14 -> 0 | V35: =+V14*$D14 -> 0 | W35: =+W14*$D14 -> 0 | X35: =+X14*$D14 -> 0 | Y35: =+Y14*$D14 -> 0 | Z35: =+Z14*$D14 -> 0 | AA35: =+AA14*$D14 -> 0 | ... AE35: =+AE14*$D14 -> 0 | AF35: =SUM(T35:AE35) -> 0 | AG35: =+AG14*$E14 -> 0 | AH35: =+AH14*$E14 -> 0 | AI35: =+AI14*$E14 -> 0 | AJ35: =+AJ14*$E14 -> 0 | AK35: =+AK14*$E14 -> 0 | AL35: =+AL14*$E14 -> 0 | AM35: =+AM14*$E14 -> 0 | AN35: =+AN14*$E14 -> 0 | ... AR35: =+AR14*$E14 -> 0 | AS35: =SUM(AG35:AR35) -> 0 | AT35: =+AT14*$F14 -> 0 | AU35: =+AU14*$F14 -> 0 | AV35: =+AV14*$F14 -> 0 | AW35: =+AW14*$F14 -> 0 | AX35: =+AX14*$F14 -> 0 | AY35: =+AY14*$F14 -> 0 | AZ35: =+AZ14*$F14 -> 0 | BA35: =+BA14*$F14 -> 0 | ... BE35: =+BE14*$F14 -> 0 | BF35: =SUM(AT35:BE35) -> 0
... A43: =+A22 -> 0 | G43: =+G22*$C22 -> 0 | H43: =+H22*$C22 -> 0 | I43: =+I22*$C22 -> 0 | J43: =+J22*$C22 -> 0 | K43: =+K22*$C22 -> 0 | L43: =+L22*$C22 -> 0 | M43: =+M22*$C22 -> 0 | N43: =+N22*$C22 -> 0 | ... R43: =+R22*$C22 -> 0 | S43: =SUM(G43:R43) -> 0 | T43: =+T22*$D22 -> 0 | U43: =+U22*$D22 -> 0 | V43: =+V22*$D22 -> 0 | W43: =+W22*$D22 -> 0 | X43: =+X22*$D22 -> 0 | Y43: =+Y22*$D22 -> 0 | Z43: =+Z22*$D22 -> 0 | AA43: =+AA22*$D22 -> 0 | ... AE43: =+AE22*$D22 -> 0 | AF43: =SUM(T43:AE43) -> 0 | AG43: =+AG22*$E22 -> 0 | AH43: =+AH22*$E22 -> 0 | AI43: =+AI22*$E22 -> 0 | AJ43: =+AJ22*$E22 -> 0 | AK43: =+AK22*$E22 -> 0 | AL43: =+AL22*$E22 -> 0 | AM43: =+AM22*$E22 -> 0 | AN43: =+AN22*$E22 -> 0 | ... AR43: =+AR22*$E22 -> 0 | AS43: =SUM(AG43:AR43) -> 0 | AT43: =+AT22*$F22 -> 0 | AU43: =+AU22*$F22 -> 0 | AV43: =+AV22*$F22 -> 0 | AW43: =+AW22*$F22 -> 0 | AX43: =+AX22*$F22 -> 0 | AY43: =+AY22*$F22 -> 0 | AZ43: =+AZ22*$F22 -> 0 | BA43: =+BA22*$F22 -> 0 | ... BE43: =+BE22*$F22 -> 0 | BF43: =SUM(AT43:BE43) -> 0
G44: =ROUND(SUM(G24:G43),0) -> 0 | H44: =ROUND(SUM(H24:H43),0) -> 0 | I44: =ROUND(SUM(I24:I43),0) -> 0 | J44: =ROUND(SUM(J24:J43),0) -> 0 | K44: =ROUND(SUM(K24:K43),0) -> 0 | L44: =ROUND(SUM(L24:L43),0) -> 0 | M44: =ROUND(SUM(M24:M43),0) -> 0 | N44: =ROUND(SUM(N24:N43),0) -> 0 | ... BF44: =ROUND(SUM(BF24:BF43),0) -> 0

Sheet Rentabilitätsvorschau
A1: =IF('Infos vor dem Start'!A17="x","Bitte Netto-Werte (ohne Umsatz- bzw. Vorsteuer) eintragen!","Bitte bei den Kosten Brutto-Werte (einschließlich Umsatzsteuer) eintragen!") -> Bitte Netto-Werte (ohne Umsatz- bzw. Vorsteuer) eintragen! | D1: =+'Umsatzplan Dienstleistungen'!G1 -> Januar | E1: =+'Umsatzplan Dienstleistungen'!H1 -> Februar | F1: =+'Umsatzplan Dienstleistungen'!I1 -> März | G1: =+'Umsatzplan Dienstleistungen'!J1 -> April | H1: =+'Umsatzplan Dienstleistungen'!K1 -> Mai | I1: =+'Umsatzplan Dienstleistungen'!L1 -> Juni | J1: =+'Umsatzplan Dienstleistungen'!M1 -> Juli | K1: =+'Umsatzplan Dienstleistungen'!N1 -> August | ... O1: =+'Umsatzplan Dienstleistungen'!R1 -> Dezember | P1: =+gj -> 2026 | Q1: =+'Umsatzplan Dienstleistungen'!T1 -> Januar | R1: =+'Umsatzplan Dienstleistungen'!U1 -> Februar | S1: =+'Umsatzplan Dienstleistungen'!V1 -> März | T1: =+'Umsatzplan Dienstleistungen'!W1 -> April | U1: =+'Umsatzplan Dienstleistungen'!X1 -> Mai | V1: =+'Umsatzplan Dienstleistungen'!Y1 -> Juni | W1: =+'Umsatzplan Dienstleistungen'!Z1 -> Juli | X1: =+'Umsatzplan Dienstleistungen'!AA1 -> August | ... AB1: =+'Umsatzplan Dienstleistungen'!AE1 -> Dezember | AC1: =+gj+1 -> 2027 | AD1: =+'Umsatzplan Dienstleistungen'!AG1 -> Januar | AE1: =+'Umsatzplan Dienstleistungen'!AH1 -> Februar | AF1: =+'Umsatzplan Dienstleistungen'!AI1 -> März | AG1: =+'Umsatzplan Dienstleistungen'!AJ1 -> April | AH1: =+'Umsatzplan Dienstleistungen'!AK1 -> Mai | AI1: =+'Umsatzplan Dienstleistungen'!AL1 -> Juni | AJ1: =+'Umsatzplan Dienstleistungen'!AM1 -> Juli | AK1: =+'Umsatzplan Dienstleistungen'!AN1 -> August | ... AO1: =+'Umsatzplan Dienstleistungen'!AR1 -> Dezember | AP1: =+gj+2 -> 2028 | AQ1: =+'Umsatzplan Dienstleistungen'!AT1 -> Januar | AR1: =+'Umsatzplan Dienstleistungen'!AU1 -> Februar | AS1: =+'Umsatzplan Dienstleistungen'!AV1 -> März | AT1: =+'Umsatzplan Dienstleistungen'!AW1 -> April | AU1: =+'Umsatzplan Dienstleistungen'!AX1 -> Mai | AV1: =+'Umsatzplan Dienstleistungen'!AY1 -> Juni | AW1: =+'Umsatzplan Dienstleistungen'!AZ1 -> Juli | AX1: =+'Umsatzplan Dienstleistungen'!BA1 -> August | ... BB1: =+'Umsatzplan Dienstleistungen'!BE1 -> Dezember | BC1: =+gj+3 -> 2029
A2: Umsatz Handel/Produktion
B3: =IF('Infos vor dem Start'!A17="x","Umsatz 19%","Umsatz") -> Umsatz 19% | P3: =SUM(D3:O3) -> 0 | AC3: =SUM(Q3:AB3) -> 0 | AP3: =SUM(AD3:AO3) -> 0 | BC3: =SUM(AQ3:BB3) -> 0
B4: =IF('Infos vor dem Start'!A17="x","Umsatz 7%","Umsatz") -> Umsatz 7% | D4: 0 | E4: 0 | F4: 0 | G4: 0 | H4: 0 | I4: 0 | J4: 0 | K4: 0 | L4: 0 | M4: 0 | N4: 0 | O4: 0 | P4: =SUM(D4:O4) -> 0 | AC4: =SUM(Q4:AB4) -> 0 | AP4: =SUM(AD4:AO4) -> 0 | BC4: =SUM(AQ4:BB4) -> 0
A5: =IF(+'Infos vor dem Start'!A17="x","Umsatz Dienstleistungen 19%","Umsatz Dienstleistungen") -> Umsatz Dienstleistungen 19% | D5: =+'Umsatzplan Dienstleistungen'!G44 -> 0 | E5: =+'Umsatzplan Dienstleistungen'!H44 -> 0 | F5: =+'Umsatzplan Dienstleistungen'!I44 -> 0 | G5: =+'Umsatzplan Dienstleistungen'!J44 -> 0 | H5: =+'Umsatzplan Dienstleistungen'!K44 -> 0 | I5: =+'Umsatzplan Dienstleistungen'!L44 -> 0 | J5: =+'Umsatzplan Dienstleistungen'!M44 -> 0 | K5: =+'Umsatzplan Dienstleistungen'!N44 -> 0 | ... O5: =+'Umsatzplan Dienstleistungen'!R44 -> 18000 | P5: =SUM(D5:O5) -> 32000 | Q5: =+'Umsatzplan Dienstleistungen'!T44 -> 0 | R5: =+'Umsatzplan Dienstleistungen'!U44 -> 0 | S5: =+'Umsatzplan Dienstleistungen'!V44 -> 0 | T5: =+'Umsatzplan Dienstleistungen'!W44 -> 0 | U5: =+'Umsatzplan Dienstleistungen'!X44 -> 0 | V5: =+'Umsatzplan Dienstleistungen'!Y44 -> 0 | W5: =+'Umsatzplan Dienstleistungen'!Z44 -> 0 | X5: =+'Umsatzplan Dienstleistungen'!AA44 -> 0 | ... AB5: =+'Umsatzplan Dienstleistungen'!AE44 -> 0 | AC5: =SUM(Q5:AB5) -> 0 | AD5: =+'Umsatzplan Dienstleistungen'!AG44 -> 0 | AE5: =+'Umsatzplan Dienstleistungen'!AH44 -> 0 | AF5: =+'Umsatzplan Dienstleistungen'!AI44 -> 0 | AG5: =+'Umsatzplan Dienstleistungen'!AJ44 -> 0 | AH5: =+'Umsatzplan Dienstleistungen'!AK44 -> 0 | AI5: =+'Umsatzplan Dienstleistungen'!AL44 -> 0 | AJ5: =+'Umsatzplan Dienstleistungen'!AM44 -> 0 | AK5: =+'Umsatzplan Dienstleistungen'!AN44 -> 0 | ... AO5: =+'Umsatzplan Dienstleistungen'!AR44 -> 0 | AP5: =SUM(AD5:AO5) -> 0 | AQ5: =+'Umsatzplan Dienstleistungen'!AT44 -> 0 | AR5: =+'Umsatzplan Dienstleistungen'!AU44 -> 0 | AS5: =+'Umsatzplan Dienstleistungen'!AV44 -> 0 | AT5: =+'Umsatzplan Dienstleistungen'!AW44 -> 0 | AU5: =+'Umsatzplan Dienstleistungen'!AX44 -> 0 | AV5: =+'Umsatzplan Dienstleistungen'!AY44 -> 0 | AW5: =+'Umsatzplan Dienstleistungen'!AZ44 -> 0 | AX5: =+'Umsatzplan Dienstleistungen'!BA44 -> 0 | ... BB5: =+'Umsatzplan Dienstleistungen'!BE44 -> 0 | BC5: =SUM(AQ5:BB5) -> 0
C6: Erlösschmälerungen (Skonto) | D6: =(+D3+D4+D5)*$B6 -> 0 | E6: =(+E3+E4+E5)*$B6 -> 0 | F6: =(+F3+F4+F5)*$B6 -> 0 | G6: =(+G3+G4+G5)*$B6 -> 0 | H6: =(+H3+H4+H5)*$B6 -> 0 | I6: =(+I3+I4+I5)*$B6 -> 0 | J6: =(+J3+J4+J5)*$B6 -> 0 | K6: =(+K3+K4+K5)*$B6 -> 0 | ... O6: =(+O3+O4+O5)*$B6 -> 0 | P6: =SUM(D6:O6) -> 0 | Q6: =(+Q3+Q4+Q5)*$B6 -> 0 | R6: =(+R3+R4+R5)*$B6 -> 0 | S6: =(+S3+S4+S5)*$B6 -> 0 | T6: =(+T3+T4+T5)*$B6 -> 0 | U6: =(+U3+U4+U5)*$B6 -> 0 | V6: =(+V3+V4+V5)*$B6 -> 0 | W6: =(+W3+W4+W5)*$B6 -> 0 | X6: =(+X3+X4+X5)*$B6 -> 0 | ... AB6: =(+AB3+AB4+AB5)*$B6 -> 0 | AC6: =SUM(Q6:AB6) -> 0 | AD6: =(+AD3+AD4+AD5)*$B6 -> 0 | AE6: =(+AE3+AE4+AE5)*$B6 -> 0 | AF6: =(+AF3+AF4+AF5)*$B6 -> 0 | AG6: =(+AG3+AG4+AG5)*$B6 -> 0 | AH6: =(+AH3+AH4+AH5)*$B6 -> 0 | AI6: =(+AI3+AI4+AI5)*$B6 -> 0 | AJ6: =(+AJ3+AJ4+AJ5)*$B6 -> 0 | AK6: =(+AK3+AK4+AK5)*$B6 -> 0 | ... AO6: =(+AO3+AO4+AO5)*$B6 -> 0 | AP6: =SUM(AD6:AO6) -> 0 | AQ6: =(+AQ3+AQ4+AQ5)*$B6 -> 0 | AR6: =(+AR3+AR4+AR5)*$B6 -> 0 | AS6: =(+AS3+AS4+AS5)*$B6 -> 0 | AT6: =(+AT3+AT4+AT5)*$B6 -> 0 | AU6: =(+AU3+AU4+AU5)*$B6 -> 0 | AV6: =(+AV3+AV4+AV5)*$B6 -> 0 | AW6: =(+AW3+AW4+AW5)*$B6 -> 0 | AX6: =(+AX3+AX4+AX5)*$B6 -> 0 | ... BB6: =(+BB3+BB4+BB5)*$B6 -> 0 | BC6: =SUM(AQ6:BB6) -> 0
A7: sonstige betriebliche Erträge | P7: =SUM(D7:O7) -> 0 | AC7: =SUM(Q7:AB7) -> 0 | AP7: =SUM(AD7:AO7) -> 0 | BC7: =SUM(AQ7:BB7) -> 0
A8: Wareneinkauf/Materialaufwand
B9: 0 | C9: pauschaler Wareneinsatz | E9: =(+D3+D4)*$B9 -> 0 | F9: =(+E3+E4)*$B9 -> 0 | G9: =(+F3+F4)*$B9 -> 0 | H9: =(+G3+G4)*$B9 -> 0 | I9: =(+H3+H4)*$B9 -> 0 | J9: =(+I3+I4)*$B9 -> 0 | K9: =(+J3+J4)*$B9 -> 0 | L9: =(+K3+K4)*$B9 -> 0 | ... O9: =(+N3+N4)*$B9 -> 0 | P9: =SUM(D9:O9) -> 0 | Q9: =(+O3+O4)*$B9 -> 0 | R9: =(+Q3+Q4)*$B9 -> 0 | S9: =(+R3+R4)*$B9 -> 0 | T9: =(+S3+S4)*$B9 -> 0 | U9: =(+T3+T4)*$B9 -> 0 | V9: =(+U3+U4)*$B9 -> 0 | W9: =(+V3+V4)*$B9 -> 0 | X9: =(+W3+W4)*$B9 -> 0 | Y9: =(+X3+X4)*$B9 -> 0 | ... AB9: =(+AA3+AA4)*$B9 -> 0 | AC9: =SUM(Q9:AB9) -> 0 | AD9: =(+AB3+AB4)*$B9 -> 0 | AE9: =(+AD3+AD4)*$B9 -> 0 | AF9: =(+AE3+AE4)*$B9 -> 0 | AG9: =(+AF3+AF4)*$B9 -> 0 | AH9: =(+AG3+AG4)*$B9 -> 0 | AI9: =(+AH3+AH4)*$B9 -> 0 | AJ9: =(+AI3+AI4)*$B9 -> 0 | AK9: =(+AJ3+AJ4)*$B9 -> 0 | AL9: =(+AK3+AK4)*$B9 -> 0 | ... AO9: =(+AN3+AN4)*$B9 -> 0 | AP9: =SUM(AD9:AO9) -> 0 | AQ9: =(+AO3+AO4)*$B9 -> 0 | AR9: =(+AQ3+AQ4)*$B9 -> 0 | AS9: =(+AR3+AR4)*$B9 -> 0 | AT9: =(+AS3+AS4)*$B9 -> 0 | AU9: =(+AT3+AT4)*$B9 -> 0 | AV9: =(+AU3+AU4)*$B9 -> 0 | AW9: =(+AV3+AV4)*$B9 -> 0 | AX9: =(+AW3+AW4)*$B9 -> 0 | AY9: =(+AX3+AX4)*$B9 -> 0 | ... BB9: =(+BA3+BA4)*$B9 -> 0 | BC9: =SUM(AQ9:BB9) -> 0
B10: Fremdleistungen | P10: =SUM(D10:O10) -> 0 | AC10: =SUM(Q10:AB10) -> 0 | AP10: =SUM(AD10:AO10) -> 0 | BC10: =SUM(AQ10:BB10) -> 0
B11: Wareneinkauf Saisongeschäft
B12: Warenlager-Erstausstattung und -aufstockung | D12: =IF(Monat=1,Investitionsplan!$C46,0) -> 0 | E12: =IF(Monat=2,Investitionsplan!$C46,0) -> 0 | F12: =IF(Monat=3,Investitionsplan!$C46,0) -> 0 | G12: =IF(Monat=4,Investitionsplan!$C46,0) -> 0 | H12: =IF(Monat=5,Investitionsplan!$C46,0) -> 0 | I12: =IF(Monat=6,Investitionsplan!$C46,0) -> 0 | J12: =IF(Monat=7,Investitionsplan!$C46,0) -> 0 | K12: =IF(Monat=8,Investitionsplan!$C46,0) -> 0 | L12: =IF(Monat=9,Investitionsplan!$C46,0) -> 0 | M12: =IF(Monat=10,Investitionsplan!$C46,0) -> 0 | N12: =IF(Monat=11,Investitionsplan!$C46,0) -> 0 | O12: =IF(Monat=12,Investitionsplan!$C46,0) -> 0 | P12: =SUM(D12:O12) -> 0 | Q12: =+Investitionsplan!E46 -> 0 | AC12: =SUM(Q12:AB12) -> 0 | AD12: =+Investitionsplan!G46 -> 0 | AP12: =SUM(AD12:AO12) -> 0 | AQ12: =+Investitionsplan!I46 -> 0 | BC12: =SUM(AQ12:BB12) -> 0
A13: Rohergebnis | D13: =+D3+D4+D5-D6+D7-D9-D10-D11-D12 -> 0 | E13: =+E3+E4+E5-E6+E7-E9-E10-E11-E12 -> 0 | F13: =+F3+F4+F5-F6+F7-F9-F10-F11-F12 -> 0 | G13: =+G3+G4+G5-G6+G7-G9-G10-G11-G12 -> 0 | H13: =+H3+H4+H5-H6+H7-H9-H10-H11-H12 -> 0 | I13: =+I3+I4+I5-I6+I7-I9-I10-I11-I12 -> 0 | J13: =+J3+J4+J5-J6+J7-J9-J10-J11-J12 -> 0 | K13: =+K3+K4+K5-K6+K7-K9-K10-K11-K12 -> 0 | ... BC13: =+BC3+BC4+BC5-BC6+BC7-BC9-BC10-BC11-BC12 -> 0
A14: Personalaufwand incl. Sozialabgaben (ca. 22%) | M14: 0 | N14: 0 | O14: 0 | P14: =SUM(D14:O14) -> 0 | Q14: 720 | R14: 720 | S14: 720 | T14: 720 | U14: 720 | V14: 720 | W14: 720 | X14: 720 | Y14: 720 | Z14: 720 | AA14: 720 | AB14: 720 | AC14: =SUM(Q14:AB14) -> 8640 | AD14: 0 | AE14: 0 | AF14: 0 | AG14: 0 | AH14: 0 | AI14: 0 | AJ14: 0 | AK14: 0 | AL14: 0 | AM14: 0 | AN14: 0 | AO14: 0 | AP14: =SUM(AD14:AO14) -> 0 | BC14: =SUM(AQ14:BB14) -> 0
A15: Abschreibungen | D15: =IF(Monat<=0,0,IF(Monat=1,ROUND(afaeins,0),)) -> 0 | E15: =IF(Monat=0,0,IF(Monat=2,ROUND(afaeins,0),IF(Monat<2,afaeins,0))) -> 0 | F15: =IF(Monat=0,0,IF(Monat=3,ROUND(afaeins,0),IF(Monat<3,afaeins,0))) -> 0 | G15: =IF(Monat=0,0,IF(Monat=4,ROUND(afaeins,0),IF(Monat<4,afaeins,0))) -> 0 | H15: =IF(Monat=0,0,IF(Monat=5,ROUND(afaeins,0),IF(Monat<5,afaeins,0))) -> 0 | I15: =IF(Monat=0,0,IF(Monat=6,ROUND(afaeins,0),IF(Monat<6,afaeins,0))) -> 0 | J15: =IF(Monat=0,0,IF(Monat=7,ROUND(afaeins,0),IF(Monat<7,afaeins,0))) -> 0 | K15: =IF(Monat=0,0,IF(Monat=8,ROUND(afaeins,0),IF(Monat<8,afaeins,0))) -> 0 | L15: =IF(Monat=0,0,IF(Monat=9,ROUND(afaeins,0),IF(Monat<9,afaeins,0))) -> 0 | M15: =IF(Monat=0,0,IF(Monat=10,ROUND(afaeins,0),IF(Monat<10,afaeins,0))) -> 0 | N15: =IF(Monat=0,0,IF(Monat=11,ROUND(afaeins,0),IF(Monat<11,afaeins,0))) -> 0 | O15: =IF(Monat=0,0,IF(Monat=11,ROUND(afaeins,0),IF(Monat<11,afaeins,0))) -> 0 | P15: =SUM(D15:O15) -> 0 | Q15: =+afazwei -> 0 | R15: =+afazwei -> 0 | S15: =+afazwei -> 0 | T15: =+afazwei -> 0 | U15: =+afazwei -> 0 | V15: =+afazwei -> 0 | W15: =+afazwei -> 0 | X15: =+afazwei -> 0 | ... AB15: =+afazwei -> 0 | AC15: =SUM(Q15:AB15) -> 0 | AD15: =+afadrei -> 0 | AE15: =+afadrei -> 0 | AF15: =+afadrei -> 0 | AG15: =+afadrei -> 0 | AH15: =+afadrei -> 0 | AI15: =+afadrei -> 0 | AJ15: =+afadrei -> 0 | AK15: =+afadrei -> 0 | ... AO15: =+afadrei -> 0 | AP15: =SUM(AD15:AO15) -> 0 | AQ15: =+afavier -> 0 | AR15: =+afavier -> 0 | AS15: =+afavier -> 0 | AT15: =+afavier -> 0 | AU15: =+afavier -> 0 | AV15: =+afavier -> 0 | AW15: =+afavier -> 0 | AX15: =+afavier -> 0 | ... BB15: =+afavier -> 0 | BC15: =SUM(AQ15:BB15) -> 0
A16: Sonstige betriebliche Aufwendungen
B17: Raumkosten (Miete, Nebenkosten, Reinigung etc.)
C18: Miete und Nebenkosten | D18: 0 | E18: 0 | F18: 0 | G18: 0 | H18: 0 | I18: 0 | J18: 0 | K18: 0 | L18: 0 | M18: 600 | N18: 600 | O18: 600 | P18: =SUM(D18:O18) -> 1800 | Q18: 600 | R18: 600 | S18: 600 | T18: 600 | U18: 600 | V18: 600 | W18: 600 | X18: 600 | Y18: 600 | Z18: 600 | AA18: 600 | AB18: 600 | AC18: =SUM(Q18:AB18) -> 7200 | AD18: 0 | AE18: 0 | AF18: 0 | AG18: 0 | AH18: 0 | AI18: 0 | AJ18: 0 | AK18: 0 | AL18: 0 | AM18: 0 | AN18: 0 | AO18: 0 | AP18: =SUM(AD18:AO18) -> 0 | BC18: =SUM(AQ18:BB18) -> 0
C19: Instandhaltung | D19: 0 | E19: 0 | F19: 0 | G19: 0 | H19: 0 | I19: 0 | J19: 0 | K19: 0 | L19: 0 | M19: 50 | N19: 50 | O19: 50 | P19: =SUM(D19:O19) -> 150 | Q19: 50 | R19: 50 | S19: 50 | T19: 50 | U19: 50 | V19: 50 | W19: 50 | X19: 50 | Y19: 50 | Z19: 50 | AA19: 50 | AB19: 50 | AC19: =SUM(Q19:AB19) -> 600 | AD19: 0 | AE19: 0 | AF19: 0 | AG19: 0 | AH19: 0 | AI19: 0 | AJ19: 0 | AK19: 0 | AL19: 0 | AM19: 0 | AN19: 0 | AO19: 0 | AP19: =SUM(AD19:AO19) -> 0 | BC19: =SUM(AQ19:BB19) -> 0
B20: Telefon, Fax | D20: 0 | E20: 0 | F20: 0 | G20: 0 | H20: 0 | I20: 0 | J20: 0 | K20: 0 | L20: 0 | M20: 100 | N20: 100 | O20: 100 | P20: =SUM(D20:O20) -> 300 | Q20: 100 | R20: 100 | S20: 100 | T20: 100 | U20: 100 | V20: 100 | W20: 100 | X20: 100 | Y20: 100 | Z20: 100 | AA20: 100 | AB20: 100 | AC20: =SUM(Q20:AB20) -> 1200 | AD20: 0 | AE20: 0 | AF20: 0 | AG20: 0 | AH20: 0 | AI20: 0 | AJ20: 0 | AK20: 0 | AL20: 0 | AM20: 0 | AN20: 0 | AO20: 0 | AP20: =SUM(AD20:AO20) -> 0 | BC20: =SUM(AQ20:BB20) -> 0
B21: Kfz-Kosten
C22: Kfz-Versicherungen | D22: 0 | E22: 0 | F22: 0 | G22: 0 | H22: 0 | I22: 0 | J22: 0 | K22: 0 | L22: 0 | M22: 0 | N22: 0 | O22: 0 | P22: =SUM(D22:O22) -> 0 | Q22: 0 | R22: 0 | S22: 0 | T22: 0 | U22: 0 | V22: 0 | W22: 0 | X22: 0 | Y22: 0 | Z22: 0 | AA22: 0 | AB22: 0 | AC22: =SUM(Q22:AB22) -> 0 | AD22: 0 | AE22: 0 | AF22: 0 | AG22: 0 | AH22: 0 | AI22: 0 | AJ22: 0 | AK22: 0 | AL22: 0 | AM22: 0 | AN22: 0 | AO22: 0 | AP22: =SUM(AD22:AO22) -> 0 | BC22: =SUM(AQ22:BB22) -> 0
C23: Wartung und Reparatur | D23: 0 | E23: 0 | F23: 0 | G23: 0 | H23: 0 | I23: 0 | J23: 0 | K23: 0 | L23: 0 | M23: 0 | N23: 0 | O23: 0 | P23: =SUM(D23:O23) -> 0 | Q23: 0 | R23: 0 | S23: 0 | T23: 0 | U23: 0 | V23: 0 | W23: 0 | X23: 0 | Y23: 0 | Z23: 0 | AA23: 0 | AB23: 0 | AC23: =SUM(Q23:AB23) -> 0 | AD23: 0 | AE23: 0 | AF23: 0 | AG23: 0 | AH23: 0 | AI23: 0 | AJ23: 0 | AK23: 0 | AL23: 0 | AM23: 0 | AN23: 0 | AO23: 0 | AP23: =SUM(AD23:AO23) -> 0 | BC23: =SUM(AQ23:BB23) -> 0
C24: Leasing (nur Kfz) | D24: 0 | E24: 0 | F24: 0 | G24: 0 | H24: 0 | I24: 0 | J24: 0 | K24: 0 | L24: 0 | M24: 0 | N24: 0 | O24: 0 | P24: =SUM(D24:O24) -> 0 | Q24: 0 | R24: 0 | S24: 0 | T24: 0 | U24: 0 | V24: 0 | W24: 0 | X24: 0 | Y24: 0 | Z24: 0 | AA24: 0 | AB24: 0 | AC24: =SUM(Q24:AB24) -> 0 | AD24: 0 | AE24: 0 | AF24: 0 | AG24: 0 | AH24: 0 | AI24: 0 | AJ24: 0 | AK24: 0 | AL24: 0 | AM24: 0 | AN24: 0 | AO24: 0 | AP24: =SUM(AD24:AO24) -> 0 | BC24: =SUM(AQ24:BB24) -> 0
C25: Betriebskosten | D25: 0 | E25: 0 | F25: 0 | G25: 0 | H25: 0 | I25: 0 | J25: 0 | K25: 0 | L25: 0 | M25: 0 | N25: 0 | O25: 0 | P25: =SUM(D25:O25) -> 0 | Q25: 0 | R25: 0 | S25: 0 | T25: 0 | U25: 0 | V25: 0 | W25: 0 | X25: 0 | Y25: 0 | Z25: 0 | AA25: 0 | AB25: 0 | AC25: =SUM(Q25:AB25) -> 0 | AD25: =AB25*1.05 -> 0 | AE25: =AC25*1.05 -> 0 | AF25: =AD25*1.05 -> 0 | AG25: =AE25*1.05 -> 0 | AH25: =AF25*1.05 -> 0 | AI25: =AG25*1.05 -> 0 | AJ25: =AH25*1.05 -> 0 | AK25: =AI25*1.05 -> 0 | AL25: =AJ25*1.05 -> 0 | AM25: 0 | AN25: 0 | AO25: 0 | AP25: =SUM(AD25:AO25) -> 0 | BC25: =SUM(AQ25:BB25) -> 0
B26: Reise- und Bewirtungskosten | D26: 0 | E26: 0 | F26: 0 | G26: 0 | H26: 0 | I26: 0 | J26: 0 | K26: 0 | L26: 0 | M26: 300 | N26: 300 | O26: 300 | P26: =SUM(D26:O26) -> 900 | Q26: 300 | R26: 300 | S26: 300 | T26: 300 | U26: 300 | V26: 300 | W26: 300 | X26: 300 | Y26: 300 | Z26: 300 | AA26: 300 | AB26: 300 | AC26: =SUM(Q26:AB26) -> 3600 | AD26: 0 | AE26: 0 | AF26: 0 | AG26: 0 | AH26: 0 | AI26: 0 | AJ26: 0 | AK26: 0 | AL26: 0 | AM26: 0 | AN26: 0 | AO26: 0 | AP26: =SUM(AD26:AO26) -> 0 | BC26: =SUM(AQ26:BB26) -> 0
B27: Anzeigen- und sonst. Werbung | D27: 0 | E27: 0 | F27: 0 | G27: 0 | H27: 0 | I27: 0 | J27: 0 | K27: 0 | L27: 0 | M27: 100 | N27: 100 | O27: 100 | P27: =SUM(D27:O27) -> 300 | Q27: 100 | R27: 100 | S27: 100 | T27: 100 | U27: 100 | V27: 100 | W27: 100 | X27: 100 | Y27: 100 | Z27: 100 | AA27: 100 | AB27: 100 | AC27: =SUM(Q27:AB27) -> 1200 | AD27: 0 | AE27: 0 | AF27: 0 | AG27: 0 | AH27: 0 | AI27: 0 | AJ27: 0 | AK27: 0 | AL27: 0 | AM27: 0 | AN27: 0 | AO27: 0 | AP27: =SUM(AD27:AO27) -> 0 | BC27: =SUM(AQ27:BB27) -> 0
B28: Kosten der Warenabgabe
C29: Verpackung/Ausgangsfrachten | D29: 0 | E29: 0 | F29: 0 | G29: 0 | H29: 0 | I29: 0 | J29: 0 | K29: 0 | L29: 0 | M29: 0 | N29: 0 | O29: 0 | P29: =SUM(D29:O29) -> 0 | Q29: 0 | R29: 0 | S29: 0 | T29: 0 | U29: 0 | V29: 0 | W29: 0 | X29: 0 | Y29: 0 | Z29: 0 | AA29: 0 | AB29: 0 | AC29: =SUM(Q29:AB29) -> 0 | AD29: 0 | AE29: 0 | AF29: 0 | AG29: 0 | AH29: 0 | AI29: 0 | AJ29: 0 | AK29: 0 | AL29: 0 | AM29: 0 | AN29: 0 | AO29: 0 | AP29: =SUM(AD29:AO29) -> 0 | BC29: =SUM(AQ29:BB29) -> 0
C30: Provisionen | D30: 0 | E30: 0 | F30: 0 | G30: 0 | H30: 0 | I30: 0 | J30: 0 | K30: 0 | L30: 0 | M30: 0 | N30: 0 | O30: 0 | P30: =SUM(D30:O30) -> 0 | Q30: 0 | R30: 0 | S30: 0 | T30: 0 | U30: 0 | V30: 0 | W30: 0 | X30: 0 | Y30: 0 | Z30: 0 | AA30: 0 | AB30: 0 | AC30: =SUM(Q30:AB30) -> 0 | AD30: 0 | AE30: 0 | AF30: 0 | AG30: 0 | AH30: 0 | AI30: 0 | AJ30: 0 | AK30: 0 | AL30: 0 | AM30: 0 | AN30: 0 | AO30: 0 | AP30: =SUM(AD30:AO30) -> 0 | BC30: =SUM(AQ30:BB30) -> 0
B31: Instandhaltung Betriebs- und Geschäftsausstattung | D31: 0 | E31: 0 | F31: 0 | G31: 0 | H31: 0 | I31: 0 | J31: 0 | K31: 0 | L31: 0 | M31: 0 | N31: 0 | O31: 0 | P31: =SUM(D31:O31) -> 0 | Q31: 0 | R31: 0 | S31: 0 | T31: 0 | U31: 0 | V31: 0 | W31: 0 | X31: 0 | Y31: 0 | Z31: 0 | AA31: 0 | AB31: 0 | AC31: =SUM(Q31:AB31) -> 0 | AD31: 0 | AE31: 0 | AF31: 0 | AG31: 0 | AH31: 0 | AI31: 0 | AJ31: 0 | AK31: 0 | AL31: 0 | AM31: 0 | AN31: 0 | AO31: 0 | AP31: =SUM(AD31:AO31) -> 0 | BC31: =SUM(AQ31:BB31) -> 0
B32: Leasing (außer Kfz) | D32: 0 | E32: 0 | F32: 0 | G32: 0 | H32: 0 | I32: 0 | J32: 0 | K32: 0 | L32: 0 | M32: 0 | N32: 0 | O32: 0 | P32: =SUM(D32:O32) -> 0 | Q32: 0 | R32: 0 | S32: 0 | T32: 0 | U32: 0 | V32: 0 | W32: 0 | X32: 0 | Y32: 0 | Z32: 0 | AA32: 0 | AB32: 0 | AC32: =SUM(Q32:AB32) -> 0 | AD32: 0 | AE32: 0 | AF32: 0 | AG32: 0 | AH32: 0 | AI32: 0 | AJ32: 0 | AK32: 0 | AL32: 0 | AM32: 0 | AN32: 0 | AO32: 0 | AP32: =SUM(AD32:AO32) -> 0 | BC32: =SUM(AQ32:BB32) -> 0
B33: Software-Updates | D33: 0 | E33: 0 | F33: 0 | G33: 0 | H33: 0 | I33: 0 | J33: 0 | K33: 0 | L33: 0 | M33: 40 | N33: 40 | O33: 40 | P33: =SUM(D33:O33) -> 120 | Q33: 40 | R33: 40 | S33: 40 | T33: 40 | U33: 40 | V33: 40 | W33: 40 | X33: 40 | Y33: 40 | Z33: 40 | AA33: 40 | AB33: 40 | AC33: =SUM(Q33:AB33) -> 480 | AD33: 0 | AE33: 0 | AF33: 0 | AG33: 0 | AH33: 0 | AI33: 0 | AJ33: 0 | AK33: 0 | AL33: 0 | AM33: 0 | AN33: 0 | AO33: 0 | AP33: =SUM(AD33:AO33) -> 0 | BC33: =SUM(AQ33:BB33) -> 0
B34: Versicherungen (ohne Kfz) | D34: 0 | E34: 0 | F34: 0 | G34: 0 | H34: 0 | I34: 0 | J34: 0 | K34: 0 | L34: 0 | M34: 40 | N34: 40 | O34: 40 | P34: =SUM(D34:O34) -> 120 | Q34: 40 | R34: 40 | S34: 40 | T34: 40 | U34: 40 | V34: 40 | W34: 40 | X34: 40 | Y34: 40 | Z34: 40 | AA34: 40 | AB34: 40 | AC34: =SUM(Q34:AB34) -> 480 | AD34: 0 | AE34: 0 | AF34: 0 | AG34: 0 | AH34: 0 | AI34: 0 | AJ34: 0 | AK34: 0 | AL34: 0 | AM34: 0 | AN34: 0 | AO34: 0 | AP34: =SUM(AD34:AO34) -> 0 | BC34: =SUM(AQ34:BB34) -> 0
B35: Beiträge, Gebühren | D35: 0 | E35: 0 | F35: 0 | G35: 0 | H35: 0 | I35: 0 | J35: 0 | K35: 0 | L35: 0 | M35: 15 | N35: 15 | O35: 15 | P35: =SUM(D35:O35) -> 45 | Q35: 15 | R35: 15 | S35: 15 | T35: 15 | U35: 15 | V35: 15 | W35: 15 | X35: 15 | Y35: 15 | Z35: 15 | AA35: 15 | AB35: 15 | AC35: =SUM(Q35:AB35) -> 180 | AD35: 0 | AE35: 0 | AF35: 0 | AG35: 0 | AH35: 0 | AI35: 0 | AJ35: 0 | AK35: 0 | AL35: 0 | AM35: 0 | AN35: 0 | AO35: 0 | AP35: =SUM(AD35:AO35) -> 0 | BC35: =SUM(AQ35:BB35) -> 0
B36: Bürobedarf | D36: 0 | E36: 0 | F36: 0 | G36: 0 | H36: 0 | I36: 0 | J36: 0 | K36: 0 | L36: 0 | M36: 30 | N36: 30 | O36: 30 | P36: =SUM(D36:O36) -> 90 | Q36: 30 | R36: 30 | S36: 30 | T36: 30 | U36: 30 | V36: 30 | W36: 30 | X36: 30 | Y36: 30 | Z36: 30 | AA36: 30 | AB36: 30 | AC36: =SUM(Q36:AB36) -> 360 | AD36: 0 | AE36: 0 | AF36: 0 | AG36: 0 | AH36: 0 | AI36: 0 | AJ36: 0 | AK36: 0 | AL36: 0 | AM36: 0 | AN36: 0 | AO36: 0 | AP36: =SUM(AD36:AO36) -> 0 | BC36: =SUM(AQ36:BB36) -> 0
B37: Postwertzeichen | D37: 0 | E37: 0 | F37: 0 | G37: 0 | H37: 0 | I37: 0 | J37: 0 | K37: 0 | L37: 0 | M37: 10 | N37: 10 | O37: 10 | P37: =SUM(D37:O37) -> 30 | Q37: 10 | R37: 10 | S37: 10 | T37: 10 | U37: 10 | V37: 10 | W37: 10 | X37: 10 | Y37: 10 | Z37: 10 | AA37: 10 | AB37: 10 | AC37: =SUM(Q37:AB37) -> 120 | AD37: 0 | AE37: 0 | AF37: 0 | AG37: 0 | AH37: 0 | AI37: 0 | AJ37: 0 | AK37: 0 | AL37: 0 | AM37: 0 | AN37: 0 | AO37: 0 | AP37: =SUM(AD37:AO37) -> 0 | BC37: =SUM(AQ37:BB37) -> 0
B38: Fachliteratur | D38: 0 | E38: 0 | F38: 0 | G38: 0 | H38: 0 | I38: 0 | J38: 0 | K38: 0 | L38: 0 | M38: 20 | N38: 20 | O38: 20 | P38: =SUM(D38:O38) -> 60 | Q38: 20 | R38: 20 | S38: 20 | T38: 20 | U38: 20 | V38: 20 | W38: 20 | X38: 20 | Y38: 20 | Z38: 20 | AA38: 20 | AB38: 20 | AC38: =SUM(Q38:AB38) -> 240 | AD38: 0 | AE38: 0 | AF38: 0 | AG38: 0 | AH38: 0 | AI38: 0 | AJ38: 0 | AK38: 0 | AL38: 0 | AM38: 0 | AN38: 0 | AO38: 0 | AP38: =SUM(AD38:AO38) -> 0 | BC38: =SUM(AQ38:BB38) -> 0
B39: Fortbildung | D39: 0 | E39: 0 | F39: 0 | G39: 0 | H39: 0 | I39: 0 | J39: 0 | K39: 0 | L39: 0 | M39: 0 | N39: 0 | O39: 0 | P39: =SUM(D39:O39) -> 0 | Q39: 0 | R39: 0 | S39: 0 | T39: 0 | U39: 0 | V39: 0 | W39: 0 | X39: 0 | Y39: 0 | Z39: 0 | AA39: 0 | AB39: 0 | AC39: =SUM(Q39:AB39) -> 0 | AD39: 0 | AE39: 0 | AF39: 0 | AG39: 0 | AH39: 0 | AI39: 0 | AJ39: 0 | AK39: 0 | AL39: 0 | AM39: 0 | AN39: 0 | AO39: 0 | AP39: =SUM(AD39:AO39) -> 0 | BC39: =SUM(AQ39:BB39) -> 0
B40: Messen und Ausstellungen | D40: 0 | E40: 0 | F40: 0 | G40: 0 | H40: 0 | I40: 0 | J40: 0 | K40: 0 | L40: 0 | M40: 0 | N40: 0 | O40: 0 | P40: =SUM(D40:O40) -> 0 | Q40: 0 | R40: 0 | S40: 0 | T40: 0 | U40: 0 | V40: 0 | W40: 0 | X40: 0 | Y40: 0 | Z40: 0 | AA40: 0 | AB40: 0 | AC40: =SUM(Q40:AB40) -> 0 | AD40: 0 | AE40: 0 | AF40: 0 | AG40: 0 | AH40: 0 | AI40: 0 | AJ40: 0 | AK40: 0 | AL40: 0 | AM40: 0 | AN40: 0 | AO40: 0 | AP40: =SUM(AD40:AO40) -> 0 | BC40: =SUM(AQ40:BB40) -> 0
B41: Beratungskosten
C42: Steuerberater | D42: 0 | E42: 0 | F42: 0 | G42: 0 | H42: 0 | I42: 0 | J42: 0 | K42: 0 | L42: 0 | M42: 150 | N42: 150 | O42: 150 | P42: =SUM(D42:O42) -> 450 | Q42: 150 | R42: 150 | S42: 150 | T42: 150 | U42: 150 | V42: 150 | W42: 150 | X42: 150 | Y42: 150 | Z42: 150 | AA42: 150 | AB42: 150 | AC42: =SUM(Q42:AB42) -> 1800 | AD42: 0 | AE42: 0 | AF42: 0 | AG42: 0 | AH42: 0 | AI42: 0 | AJ42: 0 | AK42: 0 | AL42: 0 | AM42: 0 | AN42: 0 | AO42: 0 | AP42: =SUM(AD42:AO42) -> 0 | BC42: =SUM(AQ42:BB42) -> 0
C43: Unternehmensberater | D43: 0 | E43: 0 | F43: 0 | G43: 0 | H43: 0 | I43: 0 | J43: 0 | K43: 0 | L43: 0 | M43: 0 | N43: 0 | O43: 0 | P43: =SUM(D43:O43) -> 0 | Q43: 0 | R43: 0 | S43: 0 | T43: 0 | U43: 0 | V43: 0 | W43: 0 | X43: 0 | Y43: 0 | Z43: 0 | AA43: 0 | AB43: 0 | AC43: =SUM(Q43:AB43) -> 0 | AD43: 0 | AE43: 0 | AF43: 0 | AG43: 0 | AH43: 0 | AI43: 0 | AJ43: 0 | AK43: 0 | AL43: 0 | AM43: 0 | AN43: 0 | AO43: 0 | AP43: =SUM(AD43:AO43) -> 0 | BC43: =SUM(AQ43:BB43) -> 0
C44: Rechtsanwalt | D44: 0 | E44: 0 | F44: 0 | G44: 0 | H44: 0 | I44: 0 | J44: 0 | K44: 0 | L44: 0 | M44: 0 | N44: 0 | O44: 0 | P44: =SUM(D44:O44) -> 0 | Q44: 0 | R44: 0 | S44: 0 | T44: 0 | U44: 0 | V44: 0 | W44: 0 | X44: 0 | Y44: 0 | Z44: 0 | AA44: 0 | AB44: 0 | AC44: =SUM(Q44:AB44) -> 0 | AD44: 0 | AE44: 0 | AF44: 0 | AG44: 0 | AH44: 0 | AI44: 0 | AJ44: 0 | AK44: 0 | AL44: 0 | AM44: 0 | AN44: 0 | AO44: 0 | AP44: =SUM(AD44:AO44) -> 0 | BC44: =SUM(AQ44:BB44) -> 0
B45: Kosten des Geldverkehrs | D45: 0 | E45: 0 | F45: 0 | G45: 0 | H45: 0 | I45: 0 | J45: 0 | K45: 0 | L45: 0 | M45: 20 | N45: 20 | O45: 20 | P45: =SUM(D45:O45) -> 60 | Q45: 20 | R45: 20 | S45: 20 | T45: 20 | U45: 20 | V45: 20 | W45: 20 | X45: 20 | Y45: 20 | Z45: 20 | AA45: 20 | AB45: 20 | AC45: =SUM(Q45:AB45) -> 240 | AD45: 0 | AE45: 0 | AF45: 0 | AG45: 0 | AH45: 0 | AI45: 0 | AJ45: 0 | AK45: 0 | AL45: 0 | AM45: 0 | AN45: 0 | AO45: 0 | AP45: =SUM(AD45:AO45) -> 0 | BC45: =SUM(AQ45:BB45) -> 0
B46: Andere betriebliche Aufwendungen | K46: 0 | L46: 0 | M46: 0 | N46: 0 | O46: 0 | P46: =SUM(D46:O46) -> 0 | Q46: 0 | R46: 0 | S46: 0 | T46: 0 | U46: 0 | V46: 0 | W46: 0 | X46: 0 | Y46: 0 | Z46: 0 | AA46: 0 | AB46: 0 | AC46: =SUM(Q46:AB46) -> 0 | AD46: 0 | AE46: 0 | AF46: 0 | AG46: 0 | AH46: 0 | AI46: 0 | AJ46: 0 | AK46: 0 | AL46: 0 | AM46: 0 | AN46: 0 | AO46: 0 | AP46: =SUM(AD46:AO46) -> 0 | BC46: =SUM(AQ46:BB46) -> 0
A47: Summe betrieblicher Aufwendungen | D47: =SUM(D14:D46) -> 0 | E47: =SUM(E14:E46) -> 0 | F47: =SUM(F14:F46) -> 0 | G47: =SUM(G14:G46) -> 0 | H47: =SUM(H14:H46) -> 0 | I47: =SUM(I14:I46) -> 0 | J47: =SUM(J14:J46) -> 0 | K47: =SUM(K14:K46) -> 0 | ... BC47: =SUM(BC14:BC46) -> 0
A48: Betriebsergebnis | D48: =+D13-D47 -> 0 | E48: =+E13-E47 -> 0 | F48: =+F13-F47 -> 0 | G48: =+G13-G47 -> 0 | H48: =+H13-H47 -> 0 | I48: =+I13-I47 -> 0 | J48: =+J13-J47 -> 0 | K48: =+K13-K47 -> 0 | ... BC48: =+BC13-BC47 -> 0
A49: Zinsaufwendungen 1) | P49: =SUM(D49:O49) -> 0 | AC49: =SUM(Q49:AB49) -> 0 | AP49: =SUM(AD49:AO49) -> 0 | BC49: =SUM(AQ49:BB49) -> 0
A50: Gewinn/Verlust vor Steuern | D50: =+D48-D49 -> 0 | E50: =+E48-E49 -> 0 | F50: =+F48-F49 -> 0 | G50: =+G48-G49 -> 0 | H50: =+H48-H49 -> 0 | I50: =+I48-I49 -> 0 | J50: =+J48-J49 -> 0 | K50: =+K48-K49 -> 0 | ... BC50: =+BC48-BC49 -> 0
A51: Sonstige Steuern (betrieblich) | P51: =SUM(D51:O51) -> 0 | AC51: =SUM(Q51:AB51) -> 0 | AP51: =SUM(AD51:AO51) -> 0 | BC51: =SUM(AQ51:BB51) -> 0
A52: Jahresüberschuß/Jahresfehlbetrag | D52: =+D50-D51 -> 0 | E52: =+E50-E51 -> 0 | F52: =+F50-F51 -> 0 | G52: =+G50-G51 -> 0 | H52: =+H50-H51 -> 0 | I52: =+I50-I51 -> 0 | J52: =+J50-J51 -> 0 | K52: =+K50-K51 -> 0 | ... BC52: =+BC50-BC51 -> 0
A54: 1) | B54: gem. Zins- und Tilgungsplan des Kreditinstituts für alle betrieblichen Darlehen

Sheet Liquiditätsplan
D1: =+'Umsatzplan Dienstleistungen'!G1 -> Januar | E1: =+'Umsatzplan Dienstleistungen'!H1 -> Februar | F1: =+'Umsatzplan Dienstleistungen'!I1 -> März | G1: =+'Umsatzplan Dienstleistungen'!J1 -> April | H1: =+'Umsatzplan Dienstleistungen'!K1 -> Mai | I1: =+'Umsatzplan Dienstleistungen'!L1 -> Juni | J1: =+'Umsatzplan Dienstleistungen'!M1 -> Juli | K1: =+'Umsatzplan Dienstleistungen'!N1 -> August | ... O1: =+'Umsatzplan Dienstleistungen'!R1 -> Dezember | P1: =+gj -> 2026 | Q1: =+'Umsatzplan Dienstleistungen'!T1 -> Januar | R1: =+'Umsatzplan Dienstleistungen'!U1 -> Februar | S1: =+'Umsatzplan Dienstleistungen'!V1 -> März | T1: =+'Umsatzplan Dienstleistungen'!W1 -> April | U1: =+'Umsatzplan Dienstleistungen'!X1 -> Mai | V1: =+'Umsatzplan Dienstleistungen'!Y1 -> Juni | W1: =+'Umsatzplan Dienstleistungen'!Z1 -> Juli | X1: =+'Umsatzplan Dienstleistungen'!AA1 -> August | ... AB1: =+'Umsatzplan Dienstleistungen'!AE1 -> Dezember | AC1: =+gj+1 -> 2027 | AD1: =+'Umsatzplan Dienstleistungen'!AG1 -> Januar | AE1: =+'Umsatzplan Dienstleistungen'!AH1 -> Februar | AF1: =+'Umsatzplan Dienstleistungen'!AI1 -> März | AG1: =+'Umsatzplan Dienstleistungen'!AJ1 -> April | AH1: =+'Umsatzplan Dienstleistungen'!AK1 -> Mai | AI1: =+'Umsatzplan Dienstleistungen'!AL1 -> Juni | AJ1: =+'Umsatzplan Dienstleistungen'!AM1 -> Juli | AK1: =+'Umsatzplan Dienstleistungen'!AN1 -> August | ... AO1: =+'Umsatzplan Dienstleistungen'!AR1 -> Dezember | AP1: =+gj+2 -> 2028 | AQ1: =+'Umsatzplan Dienstleistungen'!AT1 -> Januar | AR1: =+'Umsatzplan Dienstleistungen'!AU1 -> Februar | AS1: =+'Umsatzplan Dienstleistungen'!AV1 -> März | AT1: =+'Umsatzplan Dienstleistungen'!AW1 -> April | AU1: =+'Umsatzplan Dienstleistungen'!AX1 -> Mai | AV1: =+'Umsatzplan Dienstleistungen'!AY1 -> Juni | AW1: =+'Umsatzplan Dienstleistungen'!AZ1 -> Juli | AX1: =+'Umsatzplan Dienstleistungen'!BA1 -> August | ... BB1: =+'Umsatzplan Dienstleistungen'!BE1 -> Dezember | BC1: =+gj+3 -> 2029
A2: Zahlungseingänge auf gebuchten Umsatz
B3: =IF('Infos vor dem Start'!$A$17="x","Bruttoumsatz Handel/Dienstleistungen","Umsatz Handel/Dienstleistungen") -> Bruttoumsatz Handel/Dienstleistungen
C4: =IF('Infos vor dem Start'!$A$17="x","Bruttoumsatz 19%","Umsatz") -> Bruttoumsatz 19% | D4: =IF(rechnung="x",0,+Rentabilitätsvorschau!D3*(1+USteins)) -> 0 | E4: =IF(rechnung="x",+Rentabilitätsvorschau!D3*(1+USteins),+Rentabilitätsvorschau!E3*(1+USteins)) -> 0 | F4: =IF(rechnung="x",+Rentabilitätsvorschau!E3*(1+USteins),+Rentabilitätsvorschau!F3*(1+USteins)) -> 0 | G4: =IF(rechnung="x",+Rentabilitätsvorschau!F3*(1+USteins),+Rentabilitätsvorschau!G3*(1+USteins)) -> 0 | H4: =IF(rechnung="x",+Rentabilitätsvorschau!G3*(1+USteins),+Rentabilitätsvorschau!H3*(1+USteins)) -> 0 | I4: =IF(rechnung="x",+Rentabilitätsvorschau!H3*(1+USteins),+Rentabilitätsvorschau!I3*(1+USteins)) -> 0 | J4: =IF(rechnung="x",+Rentabilitätsvorschau!I3*(1+USteins),+Rentabilitätsvorschau!J3*(1+USteins)) -> 0 | K4: =IF(rechnung="x",+Rentabilitätsvorschau!J3*(1+USteins),+Rentabilitätsvorschau!K3*(1+USteins)) -> 0 | L4: =IF(rechnung="x",+Rentabilitätsvorschau!K3*(1+USteins),+Rentabilitätsvorschau!L3*(1+USteins)) -> 0 | ... O4: =IF(rechnung="x",+Rentabilitätsvorschau!N3*(1+USteins),+Rentabilitätsvorschau!O3*(1+USteins)) -> 0 | P4: =SUM(D4:O4) -> 0 | Q4: =IF(rechnung="x",+Rentabilitätsvorschau!O3*(1+USteins),+Rentabilitätsvorschau!Q3*(1+USt)) -> 0 | R4: =IF(rechnung="x",+Rentabilitätsvorschau!Q3*(1+USt),+Rentabilitätsvorschau!R3*(1+USt)) -> 0 | S4: =IF(rechnung="x",+Rentabilitätsvorschau!R3*(1+USt),+Rentabilitätsvorschau!S3*(1+USt)) -> 0 | T4: =IF(rechnung="x",+Rentabilitätsvorschau!S3*(1+USt),+Rentabilitätsvorschau!T3*(1+USt)) -> 0 | U4: =IF(rechnung="x",+Rentabilitätsvorschau!T3*(1+USt),+Rentabilitätsvorschau!U3*(1+USt)) -> 0 | V4: =IF(rechnung="x",+Rentabilitätsvorschau!U3*(1+USt),+Rentabilitätsvorschau!V3*(1+USt)) -> 0 | W4: =IF(rechnung="x",+Rentabilitätsvorschau!V3*(1+USt),+Rentabilitätsvorschau!W3*(1+USt)) -> 0 | X4: =IF(rechnung="x",+Rentabilitätsvorschau!W3*(1+USt),+Rentabilitätsvorschau!X3*(1+USt)) -> 0 | Y4: =IF(rechnung="x",+Rentabilitätsvorschau!X3*(1+USt),+Rentabilitätsvorschau!Y3*(1+USt)) -> 0 | ... AB4: =IF(rechnung="x",+Rentabilitätsvorschau!AA3*(1+USt),+Rentabilitätsvorschau!AB3*(1+USt)) -> 0 | AC4: =SUM(Q4:AB4) -> 0 | AD4: =IF(rechnung="x",+Rentabilitätsvorschau!AB3*(1+USt),+Rentabilitätsvorschau!AD3*(1+USt)) -> 0 | AE4: =IF(rechnung="x",+Rentabilitätsvorschau!AD3*(1+USt),+Rentabilitätsvorschau!AE3*(1+USt)) -> 0 | AF4: =IF(rechnung="x",+Rentabilitätsvorschau!AE3*(1+USt),+Rentabilitätsvorschau!AF3*(1+USt)) -> 0 | AG4: =IF(rechnung="x",+Rentabilitätsvorschau!AF3*(1+USt),+Rentabilitätsvorschau!AG3*(1+USt)) -> 0 | AH4: =IF(rechnung="x",+Rentabilitätsvorschau!AG3*(1+USt),+Rentabilitätsvorschau!AH3*(1+USt)) -> 0 | AI4: =IF(rechnung="x",+Rentabilitätsvorschau!AH3*(1+USt),+Rentabilitätsvorschau!AI3*(1+USt)) -> 0 | AJ4: =IF(rechnung="x",+Rentabilitätsvorschau!AI3*(1+USt),+Rentabilitätsvorschau!AJ3*(1+USt)) -> 0 | AK4: =IF(rechnung="x",+Rentabilitätsvorschau!AJ3*(1+USt),+Rentabilitätsvorschau!AK3*(1+USt)) -> 0 | AL4: =IF(rechnung="x",+Rentabilitätsvorschau!AK3*(1+USt),+Rentabilitätsvorschau!AL3*(1+USt)) -> 0 | ... AO4: =IF(rechnung="x",+Rentabilitätsvorschau!AN3*(1+USt),+Rentabilitätsvorschau!AO3*(1+USt)) -> 0 | AP4: =SUM(AD4:AO4) -> 0 | AQ4: =IF(rechnung="x",+Rentabilitätsvorschau!AO3*(1+USt),+Rentabilitätsvorschau!AQ3*(1+USt)) -> 0 | AR4: =IF(rechnung="x",+Rentabilitätsvorschau!AQ3*(1+USt),+Rentabilitätsvorschau!AR3*(1+USt)) -> 0 | AS4: =IF(rechnung="x",+Rentabilitätsvorschau!AR3*(1+USt),+Rentabilitätsvorschau!AS3*(1+USt)) -> 0 | AT4: =IF(rechnung="x",+Rentabilitätsvorschau!AS3*(1+USt),+Rentabilitätsvorschau!AT3*(1+USt)) -> 0 | AU4: =IF(rechnung="x",+Rentabilitätsvorschau!AT3*(1+USt),+Rentabilitätsvorschau!AU3*(1+USt)) -> 0 | AV4: =IF(rechnung="x",+Rentabilitätsvorschau!AU3*(1+USt),+Rentabilitätsvorschau!AV3*(1+USt)) -> 0 | AW4: =IF(rechnung="x",+Rentabilitätsvorschau!AV3*(1+USt),+Rentabilitätsvorschau!AW3*(1+USt)) -> 0 | AX4: =IF(rechnung="x",+Rentabilitätsvorschau!AW3*(1+USt),+Rentabilitätsvorschau!AX3*(1+USt)) -> 0 | AY4: =IF(rechnung="x",+Rentabilitätsvorschau!AX3*(1+USt),+Rentabilitätsvorschau!AY3*(1+USt)) -> 0 | ... BB4: =IF(rechnung="x",+Rentabilitätsvorschau!BA3*(1+USt),+Rentabilitätsvorschau!BB3*(1+USt)) -> 0 | BC4: =SUM(AQ4:BB4) -> 0
C5: =IF('Infos vor dem Start'!$A$17="x","Bruttoumsatz 7%","Umsatz") -> Bruttoumsatz 7% | D5: =IF(rechnung="x",0,+Rentabilitätsvorschau!D4*(1+UStermeins)) -> 0 | E5: =IF(rechnung="x",+Rentabilitätsvorschau!D4*(1+UStermeins),+Rentabilitätsvorschau!E4*(1+UStermeins)) -> 0 | F5: =IF(rechnung="x",+Rentabilitätsvorschau!E4*(1+UStermeins),+Rentabilitätsvorschau!F4*(1+UStermeins)) -> 0 | G5: =IF(rechnung="x",+Rentabilitätsvorschau!F4*(1+UStermeins),+Rentabilitätsvorschau!G4*(1+UStermeins)) -> 0 | H5: =IF(rechnung="x",+Rentabilitätsvorschau!G4*(1+UStermeins),+Rentabilitätsvorschau!H4*(1+UStermeins)) -> 0 | I5: =IF(rechnung="x",+Rentabilitätsvorschau!H4*(1+UStermeins),+Rentabilitätsvorschau!I4*(1+UStermeins)) -> 0 | J5: =IF(rechnung="x",+Rentabilitätsvorschau!I4*(1+UStermeins),+Rentabilitätsvorschau!J4*(1+UStermeins)) -> 0 | K5: =IF(rechnung="x",+Rentabilitätsvorschau!J4*(1+UStermeins),+Rentabilitätsvorschau!K4*(1+UStermeins)) -> 0 | L5: =IF(rechnung="x",+Rentabilitätsvorschau!K4*(1+UStermeins),+Rentabilitätsvorschau!L4*(1+UStermeins)) -> 0 | ... O5: =IF(rechnung="x",+Rentabilitätsvorschau!N4*(1+UStermeins),+Rentabilitätsvorschau!O4*(1+UStermeins)) -> 0 | P5: =SUM(D5:O5) -> 0 | Q5: =IF(rechnung="x",+Rentabilitätsvorschau!O4*(1+UStermeins),+Rentabilitätsvorschau!Q4*(1+USterm)) -> 0 | R5: =IF(rechnung="x",+Rentabilitätsvorschau!Q4*(1+USterm),+Rentabilitätsvorschau!R4*(1+USterm)) -> 0 | S5: =IF(rechnung="x",+Rentabilitätsvorschau!R4*(1+USterm),+Rentabilitätsvorschau!S4*(1+USterm)) -> 0 | T5: =IF(rechnung="x",+Rentabilitätsvorschau!S4*(1+USterm),+Rentabilitätsvorschau!T4*(1+USterm)) -> 0 | U5: =IF(rechnung="x",+Rentabilitätsvorschau!T4*(1+USterm),+Rentabilitätsvorschau!U4*(1+USterm)) -> 0 | V5: =IF(rechnung="x",+Rentabilitätsvorschau!U4*(1+USterm),+Rentabilitätsvorschau!V4*(1+USterm)) -> 0 | W5: =IF(rechnung="x",+Rentabilitätsvorschau!V4*(1+USterm),+Rentabilitätsvorschau!W4*(1+USterm)) -> 0 | X5: =IF(rechnung="x",+Rentabilitätsvorschau!W4*(1+USterm),+Rentabilitätsvorschau!X4*(1+USterm)) -> 0 | Y5: =IF(rechnung="x",+Rentabilitätsvorschau!X4*(1+USterm),+Rentabilitätsvorschau!Y4*(1+USterm)) -> 0 | ... AB5: =IF(rechnung="x",+Rentabilitätsvorschau!AA4*(1+USterm),+Rentabilitätsvorschau!AB4*(1+USterm)) -> 0 | AC5: =SUM(Q5:AB5) -> 0 | AD5: =IF(rechnung="x",+Rentabilitätsvorschau!AB4*(1+USterm),+Rentabilitätsvorschau!AD4*(1+USterm)) -> 0 | AE5: =IF(rechnung="x",+Rentabilitätsvorschau!AD4*(1+USterm),+Rentabilitätsvorschau!AE4*(1+USterm)) -> 0 | AF5: =IF(rechnung="x",+Rentabilitätsvorschau!AE4*(1+USterm),+Rentabilitätsvorschau!AF4*(1+USterm)) -> 0 | AG5: =IF(rechnung="x",+Rentabilitätsvorschau!AF4*(1+USterm),+Rentabilitätsvorschau!AG4*(1+USterm)) -> 0 | AH5: =IF(rechnung="x",+Rentabilitätsvorschau!AG4*(1+USterm),+Rentabilitätsvorschau!AH4*(1+USterm)) -> 0 | AI5: =IF(rechnung="x",+Rentabilitätsvorschau!AH4*(1+USterm),+Rentabilitätsvorschau!AI4*(1+USterm)) -> 0 | AJ5: =IF(rechnung="x",+Rentabilitätsvorschau!AI4*(1+USterm),+Rentabilitätsvorschau!AJ4*(1+USterm)) -> 0 | AK5: =IF(rechnung="x",+Rentabilitätsvorschau!AJ4*(1+USterm),+Rentabilitätsvorschau!AK4*(1+USterm)) -> 0 | AL5: =IF(rechnung="x",+Rentabilitätsvorschau!AK4*(1+USterm),+Rentabilitätsvorschau!AL4*(1+USterm)) -> 0 | ... AO5: =IF(rechnung="x",+Rentabilitätsvorschau!AN4*(1+USterm),+Rentabilitätsvorschau!AO4*(1+USterm)) -> 0 | AP5: =SUM(AD5:AO5) -> 0 | AQ5: =IF(rechnung="x",+Rentabilitätsvorschau!AO4*(1+USterm),+Rentabilitätsvorschau!AQ4*(1+USterm)) -> 0 | AR5: =IF(rechnung="x",+Rentabilitätsvorschau!AQ4*(1+USterm),+Rentabilitätsvorschau!AR4*(1+USterm)) -> 0 | AS5: =IF(rechnung="x",+Rentabilitätsvorschau!AR4*(1+USterm),+Rentabilitätsvorschau!AS4*(1+USterm)) -> 0 | AT5: =IF(rechnung="x",+Rentabilitätsvorschau!AS4*(1+USterm),+Rentabilitätsvorschau!AT4*(1+USterm)) -> 0 | AU5: =IF(rechnung="x",+Rentabilitätsvorschau!AT4*(1+USterm),+Rentabilitätsvorschau!AU4*(1+USterm)) -> 0 | AV5: =IF(rechnung="x",+Rentabilitätsvorschau!AU4*(1+USterm),+Rentabilitätsvorschau!AV4*(1+USterm)) -> 0 | AW5: =IF(rechnung="x",+Rentabilitätsvorschau!AV4*(1+USterm),+Rentabilitätsvorschau!AW4*(1+USterm)) -> 0 | AX5: =IF(rechnung="x",+Rentabilitätsvorschau!AW4*(1+USterm),+Rentabilitätsvorschau!AX4*(1+USterm)) -> 0 | AY5: =IF(rechnung="x",+Rentabilitätsvorschau!AX4*(1+USterm),+Rentabilitätsvorschau!AY4*(1+USterm)) -> 0 | ... BB5: =IF(rechnung="x",+Rentabilitätsvorschau!BA4*(1+USterm),+Rentabilitätsvorschau!BB4*(1+USterm)) -> 0 | BC5: =SUM(AQ5:BB5) -> 0
B6: =IF('Infos vor dem Start'!$A$17="x","Bruttoumsatz Dienstleistungen 19%","Umsatz Dienstleistungen") -> Bruttoumsatz Dienstleistungen 19% | D6: =IF(rechnung="x",0,+Rentabilitätsvorschau!D5*(1+USteins)) -> 0 | E6: =IF(rechnung="x",+Rentabilitätsvorschau!D5*(1+USteins),+Rentabilitätsvorschau!E5*(1+USteins)) -> 0 | F6: =IF(rechnung="x",+Rentabilitätsvorschau!E5*(1+USteins),+Rentabilitätsvorschau!F5*(1+USteins)) -> 0 | G6: =IF(rechnung="x",+Rentabilitätsvorschau!F5*(1+USteins),+Rentabilitätsvorschau!G5*(1+USteins)) -> 0 | H6: =IF(rechnung="x",+Rentabilitätsvorschau!G5*(1+USteins),+Rentabilitätsvorschau!H5*(1+USteins)) -> 0 | I6: =IF(rechnung="x",+Rentabilitätsvorschau!H5*(1+USteins),+Rentabilitätsvorschau!I5*(1+USteins)) -> 0 | J6: =IF(rechnung="x",+Rentabilitätsvorschau!I5*(1+USteins),+Rentabilitätsvorschau!J5*(1+USteins)) -> 0 | K6: =IF(rechnung="x",+Rentabilitätsvorschau!J5*(1+USteins),+Rentabilitätsvorschau!K5*(1+USteins)) -> 0 | L6: =IF(rechnung="x",+Rentabilitätsvorschau!K5*(1+USteins),+Rentabilitätsvorschau!L5*(1+USteins)) -> 0 | ... O6: =IF(rechnung="x",+Rentabilitätsvorschau!N5*(1+USteins),+Rentabilitätsvorschau!O5*(1+USteins)) -> 0 | P6: =SUM(D6:O6) -> 16660 | Q6: =IF(rechnung="x",+Rentabilitätsvorschau!O5*(1+USteins),+Rentabilitätsvorschau!Q5*(1+USt)) -> 21420 | R6: =IF(rechnung="x",+Rentabilitätsvorschau!Q5*(1+USt),+Rentabilitätsvorschau!R5*(1+USt)) -> 0 | S6: =IF(rechnung="x",+Rentabilitätsvorschau!R5*(1+USt),+Rentabilitätsvorschau!S5*(1+USt)) -> 0 | T6: =IF(rechnung="x",+Rentabilitätsvorschau!S5*(1+USt),+Rentabilitätsvorschau!T5*(1+USt)) -> 0 | U6: =IF(rechnung="x",+Rentabilitätsvorschau!T5*(1+USt),+Rentabilitätsvorschau!U5*(1+USt)) -> 0 | V6: =IF(rechnung="x",+Rentabilitätsvorschau!U5*(1+USt),+Rentabilitätsvorschau!V5*(1+USt)) -> 0 | W6: =IF(rechnung="x",+Rentabilitätsvorschau!V5*(1+USt),+Rentabilitätsvorschau!W5*(1+USt)) -> 0 | X6: =IF(rechnung="x",+Rentabilitätsvorschau!W5*(1+USt),+Rentabilitätsvorschau!X5*(1+USt)) -> 0 | Y6: =IF(rechnung="x",+Rentabilitätsvorschau!X5*(1+USt),+Rentabilitätsvorschau!Y5*(1+USt)) -> 0 | ... AB6: =IF(rechnung="x",+Rentabilitätsvorschau!AA5*(1+USt),+Rentabilitätsvorschau!AB5*(1+USt)) -> 0 | AC6: =SUM(Q6:AB6) -> 21420 | AD6: =IF(rechnung="x",+Rentabilitätsvorschau!AB5*(1+USt),+Rentabilitätsvorschau!AD5*(1+USt)) -> 0 | AE6: =IF(rechnung="x",+Rentabilitätsvorschau!AD5*(1+USt),+Rentabilitätsvorschau!AE5*(1+USt)) -> 0 | AF6: =IF(rechnung="x",+Rentabilitätsvorschau!AE5*(1+USt),+Rentabilitätsvorschau!AF5*(1+USt)) -> 0 | AG6: =IF(rechnung="x",+Rentabilitätsvorschau!AF5*(1+USt),+Rentabilitätsvorschau!AG5*(1+USt)) -> 0 | AH6: =IF(rechnung="x",+Rentabilitätsvorschau!AG5*(1+USt),+Rentabilitätsvorschau!AH5*(1+USt)) -> 0 | AI6: =IF(rechnung="x",+Rentabilitätsvorschau!AH5*(1+USt),+Rentabilitätsvorschau!AI5*(1+USt)) -> 0 | AJ6: =IF(rechnung="x",+Rentabilitätsvorschau!AI5*(1+USt),+Rentabilitätsvorschau!AJ5*(1+USt)) -> 0 | AK6: =IF(rechnung="x",+Rentabilitätsvorschau!AJ5*(1+USt),+Rentabilitätsvorschau!AK5*(1+USt)) -> 0 | AL6: =IF(rechnung="x",+Rentabilitätsvorschau!AK5*(1+USt),+Rentabilitätsvorschau!AL5*(1+USt)) -> 0 | ... AO6: =IF(rechnung="x",+Rentabilitätsvorschau!AN5*(1+USt),+Rentabilitätsvorschau!AO5*(1+USt)) -> 0 | AP6: =SUM(AD6:AO6) -> 0 | AQ6: =IF(rechnung="x",+Rentabilitätsvorschau!AO5*(1+USt),+Rentabilitätsvorschau!AQ5*(1+USt)) -> 0 | AR6: =IF(rechnung="x",+Rentabilitätsvorschau!AQ5*(1+USt),+Rentabilitätsvorschau!AR5*(1+USt)) -> 0 | AS6: =IF(rechnung="x",+Rentabilitätsvorschau!AR5*(1+USt),+Rentabilitätsvorschau!AS5*(1+USt)) -> 0 | AT6: =IF(rechnung="x",+Rentabilitätsvorschau!AS5*(1+USt),+Rentabilitätsvorschau!AT5*(1+USt)) -> 0 | AU6: =IF(rechnung="x",+Rentabilitätsvorschau!AT5*(1+USt),+Rentabilitätsvorschau!AU5*(1+USt)) -> 0 | AV6: =IF(rechnung="x",+Rentabilitätsvorschau!AU5*(1+USt),+Rentabilitätsvorschau!AV5*(1+USt)) -> 0 | AW6: =IF(rechnung="x",+Rentabilitätsvorschau!AV5*(1+USt),+Rentabilitätsvorschau!AW5*(1+USt)) -> 0 | AX6: =IF(rechnung="x",+Rentabilitätsvorschau!AW5*(1+USt),+Rentabilitätsvorschau!AX5*(1+USt)) -> 0 | AY6: =IF(rechnung="x",+Rentabilitätsvorschau!AX5*(1+USt),+Rentabilitätsvorschau!AY5*(1+USt)) -> 0 | ... BB6: =IF(rechnung="x",+Rentabilitätsvorschau!BA5*(1+USt),+Rentabilitätsvorschau!BB5*(1+USt)) -> 0 | BC6: =SUM(AQ6:BB6) -> 0
B7: =IF('Infos vor dem Start'!$A$17="x","Erlösschmälerungen (Skonto) brutto","Erlösschmälerungen (Skonto)") -> Erlösschmälerungen (Skonto) brutto | D7: =IF(rechnung="x",0,(((+Rentabilitätsvorschau!D3+Rentabilitätsvorschau!D5)*(1+USteins)+Rentabilitätsvorschau!D4*(1+UStermeins)))*Rentabilitätsvorschau!$B6) -> 0 | E7: =IF(rechnung="x",((Rentabilitätsvorschau!D3+Rentabilitätsvorschau!D5)*(1+USteins)+Rentabilitätsvorschau!D4*(1+UStermeins))*Rentabilitätsvorschau!$B6,((+Rentabilitätsvorschau!D3+Rentabilitätsvorschau!D5)*(1+USteins)+Rentabilitätsvorschau!E4*(1+UStermeins))*Rentabilitätsvorschau!$B6) -> 0 | F7: =IF(rechnung="x",((Rentabilitätsvorschau!E3+Rentabilitätsvorschau!E5)*(1+USteins)+Rentabilitätsvorschau!E4*(1+UStermeins))*Rentabilitätsvorschau!$B6,((+Rentabilitätsvorschau!E3+Rentabilitätsvorschau!E5)*(1+USteins)+Rentabilitätsvorschau!F4*(1+UStermeins))*Rentabilitätsvorschau!$B6) -> 0 | G7: =IF(rechnung="x",((Rentabilitätsvorschau!F3+Rentabilitätsvorschau!F5)*(1+USteins)+Rentabilitätsvorschau!F4*(1+UStermeins))*Rentabilitätsvorschau!$B6,((+Rentabilitätsvorschau!F3+Rentabilitätsvorschau!F5)*(1+USteins)+Rentabilitätsvorschau!G4*(1+UStermeins))*Rentabilitätsvorschau!$B6) -> 0 | H7: =IF(rechnung="x",((Rentabilitätsvorschau!G3+Rentabilitätsvorschau!G5)*(1+USteins)+Rentabilitätsvorschau!G4*(1+UStermeins))*Rentabilitätsvorschau!$B6,((+Rentabilitätsvorschau!G3+Rentabilitätsvorschau!G5)*(1+USteins)+Rentabilitätsvorschau!H4*(1+UStermeins))*Rentabilitätsvorschau!$B6) -> 0 | I7: =IF(rechnung="x",((Rentabilitätsvorschau!H3+Rentabilitätsvorschau!H5)*(1+USteins)+Rentabilitätsvorschau!H4*(1+UStermeins))*Rentabilitätsvorschau!$B6,((+Rentabilitätsvorschau!H3+Rentabilitätsvorschau!H5)*(1+USteins)+Rentabilitätsvorschau!I4*(1+UStermeins))*Rentabilitätsvorschau!$B6) -> 0 | J7: =IF(rechnung="x",((Rentabilitätsvorschau!I3+Rentabilitätsvorschau!I5)*(1+USteins)+Rentabilitätsvorschau!I4*(1+UStermeins))*Rentabilitätsvorschau!$B6,((+Rentabilitätsvorschau!I3+Rentabilitätsvorschau!I5)*(1+USteins)+Rentabilitätsvorschau!J4*(1+UStermeins))*Rentabilitätsvorschau!$B6) -> 0 | K7: =IF(rechnung="x",((Rentabilitätsvorschau!J3+Rentabilitätsvorschau!J5)*(1+USteins)+Rentabilitätsvorschau!J4*(1+UStermeins))*Rentabilitätsvorschau!$B6,((+Rentabilitätsvorschau!J3+Rentabilitätsvorschau!J5)*(1+USteins)+Rentabilitätsvorschau!K4*(1+UStermeins))*Rentabilitätsvorschau!$B6) -> 0 | L7: =IF(rechnung="x",((Rentabilitätsvorschau!K3+Rentabilitätsvorschau!K5)*(1+USteins)+Rentabilitätsvorschau!K4*(1+UStermeins))*Rentabilitätsvorschau!$B6,((+Rentabilitätsvorschau!K3+Rentabilitätsvorschau!K5)*(1+USteins)+Rentabilitätsvorschau!L4*(1+UStermeins))*Rentabilitätsvorschau!$B6) -> 0 | ... O7: =IF(rechnung="x",((Rentabilitätsvorschau!N3+Rentabilitätsvorschau!N5)*(1+USteins)+Rentabilitätsvorschau!N4*(1+UStermeins))*Rentabilitätsvorschau!$B6,((+Rentabilitätsvorschau!N3+Rentabilitätsvorschau!N5)*(1+USteins)+Rentabilitätsvorschau!O4*(1+UStermeins))*Rentabilitätsvorschau!$B6) -> 0 | P7: =SUM(D7:O7) -> 0 | Q7: =IF(rechnung="x",((Rentabilitätsvorschau!O3+Rentabilitätsvorschau!O5)*(1+USteins)+Rentabilitätsvorschau!O4*(1+UStermeins))*Rentabilitätsvorschau!$B6,((+Rentabilitätsvorschau!Q3+Rentabilitätsvorschau!Q5)*(1+USt)+Rentabilitätsvorschau!Q4*(1+USterm))*Rentabilitätsvorschau!$B6) -> 0 | R7: =IF(rechnung="x",((Rentabilitätsvorschau!Q3+Rentabilitätsvorschau!Q5)*(1+USt)+Rentabilitätsvorschau!Q4*(1+USterm))*Rentabilitätsvorschau!$B6,((+Rentabilitätsvorschau!R3+Rentabilitätsvorschau!R5)*(1+USt)+Rentabilitätsvorschau!R4*(1+USterm))*Rentabilitätsvorschau!$B6) -> 0 | S7: =IF(rechnung="x",((Rentabilitätsvorschau!R3+Rentabilitätsvorschau!R5)*(1+USt)+Rentabilitätsvorschau!R4*(1+USterm))*Rentabilitätsvorschau!$B6,((+Rentabilitätsvorschau!S3+Rentabilitätsvorschau!S5)*(1+USt)+Rentabilitätsvorschau!S4*(1+USterm))*Rentabilitätsvorschau!$B6) -> 0 | T7: =IF(rechnung="x",((Rentabilitätsvorschau!S3+Rentabilitätsvorschau!S5)*(1+USt)+Rentabilitätsvorschau!S4*(1+USterm))*Rentabilitätsvorschau!$B6,((+Rentabilitätsvorschau!T3+Rentabilitätsvorschau!T5)*(1+USt)+Rentabilitätsvorschau!T4*(1+USterm))*Rentabilitätsvorschau!$B6) -> 0 | U7: =IF(rechnung="x",((Rentabilitätsvorschau!T3+Rentabilitätsvorschau!T5)*(1+USt)+Rentabilitätsvorschau!T4*(1+USterm))*Rentabilitätsvorschau!$B6,((+Rentabilitätsvorschau!U3+Rentabilitätsvorschau!U5)*(1+USt)+Rentabilitätsvorschau!U4*(1+USterm))*Rentabilitätsvorschau!$B6) -> 0 | V7: =IF(rechnung="x",((Rentabilitätsvorschau!U3+Rentabilitätsvorschau!U5)*(1+USt)+Rentabilitätsvorschau!U4*(1+USterm))*Rentabilitätsvorschau!$B6,((+Rentabilitätsvorschau!V3+Rentabilitätsvorschau!V5)*(1+USt)+Rentabilitätsvorschau!V4*(1+USterm))*Rentabilitätsvorschau!$B6) -> 0 | W7: =IF(rechnung="x",((Rentabilitätsvorschau!V3+Rentabilitätsvorschau!V5)*(1+USt)+Rentabilitätsvorschau!V4*(1+USterm))*Rentabilitätsvorschau!$B6,((+Rentabilitätsvorschau!W3+Rentabilitätsvorschau!W5)*(1+USt)+Rentabilitätsvorschau!W4*(1+USterm))*Rentabilitätsvorschau!$B6) -> 0 | X7: =IF(rechnung="x",((Rentabilitätsvorschau!W3+Rentabilitätsvorschau!W5)*(1+USt)+Rentabilitätsvorschau!W4*(1+USterm))*Rentabilitätsvorschau!$B6,((+Rentabilitätsvorschau!X3+Rentabilitätsvorschau!X5)*(1+USt)+Rentabilitätsvorschau!X4*(1+USterm))*Rentabilitätsvorschau!$B6) -> 0 | Y7: =IF(rechnung="x",((Rentabilitätsvorschau!X3+Rentabilitätsvorschau!X5)*(1+USt)+Rentabilitätsvorschau!X4*(1+USterm))*Rentabilitätsvorschau!$B6,((+Rentabilitätsvorschau!Y3+Rentabilitätsvorschau!Y5)*(1+USt)+Rentabilitätsvorschau!Y4*(1+USterm))*Rentabilitätsvorschau!$B6) -> 0 | ... AB7: =IF(rechnung="x",((Rentabilitätsvorschau!AA3+Rentabilitätsvorschau!AA5)*(1+USt)+Rentabilitätsvorschau!AA4*(1+USterm))*Rentabilitätsvorschau!$B6,((+Rentabilitätsvorschau!AB3+Rentabilitätsvorschau!AB5)*(1+USt)+Rentabilitätsvorschau!AB4*(1+USterm))*Rentabilitätsvorschau!$B6) -> 0 | AC7: =SUM(Q7:AB7) -> 0 | AD7: =IF(rechnung="x",((Rentabilitätsvorschau!AB3+Rentabilitätsvorschau!AB5)*(1+USt)+Rentabilitätsvorschau!AB4*(1+USterm))*Rentabilitätsvorschau!$B6,((+Rentabilitätsvorschau!AD3+Rentabilitätsvorschau!AD5)*(1+USt)+Rentabilitätsvorschau!AD4*(1+USterm))*Rentabilitätsvorschau!$B6) -> 0 | AE7: =IF(rechnung="x",((Rentabilitätsvorschau!AD3+Rentabilitätsvorschau!AD5)*(1+USt)+Rentabilitätsvorschau!AD4*(1+USterm))*Rentabilitätsvorschau!$B6,((+Rentabilitätsvorschau!AE3+Rentabilitätsvorschau!AE5)*(1+USt)+Rentabilitätsvorschau!AE4*(1+USterm))*Rentabilitätsvorschau!$B6) -> 0 | AF7: =IF(rechnung="x",((Rentabilitätsvorschau!AE3+Rentabilitätsvorschau!AE5)*(1+USt)+Rentabilitätsvorschau!AE4*(1+USterm))*Rentabilitätsvorschau!$B6,((+Rentabilitätsvorschau!AF3+Rentabilitätsvorschau!AF5)*(1+USt)+Rentabilitätsvorschau!AF4*(1+USterm))*Rentabilitätsvorschau!$B6) -> 0 | AG7: =IF(rechnung="x",((Rentabilitätsvorschau!AF3+Rentabilitätsvorschau!AF5)*(1+USt)+Rentabilitätsvorschau!AF4*(1+USterm))*Rentabilitätsvorschau!$B6,((+Rentabilitätsvorschau!AG3+Rentabilitätsvorschau!AG5)*(1+USt)+Rentabilitätsvorschau!AG4*(1+USterm))*Rentabilitätsvorschau!$B6) -> 0 | AH7: =IF(rechnung="x",((Rentabilitätsvorschau!AG3+Rentabilitätsvorschau!AG5)*(1+USt)+Rentabilitätsvorschau!AG4*(1+USterm))*Rentabilitätsvorschau!$B6,((+Rentabilitätsvorschau!AH3+Rentabilitätsvorschau!AH5)*(1+USt)+Rentabilitätsvorschau!AH4*(1+USterm))*Rentabilitätsvorschau!$B6) -> 0 | AI7: =IF(rechnung="x",((Rentabilitätsvorschau!AH3+Rentabilitätsvorschau!AH5)*(1+USt)+Rentabilitätsvorschau!AH4*(1+USterm))*Rentabilitätsvorschau!$B6,((+Rentabilitätsvorschau!AI3+Rentabilitätsvorschau!AI5)*(1+USt)+Rentabilitätsvorschau!AI4*(1+USterm))*Rentabilitätsvorschau!$B6) -> 0 | AJ7: =IF(rechnung="x",((Rentabilitätsvorschau!AI3+Rentabilitätsvorschau!AI5)*(1+USt)+Rentabilitätsvorschau!AI4*(1+USterm))*Rentabilitätsvorschau!$B6,((+Rentabilitätsvorschau!AJ3+Rentabilitätsvorschau!AJ5)*(1+USt)+Rentabilitätsvorschau!AJ4*(1+USterm))*Rentabilitätsvorschau!$B6) -> 0 | AK7: =IF(rechnung="x",((Rentabilitätsvorschau!AJ3+Rentabilitätsvorschau!AJ5)*(1+USt)+Rentabilitätsvorschau!AJ4*(1+USterm))*Rentabilitätsvorschau!$B6,((+Rentabilitätsvorschau!AK3+Rentabilitätsvorschau!AK5)*(1+USt)+Rentabilitätsvorschau!AK4*(1+USterm))*Rentabilitätsvorschau!$B6) -> 0 | AL7: =IF(rechnung="x",((Rentabilitätsvorschau!AK3+Rentabilitätsvorschau!AK5)*(1+USt)+Rentabilitätsvorschau!AK4*(1+USterm))*Rentabilitätsvorschau!$B6,((+Rentabilitätsvorschau!AL3+Rentabilitätsvorschau!AL5)*(1+USt)+Rentabilitätsvorschau!AL4*(1+USterm))*Rentabilitätsvorschau!$B6) -> 0 | ... AO7: =IF(rechnung="x",((Rentabilitätsvorschau!AN3+Rentabilitätsvorschau!AN5)*(1+USt)+Rentabilitätsvorschau!AN4*(1+USterm))*Rentabilitätsvorschau!$B6,((+Rentabilitätsvorschau!AO3+Rentabilitätsvorschau!AO5)*(1+USt)+Rentabilitätsvorschau!AO4*(1+USterm))*Rentabilitätsvorschau!$B6) -> 0 | AP7: =SUM(AD7:AO7) -> 0 | AQ7: =IF(rechnung="x",((Rentabilitätsvorschau!AO3+Rentabilitätsvorschau!AO5)*(1+USt)+Rentabilitätsvorschau!AO4*(1+USterm))*Rentabilitätsvorschau!$B6,((+Rentabilitätsvorschau!AQ3+Rentabilitätsvorschau!AQ5)*(1+USt)+Rentabilitätsvorschau!AQ4*(1+USterm))*Rentabilitätsvorschau!$B6) -> 0 | AR7: =IF(rechnung="x",((Rentabilitätsvorschau!AQ3+Rentabilitätsvorschau!AQ5)*(1+USt)+Rentabilitätsvorschau!AQ4*(1+USterm))*Rentabilitätsvorschau!$B6,((+Rentabilitätsvorschau!AR3+Rentabilitätsvorschau!AR5)*(1+USt)+Rentabilitätsvorschau!AR4*(1+USterm))*Rentabilitätsvorschau!$B6) -> 0 | AS7: =IF(rechnung="x",((Rentabilitätsvorschau!AR3+Rentabilitätsvorschau!AR5)*(1+USt)+Rentabilitätsvorschau!AR4*(1+USterm))*Rentabilitätsvorschau!$B6,((+Rentabilitätsvorschau!AS3+Rentabilitätsvorschau!AS5)*(1+USt)+Rentabilitätsvorschau!AS4*(1+USterm))*Rentabilitätsvorschau!$B6) -> 0 | AT7: =IF(rechnung="x",((Rentabilitätsvorschau!AS3+Rentabilitätsvorschau!AS5)*(1+USt)+Rentabilitätsvorschau!AS4*(1+USterm))*Rentabilitätsvorschau!$B6,((+Rentabilitätsvorschau!AT3+Rentabilitätsvorschau!AT5)*(1+USt)+Rentabilitätsvorschau!AT4*(1+USterm))*Rentabilitätsvorschau!$B6) -> 0 | AU7: =IF(rechnung="x",((Rentabilitätsvorschau!AT3+Rentabilitätsvorschau!AT5)*(1+USt)+Rentabilitätsvorschau!AT4*(1+USterm))*Rentabilitätsvorschau!$B6,((+Rentabilitätsvorschau!AU3+Rentabilitätsvorschau!AU5)*(1+USt)+Rentabilitätsvorschau!AU4*(1+USterm))*Rentabilitätsvorschau!$B6) -> 0 | AV7: =IF(rechnung="x",((Rentabilitätsvorschau!AU3+Rentabilitätsvorschau!AU5)*(1+USt)+Rentabilitätsvorschau!AU4*(1+USterm))*Rentabilitätsvorschau!$B6,((+Rentabilitätsvorschau!AV3+Rentabilitätsvorschau!AV5)*(1+USt)+Rentabilitätsvorschau!AV4*(1+USterm))*Rentabilitätsvorschau!$B6) -> 0 | AW7: =IF(rechnung="x",((Rentabilitätsvorschau!AV3+Rentabilitätsvorschau!AV5)*(1+USt)+Rentabilitätsvorschau!AV4*(1+USterm))*Rentabilitätsvorschau!$B6,((+Rentabilitätsvorschau!AW3+Rentabilitätsvorschau!AW5)*(1+USt)+Rentabilitätsvorschau!AW4*(1+USterm))*Rentabilitätsvorschau!$B6) -> 0 | AX7: =IF(rechnung="x",((Rentabilitätsvorschau!AW3+Rentabilitätsvorschau!AW5)*(1+USt)+Rentabilitätsvorschau!AW4*(1+USterm))*Rentabilitätsvorschau!$B6,((+Rentabilitätsvorschau!AX3+Rentabilitätsvorschau!AX5)*(1+USt)+Rentabilitätsvorschau!AX4*(1+USterm))*Rentabilitätsvorschau!$B6) -> 0 | AY7: =IF(rechnung="x",((Rentabilitätsvorschau!AX3+Rentabilitätsvorschau!AX5)*(1+USt)+Rentabilitätsvorschau!AX4*(1+USterm))*Rentabilitätsvorschau!$B6,((+Rentabilitätsvorschau!AY3+Rentabilitätsvorschau!AY5)*(1+USt)+Rentabilitätsvorschau!AY4*(1+USterm))*Rentabilitätsvorschau!$B6) -> 0 | ... BB7: =IF(rechnung="x",((Rentabilitätsvorschau!BA3+Rentabilitätsvorschau!BA5)*(1+USt)+Rentabilitätsvorschau!BA4*(1+USterm))*Rentabilitätsvorschau!$B6,((+Rentabilitätsvorschau!BB3+Rentabilitätsvorschau!BB5)*(1+USt)+Rentabilitätsvorschau!BB4*(1+USterm))*Rentabilitätsvorschau!$B6) -> 0 | BC7: =SUM(AQ7:BB7) -> 0
A8: =+Rentabilitätsvorschau!A7 -> sonstige betriebliche Erträge | D8: =+Rentabilitätsvorschau!D7*(1+USteins) -> 0 | E8: =+Rentabilitätsvorschau!E7*(1+USteins) -> 0 | F8: =+Rentabilitätsvorschau!F7*(1+USteins) -> 0 | G8: =+Rentabilitätsvorschau!G7*(1+USteins) -> 0 | H8: =+Rentabilitätsvorschau!H7*(1+USteins) -> 0 | I8: =+Rentabilitätsvorschau!I7*(1+USteins) -> 0 | J8: =+Rentabilitätsvorschau!J7*(1+USteins) -> 0 | K8: =+Rentabilitätsvorschau!K7*(1+USteins) -> 0 | ... O8: =+Rentabilitätsvorschau!O7*(1+USteins) -> 0 | P8: =SUM(D8:O8) -> 0 | Q8: =+Rentabilitätsvorschau!Q7*(1+USt) -> 0 | R8: =+Rentabilitätsvorschau!R7*(1+USt) -> 0 | S8: =+Rentabilitätsvorschau!S7*(1+USt) -> 0 | T8: =+Rentabilitätsvorschau!T7*(1+USt) -> 0 | U8: =+Rentabilitätsvorschau!U7*(1+USt) -> 0 | V8: =+Rentabilitätsvorschau!V7*(1+USt) -> 0 | W8: =+Rentabilitätsvorschau!W7*(1+USt) -> 0 | X8: =+Rentabilitätsvorschau!X7*(1+USt) -> 0 | ... AB8: =+Rentabilitätsvorschau!AB7*(1+USt) -> 0 | AC8: =SUM(Q8:AB8) -> 0 | AD8: =+Rentabilitätsvorschau!AD7*(1+USt) -> 0 | AE8: =+Rentabilitätsvorschau!AE7*(1+USt) -> 0 | AF8: =+Rentabilitätsvorschau!AF7*(1+USt) -> 0 | AG8: =+Rentabilitätsvorschau!AG7*(1+USt) -> 0 | AH8: =+Rentabilitätsvorschau!AH7*(1+USt) -> 0 | AI8: =+Rentabilitätsvorschau!AI7*(1+USt) -> 0 | AJ8: =+Rentabilitätsvorschau!AJ7*(1+USt) -> 0 | AK8: =+Rentabilitätsvorschau!AK7*(1+USt) -> 0 | ... AO8: =+Rentabilitätsvorschau!AO7*(1+USt) -> 0 | AP8: =SUM(AD8:AO8) -> 0 | AQ8: =+Rentabilitätsvorschau!AQ7*(1+USt) -> 0 | AR8: =+Rentabilitätsvorschau!AR7*(1+USt) -> 0 | AS8: =+Rentabilitätsvorschau!AS7*(1+USt) -> 0 | AT8: =+Rentabilitätsvorschau!AT7*(1+USt) -> 0 | AU8: =+Rentabilitätsvorschau!AU7*(1+USt) -> 0 | AV8: =+Rentabilitätsvorschau!AV7*(1+USt) -> 0 | AW8: =+Rentabilitätsvorschau!AW7*(1+USt) -> 0 | AX8: =+Rentabilitätsvorschau!AX7*(1+USt) -> 0 | ... BB8: =+Rentabilitätsvorschau!BB7*(1+USt) -> 0 | BC8: =SUM(AQ8:BB8) -> 0
A9: =+Rentabilitätsvorschau!A8 -> Wareneinkauf/Materialaufwand
B10: =+Rentabilitätsvorschau!C9 -> pauschaler Wareneinsatz | D10: =+Rentabilitätsvorschau!D9*(1+VStWEeins) -> 0 | E10: =+Rentabilitätsvorschau!E9*(1+VStWEeins) -> 0 | F10: =+Rentabilitätsvorschau!F9*(1+VStWEeins) -> 0 | G10: =+Rentabilitätsvorschau!G9*(1+VStWEeins) -> 0 | H10: =+Rentabilitätsvorschau!H9*(1+VStWEeins) -> 0 | I10: =+Rentabilitätsvorschau!I9*(1+VStWEeins) -> 0 | J10: =+Rentabilitätsvorschau!J9*(1+VStWEeins) -> 0 | K10: =+Rentabilitätsvorschau!K9*(1+VStWEeins) -> 0 | ... O10: =+Rentabilitätsvorschau!O9*(1+VStWEeins) -> 0 | P10: =SUM(D10:O10) -> 0 | Q10: =+Rentabilitätsvorschau!Q9*(1+VStWE) -> 0 | R10: =+Rentabilitätsvorschau!R9*(1+VStWE) -> 0 | S10: =+Rentabilitätsvorschau!S9*(1+VStWE) -> 0 | T10: =+Rentabilitätsvorschau!T9*(1+VStWE) -> 0 | U10: =+Rentabilitätsvorschau!U9*(1+VStWE) -> 0 | V10: =+Rentabilitätsvorschau!V9*(1+VStWE) -> 0 | W10: =+Rentabilitätsvorschau!W9*(1+VStWE) -> 0 | X10: =+Rentabilitätsvorschau!X9*(1+VStWE) -> 0 | ... AB10: =+Rentabilitätsvorschau!AB9*(1+VStWE) -> 0 | AC10: =SUM(Q10:AB10) -> 0 | AD10: =+Rentabilitätsvorschau!AD9*(1+VStWE) -> 0 | AE10: =+Rentabilitätsvorschau!AE9*(1+VStWE) -> 0 | AF10: =+Rentabilitätsvorschau!AF9*(1+VStWE) -> 0 | AG10: =+Rentabilitätsvorschau!AG9*(1+VStWE) -> 0 | AH10: =+Rentabilitätsvorschau!AH9*(1+VStWE) -> 0 | AI10: =+Rentabilitätsvorschau!AI9*(1+VStWE) -> 0 | AJ10: =+Rentabilitätsvorschau!AJ9*(1+VStWE) -> 0 | AK10: =+Rentabilitätsvorschau!AK9*(1+VStWE) -> 0 | ... AO10: =+Rentabilitätsvorschau!AO9*(1+VStWE) -> 0 | AP10: =SUM(AD10:AO10) -> 0 | AQ10: =+Rentabilitätsvorschau!AQ9*(1+VStWE) -> 0 | AR10: =+Rentabilitätsvorschau!AR9*(1+VStWE) -> 0 | AS10: =+Rentabilitätsvorschau!AS9*(1+VStWE) -> 0 | AT10: =+Rentabilitätsvorschau!AT9*(1+VStWE) -> 0 | AU10: =+Rentabilitätsvorschau!AU9*(1+VStWE) -> 0 | AV10: =+Rentabilitätsvorschau!AV9*(1+VStWE) -> 0 | AW10: =+Rentabilitätsvorschau!AW9*(1+VStWE) -> 0 | AX10: =+Rentabilitätsvorschau!AX9*(1+VStWE) -> 0 | ... BB10: =+Rentabilitätsvorschau!BB9*(1+VStWE) -> 0 | BC10: =SUM(AQ10:BB10) -> 0
B11: =+Rentabilitätsvorschau!B10 -> Fremdleistungen | D11: =+Rentabilitätsvorschau!D10*(1+VSteins) -> 0 | E11: =+Rentabilitätsvorschau!E10*(1+VSteins) -> 0 | F11: =+Rentabilitätsvorschau!F10*(1+VSteins) -> 0 | G11: =+Rentabilitätsvorschau!G10*(1+VSteins) -> 0 | H11: =+Rentabilitätsvorschau!H10*(1+VSteins) -> 0 | I11: =+Rentabilitätsvorschau!I10*(1+VSteins) -> 0 | J11: =+Rentabilitätsvorschau!J10*(1+VSteins) -> 0 | K11: =+Rentabilitätsvorschau!K10*(1+VSteins) -> 0 | ... O11: =+Rentabilitätsvorschau!O10*(1+VSteins) -> 0 | P11: =SUM(D11:O11) -> 0 | Q11: =+Rentabilitätsvorschau!Q10*(1+VSt) -> 0 | R11: =+Rentabilitätsvorschau!R10*(1+VSt) -> 0 | S11: =+Rentabilitätsvorschau!S10*(1+VSt) -> 0 | T11: =+Rentabilitätsvorschau!T10*(1+VSt) -> 0 | U11: =+Rentabilitätsvorschau!U10*(1+VSt) -> 0 | V11: =+Rentabilitätsvorschau!V10*(1+VSt) -> 0 | W11: =+Rentabilitätsvorschau!W10*(1+VSt) -> 0 | X11: =+Rentabilitätsvorschau!X10*(1+VSt) -> 0 | ... AB11: =+Rentabilitätsvorschau!AB10*(1+VSt) -> 0 | AC11: =SUM(Q11:AB11) -> 0 | AD11: =+Rentabilitätsvorschau!AD10*(1+VStWE) -> 0 | AE11: =+Rentabilitätsvorschau!AE10*(1+VStWE) -> 0 | AF11: =+Rentabilitätsvorschau!AF10*(1+VStWE) -> 0 | AG11: =+Rentabilitätsvorschau!AG10*(1+VStWE) -> 0 | AH11: =+Rentabilitätsvorschau!AH10*(1+VStWE) -> 0 | AI11: =+Rentabilitätsvorschau!AI10*(1+VStWE) -> 0 | AJ11: =+Rentabilitätsvorschau!AJ10*(1+VStWE) -> 0 | AK11: =+Rentabilitätsvorschau!AK10*(1+VStWE) -> 0 | ... AO11: =+Rentabilitätsvorschau!AO10*(1+VStWE) -> 0 | AP11: =SUM(AD11:AO11) -> 0 | AQ11: =+Rentabilitätsvorschau!AQ10*(1+VStWE) -> 0 | AR11: =+Rentabilitätsvorschau!AR10*(1+VStWE) -> 0 | AS11: =+Rentabilitätsvorschau!AS10*(1+VStWE) -> 0 | AT11: =+Rentabilitätsvorschau!AT10*(1+VStWE) -> 0 | AU11: =+Rentabilitätsvorschau!AU10*(1+VStWE) -> 0 | AV11: =+Rentabilitätsvorschau!AV10*(1+VStWE) -> 0 | AW11: =+Rentabilitätsvorschau!AW10*(1+VStWE) -> 0 | AX11: =+Rentabilitätsvorschau!AX10*(1+VStWE) -> 0 | ... BB11: =+Rentabilitätsvorschau!BB10*(1+VStWE) -> 0 | BC11: =SUM(AQ11:BB11) -> 0
B12: =+Rentabilitätsvorschau!B11 -> Wareneinkauf Saisongeschäft | D12: =+Rentabilitätsvorschau!D11*(1+VSteins) -> 0 | E12: =+Rentabilitätsvorschau!E11*(1+VSteins) -> 0 | F12: =+Rentabilitätsvorschau!F11*(1+VSteins) -> 0 | G12: =+Rentabilitätsvorschau!G11*(1+VSteins) -> 0 | H12: =+Rentabilitätsvorschau!H11*(1+VSteins) -> 0 | I12: =+Rentabilitätsvorschau!I11*(1+VSteins) -> 0 | J12: =+Rentabilitätsvorschau!J11*(1+VSteins) -> 0 | K12: =+Rentabilitätsvorschau!K11*(1+VSteins) -> 0 | ... O12: =+Rentabilitätsvorschau!O11*(1+VSteins) -> 0 | P12: =SUM(D12:O12) -> 0 | Q12: =+Rentabilitätsvorschau!Q11*(1+VSt) -> 0 | R12: =+Rentabilitätsvorschau!R11*(1+VSt) -> 0 | S12: =+Rentabilitätsvorschau!S11*(1+VSt) -> 0 | T12: =+Rentabilitätsvorschau!T11*(1+VSt) -> 0 | U12: =+Rentabilitätsvorschau!U11*(1+VSt) -> 0 | V12: =+Rentabilitätsvorschau!V11*(1+VSt) -> 0 | W12: =+Rentabilitätsvorschau!W11*(1+VSt) -> 0 | X12: =+Rentabilitätsvorschau!X11*(1+VSt) -> 0 | ... AB12: =+Rentabilitätsvorschau!AB11*(1+VSt) -> 0 | AC12: =SUM(Q12:AB12) -> 0 | AD12: =+Rentabilitätsvorschau!AD11*(1+VStWE) -> 0 | AE12: =+Rentabilitätsvorschau!AE11*(1+VStWE) -> 0 | AF12: =+Rentabilitätsvorschau!AF11*(1+VStWE) -> 0 | AG12: =+Rentabilitätsvorschau!AG11*(1+VStWE) -> 0 | AH12: =+Rentabilitätsvorschau!AH11*(1+VStWE) -> 0 | AI12: =+Rentabilitätsvorschau!AI11*(1+VStWE) -> 0 | AJ12: =+Rentabilitätsvorschau!AJ11*(1+VStWE) -> 0 | AK12: =+Rentabilitätsvorschau!AK11*(1+VStWE) -> 0 | ... AO12: =+Rentabilitätsvorschau!AO11*(1+VStWE) -> 0 | AP12: =SUM(AD12:AO12) -> 0 | AQ12: =+Rentabilitätsvorschau!AQ11*(1+VStWE) -> 0 | AR12: =+Rentabilitätsvorschau!AR11*(1+VStWE) -> 0 | AS12: =+Rentabilitätsvorschau!AS11*(1+VStWE) -> 0 | AT12: =+Rentabilitätsvorschau!AT11*(1+VStWE) -> 0 | AU12: =+Rentabilitätsvorschau!AU11*(1+VStWE) -> 0 | AV12: =+Rentabilitätsvorschau!AV11*(1+VStWE) -> 0 | AW12: =+Rentabilitätsvorschau!AW11*(1+VStWE) -> 0 | AX12: =+Rentabilitätsvorschau!AX11*(1+VStWE) -> 0 | ... BB12: =+Rentabilitätsvorschau!BB11*(1+VStWE) -> 0 | BC12: =SUM(AQ12:BB12) -> 0
B13: =+Rentabilitätsvorschau!B12 -> Warenlager-Erstausstattung und -aufstockung | D13: =+Rentabilitätsvorschau!D12*(1+VSteins) -> 0 | E13: =+Rentabilitätsvorschau!E12*(1+VSteins) -> 0 | F13: =+Rentabilitätsvorschau!F12*(1+VSteins) -> 0 | G13: =+Rentabilitätsvorschau!G12*(1+VSteins) -> 0 | H13: =+Rentabilitätsvorschau!H12*(1+VSteins) -> 0 | I13: =+Rentabilitätsvorschau!I12*(1+VSteins) -> 0 | J13: =+Rentabilitätsvorschau!J12*(1+VSteins) -> 0 | K13: =+Rentabilitätsvorschau!K12*(1+VSteins) -> 0 | ... O13: =+Rentabilitätsvorschau!O12*(1+VSteins) -> 0 | P13: =SUM(D13:O13) -> 0 | Q13: =+Rentabilitätsvorschau!Q12*(1+VSt) -> 0 | R13: =+Rentabilitätsvorschau!R12*(1+VSt) -> 0 | S13: =+Rentabilitätsvorschau!S12*(1+VSt) -> 0 | T13: =+Rentabilitätsvorschau!T12*(1+VSt) -> 0 | U13: =+Rentabilitätsvorschau!U12*(1+VSt) -> 0 | V13: =+Rentabilitätsvorschau!V12*(1+VSt) -> 0 | W13: =+Rentabilitätsvorschau!W12*(1+VSt) -> 0 | X13: =+Rentabilitätsvorschau!X12*(1+VSt) -> 0 | ... AB13: =+Rentabilitätsvorschau!AB12*(1+VSt) -> 0 | AC13: =SUM(Q13:AB13) -> 0 | AD13: =+Rentabilitätsvorschau!AD12*(1+VStWE) -> 0 | AE13: =+Rentabilitätsvorschau!AE12*(1+VStWE) -> 0 | AF13: =+Rentabilitätsvorschau!AF12*(1+VStWE) -> 0 | AG13: =+Rentabilitätsvorschau!AG12*(1+VStWE) -> 0 | AH13: =+Rentabilitätsvorschau!AH12*(1+VStWE) -> 0 | AI13: =+Rentabilitätsvorschau!AI12*(1+VStWE) -> 0 | AJ13: =+Rentabilitätsvorschau!AJ12*(1+VStWE) -> 0 | AK13: =+Rentabilitätsvorschau!AK12*(1+VStWE) -> 0 | ... AO13: =+Rentabilitätsvorschau!AO12*(1+VStWE) -> 0 | AP13: =SUM(AD13:AO13) -> 0 | AQ13: =+Rentabilitätsvorschau!AQ12*(1+VStWE) -> 0 | AR13: =+Rentabilitätsvorschau!AR12*(1+VStWE) -> 0 | AS13: =+Rentabilitätsvorschau!AS12*(1+VStWE) -> 0 | AT13: =+Rentabilitätsvorschau!AT12*(1+VStWE) -> 0 | AU13: =+Rentabilitätsvorschau!AU12*(1+VStWE) -> 0 | AV13: =+Rentabilitätsvorschau!AV12*(1+VStWE) -> 0 | AW13: =+Rentabilitätsvorschau!AW12*(1+VStWE) -> 0 | AX13: =+Rentabilitätsvorschau!AX12*(1+VStWE) -> 0 | ... BB13: =+Rentabilitätsvorschau!BB12*(1+VStWE) -> 0 | BC13: =SUM(AQ13:BB13) -> 0
A14: =+Rentabilitätsvorschau!A13 -> Rohergebnis | D14: =+D4+D5+D6-D7+D8-D10-D11-D12-D13 -> 0 | E14: =+E4+E5+E6-E7+E8-E10-E11-E12-E13 -> 0 | F14: =+F4+F5+F6-F7+F8-F10-F11-F12-F13 -> 0 | G14: =+G4+G5+G6-G7+G8-G10-G11-G12-G13 -> 0 | H14: =+H4+H5+H6-H7+H8-H10-H11-H12-H13 -> 0 | I14: =+I4+I5+I6-I7+I8-I10-I11-I12-I13 -> 0 | J14: =+J4+J5+J6-J7+J8-J10-J11-J12-J13 -> 0 | K14: =+K4+K5+K6-K7+K8-K10-K11-K12-K13 -> 0 | ... BC14: =+BC4+BC5+BC6-BC7+BC8-BC10-BC11-BC12-BC13 -> 0
A15: =+Rentabilitätsvorschau!A14 -> Personalaufwand incl. Sozialabgaben (ca. 22%) | D15: =+Rentabilitätsvorschau!D14 -> 0 | E15: =+Rentabilitätsvorschau!E14 -> 0 | F15: =+Rentabilitätsvorschau!F14 -> 0 | G15: =+Rentabilitätsvorschau!G14 -> 0 | H15: =+Rentabilitätsvorschau!H14 -> 0 | I15: =+Rentabilitätsvorschau!I14 -> 0 | J15: =+Rentabilitätsvorschau!J14 -> 0 | K15: =+Rentabilitätsvorschau!K14 -> 0 | ... O15: =+Rentabilitätsvorschau!O14 -> 0 | P15: =SUM(D15:O15) -> 0 | Q15: =+Rentabilitätsvorschau!Q14 -> 720 | R15: =+Rentabilitätsvorschau!R14 -> 720 | S15: =+Rentabilitätsvorschau!S14 -> 720 | T15: =+Rentabilitätsvorschau!T14 -> 720 | U15: =+Rentabilitätsvorschau!U14 -> 720 | V15: =+Rentabilitätsvorschau!V14 -> 720 | W15: =+Rentabilitätsvorschau!W14 -> 720 | X15: =+Rentabilitätsvorschau!X14 -> 720 | ... AB15: =+Rentabilitätsvorschau!AB14 -> 720 | AC15: =SUM(Q15:AB15) -> 8640 | AD15: =+Rentabilitätsvorschau!AD14 -> 0 | AE15: =+Rentabilitätsvorschau!AE14 -> 0 | AF15: =+Rentabilitätsvorschau!AF14 -> 0 | AG15: =+Rentabilitätsvorschau!AG14 -> 0 | AH15: =+Rentabilitätsvorschau!AH14 -> 0 | AI15: =+Rentabilitätsvorschau!AI14 -> 0 | AJ15: =+Rentabilitätsvorschau!AJ14 -> 0 | AK15: =+Rentabilitätsvorschau!AK14 -> 0 | ... AO15: =+Rentabilitätsvorschau!AO14 -> 0 | AP15: =SUM(AD15:AO15) -> 0 | AQ15: =+Rentabilitätsvorschau!AQ14 -> 0 | AR15: =+Rentabilitätsvorschau!AR14 -> 0 | AS15: =+Rentabilitätsvorschau!AS14 -> 0 | AT15: =+Rentabilitätsvorschau!AT14 -> 0 | AU15: =+Rentabilitätsvorschau!AU14 -> 0 | AV15: =+Rentabilitätsvorschau!AV14 -> 0 | AW15: =+Rentabilitätsvorschau!AW14 -> 0 | AX15: =+Rentabilitätsvorschau!AX14 -> 0 | ... BB15: =+Rentabilitätsvorschau!BB14 -> 0 | BC15: =SUM(AQ15:BB15) -> 0
A16: =+Rentabilitätsvorschau!A15 -> Abschreibungen | D16: - | E16: - | F16: - | G16: - | H16: - | I16: - | J16: - | K16: - | L16: - | M16: - | N16: - | O16: - | P16: - | Q16: - | R16: - | S16: - | T16: - | U16: - | V16: - | W16: - | X16: - | Y16: - | Z16: - | AA16: - | AB16: - | AC16: - | AD16: - | AE16: - | AF16: - | AG16: - | AH16: - | AI16: - | AJ16: - | AK16: - | AL16: - | AM16: - | AN16: - | AO16: - | AP16: - | AQ16: - | AR16: - | AS16: - | AT16: - | AU16: - | AV16: - | AW16: - | AX16: - | AY16: - | AZ16: - | BA16: - | BB16: - | BC16: -
A17: =+Rentabilitätsvorschau!A16 -> Sonstige betriebliche Aufwendungen
B18: =+Rentabilitätsvorschau!B17 -> Raumkosten (Miete, Nebenkosten, Reinigung etc.)
C19: =+Rentabilitätsvorschau!C18 -> Miete und Nebenkosten | D19: =+Rentabilitätsvorschau!D18*(1+VSteins) -> 0 | E19: =+Rentabilitätsvorschau!E18*(1+VSteins) -> 0 | F19: =+Rentabilitätsvorschau!F18*(1+VSteins) -> 0 | G19: =+Rentabilitätsvorschau!G18*(1+VSteins) -> 0 | H19: =+Rentabilitätsvorschau!H18*(1+VSteins) -> 0 | I19: =+Rentabilitätsvorschau!I18*(1+VSteins) -> 0 | J19: =+Rentabilitätsvorschau!J18*(1+VSteins) -> 0 | K19: =+Rentabilitätsvorschau!K18*(1+VSteins) -> 0 | ... O19: =+Rentabilitätsvorschau!O18*(1+VSteins) -> 714 | P19: =SUM(D19:O19) -> 2142 | Q19: =+Rentabilitätsvorschau!Q18*(1+VSt) -> 714 | R19: =+Rentabilitätsvorschau!R18*(1+VSt) -> 714 | S19: =+Rentabilitätsvorschau!S18*(1+VSt) -> 714 | T19: =+Rentabilitätsvorschau!T18*(1+VSt) -> 714 | U19: =+Rentabilitätsvorschau!U18*(1+VSt) -> 714 | V19: =+Rentabilitätsvorschau!V18*(1+VSt) -> 714 | W19: =+Rentabilitätsvorschau!W18*(1+VSt) -> 714 | X19: =+Rentabilitätsvorschau!X18*(1+VSt) -> 714 | ... AB19: =+Rentabilitätsvorschau!AB18*(1+VSt) -> 714 | AC19: =SUM(Q19:AB19) -> 8568 | AD19: =+Rentabilitätsvorschau!AD18*(1+VSt) -> 0 | AE19: =+Rentabilitätsvorschau!AE18*(1+VSt) -> 0 | AF19: =+Rentabilitätsvorschau!AF18*(1+VSt) -> 0 | AG19: =+Rentabilitätsvorschau!AG18*(1+VSt) -> 0 | AH19: =+Rentabilitätsvorschau!AH18*(1+VSt) -> 0 | AI19: =+Rentabilitätsvorschau!AI18*(1+VSt) -> 0 | AJ19: =+Rentabilitätsvorschau!AJ18*(1+VSt) -> 0 | AK19: =+Rentabilitätsvorschau!AK18*(1+VSt) -> 0 | ... AO19: =+Rentabilitätsvorschau!AO18*(1+VSt) -> 0 | AP19: =SUM(AD19:AO19) -> 0 | AQ19: =+Rentabilitätsvorschau!AQ18*(1+VSt) -> 0 | AR19: =+Rentabilitätsvorschau!AR18*(1+VSt) -> 0 | AS19: =+Rentabilitätsvorschau!AS18*(1+VSt) -> 0 | AT19: =+Rentabilitätsvorschau!AT18*(1+VSt) -> 0 | AU19: =+Rentabilitätsvorschau!AU18*(1+VSt) -> 0 | AV19: =+Rentabilitätsvorschau!AV18*(1+VSt) -> 0 | AW19: =+Rentabilitätsvorschau!AW18*(1+VSt) -> 0 | AX19: =+Rentabilitätsvorschau!AX18*(1+VSt) -> 0 | ... BB19: =+Rentabilitätsvorschau!BB18*(1+VSt) -> 0 | BC19: =SUM(AQ19:BB19) -> 0
C20: =+Rentabilitätsvorschau!C19 -> Instandhaltung | D20: =+Rentabilitätsvorschau!D19*(1+VSteins) -> 0 | E20: =+Rentabilitätsvorschau!E19*(1+VSteins) -> 0 | F20: =+Rentabilitätsvorschau!F19*(1+VSteins) -> 0 | G20: =+Rentabilitätsvorschau!G19*(1+VSteins) -> 0 | H20: =+Rentabilitätsvorschau!H19*(1+VSteins) -> 0 | I20: =+Rentabilitätsvorschau!I19*(1+VSteins) -> 0 | J20: =+Rentabilitätsvorschau!J19*(1+VSteins) -> 0 | K20: =+Rentabilitätsvorschau!K19*(1+VSteins) -> 0 | ... O20: =+Rentabilitätsvorschau!O19*(1+VSteins) -> 59.5 | P20: =SUM(D20:O20) -> 178.5 | Q20: =+Rentabilitätsvorschau!Q19*(1+VSt) -> 59.5 | R20: =+Rentabilitätsvorschau!R19*(1+VSt) -> 59.5 | S20: =+Rentabilitätsvorschau!S19*(1+VSt) -> 59.5 | T20: =+Rentabilitätsvorschau!T19*(1+VSt) -> 59.5 | U20: =+Rentabilitätsvorschau!U19*(1+VSt) -> 59.5 | V20: =+Rentabilitätsvorschau!V19*(1+VSt) -> 59.5 | W20: =+Rentabilitätsvorschau!W19*(1+VSt) -> 59.5 | X20: =+Rentabilitätsvorschau!X19*(1+VSt) -> 59.5 | ... AB20: =+Rentabilitätsvorschau!AB19*(1+VSt) -> 59.5 | AC20: =SUM(Q20:AB20) -> 714 | AD20: =+Rentabilitätsvorschau!AD19*(1+VSt) -> 0 | AE20: =+Rentabilitätsvorschau!AE19*(1+VSt) -> 0 | AF20: =+Rentabilitätsvorschau!AF19*(1+VSt) -> 0 | AG20: =+Rentabilitätsvorschau!AG19*(1+VSt) -> 0 | AH20: =+Rentabilitätsvorschau!AH19*(1+VSt) -> 0 | AI20: =+Rentabilitätsvorschau!AI19*(1+VSt) -> 0 | AJ20: =+Rentabilitätsvorschau!AJ19*(1+VSt) -> 0 | AK20: =+Rentabilitätsvorschau!AK19*(1+VSt) -> 0 | ... AO20: =+Rentabilitätsvorschau!AO19*(1+VSt) -> 0 | AP20: =SUM(AD20:AO20) -> 0 | AQ20: =+Rentabilitätsvorschau!AQ19*(1+VSt) -> 0 | AR20: =+Rentabilitätsvorschau!AR19*(1+VSt) -> 0 | AS20: =+Rentabilitätsvorschau!AS19*(1+VSt) -> 0 | AT20: =+Rentabilitätsvorschau!AT19*(1+VSt) -> 0 | AU20: =+Rentabilitätsvorschau!AU19*(1+VSt) -> 0 | AV20: =+Rentabilitätsvorschau!AV19*(1+VSt) -> 0 | AW20: =+Rentabilitätsvorschau!AW19*(1+VSt) -> 0 | AX20: =+Rentabilitätsvorschau!AX19*(1+VSt) -> 0 | ... BB20: =+Rentabilitätsvorschau!BB19*(1+VSt) -> 0 | BC20: =SUM(AQ20:BB20) -> 0
B21: =+Rentabilitätsvorschau!B20 -> Telefon, Fax | D21: =+Rentabilitätsvorschau!D20*(1+VSteins) -> 0 | E21: =+Rentabilitätsvorschau!E20*(1+VSteins) -> 0 | F21: =+Rentabilitätsvorschau!F20*(1+VSteins) -> 0 | G21: =+Rentabilitätsvorschau!G20*(1+VSteins) -> 0 | H21: =+Rentabilitätsvorschau!H20*(1+VSteins) -> 0 | I21: =+Rentabilitätsvorschau!I20*(1+VSteins) -> 0 | J21: =+Rentabilitätsvorschau!J20*(1+VSteins) -> 0 | K21: =+Rentabilitätsvorschau!K20*(1+VSteins) -> 0 | ... O21: =+Rentabilitätsvorschau!O20*(1+VSteins) -> 119 | P21: =SUM(D21:O21) -> 357 | Q21: =+Rentabilitätsvorschau!Q20*(1+VSt) -> 119 | R21: =+Rentabilitätsvorschau!R20*(1+VSt) -> 119 | S21: =+Rentabilitätsvorschau!S20*(1+VSt) -> 119 | T21: =+Rentabilitätsvorschau!T20*(1+VSt) -> 119 | U21: =+Rentabilitätsvorschau!U20*(1+VSt) -> 119 | V21: =+Rentabilitätsvorschau!V20*(1+VSt) -> 119 | W21: =+Rentabilitätsvorschau!W20*(1+VSt) -> 119 | X21: =+Rentabilitätsvorschau!X20*(1+VSt) -> 119 | ... AB21: =+Rentabilitätsvorschau!AB20*(1+VSt) -> 119 | AC21: =SUM(Q21:AB21) -> 1428 | AD21: =+Rentabilitätsvorschau!AD20*(1+VSt) -> 0 | AE21: =+Rentabilitätsvorschau!AE20*(1+VSt) -> 0 | AF21: =+Rentabilitätsvorschau!AF20*(1+VSt) -> 0 | AG21: =+Rentabilitätsvorschau!AG20*(1+VSt) -> 0 | AH21: =+Rentabilitätsvorschau!AH20*(1+VSt) -> 0 | AI21: =+Rentabilitätsvorschau!AI20*(1+VSt) -> 0 | AJ21: =+Rentabilitätsvorschau!AJ20*(1+VSt) -> 0 | AK21: =+Rentabilitätsvorschau!AK20*(1+VSt) -> 0 | ... AO21: =+Rentabilitätsvorschau!AO20*(1+VSt) -> 0 | AP21: =SUM(AD21:AO21) -> 0 | AQ21: =+Rentabilitätsvorschau!AQ20*(1+VSt) -> 0 | AR21: =+Rentabilitätsvorschau!AR20*(1+VSt) -> 0 | AS21: =+Rentabilitätsvorschau!AS20*(1+VSt) -> 0 | AT21: =+Rentabilitätsvorschau!AT20*(1+VSt) -> 0 | AU21: =+Rentabilitätsvorschau!AU20*(1+VSt) -> 0 | AV21: =+Rentabilitätsvorschau!AV20*(1+VSt) -> 0 | AW21: =+Rentabilitätsvorschau!AW20*(1+VSt) -> 0 | AX21: =+Rentabilitätsvorschau!AX20*(1+VSt) -> 0 | ... BB21: =+Rentabilitätsvorschau!BB20*(1+VSt) -> 0 | BC21: =SUM(AQ21:BB21) -> 0
B22: =+Rentabilitätsvorschau!B21 -> Kfz-Kosten
C23: =+Rentabilitätsvorschau!C22 -> Kfz-Versicherungen | D23: =+Rentabilitätsvorschau!D22 -> 0 | E23: =+Rentabilitätsvorschau!E22 -> 0 | F23: =+Rentabilitätsvorschau!F22 -> 0 | G23: =+Rentabilitätsvorschau!G22 -> 0 | H23: =+Rentabilitätsvorschau!H22 -> 0 | I23: =+Rentabilitätsvorschau!I22 -> 0 | J23: =+Rentabilitätsvorschau!J22 -> 0 | ... O23: =+Rentabilitätsvorschau!O22 -> 0 | P23: =SUM(D23:O23) -> 0 | Q23: =+Rentabilitätsvorschau!Q22 -> 0 | R23: =+Rentabilitätsvorschau!R22 -> 0 | S23: =+Rentabilitätsvorschau!S22 -> 0 | T23: =+Rentabilitätsvorschau!T22 -> 0 | U23: =+Rentabilitätsvorschau!U22 -> 0 | V23: =+Rentabilitätsvorschau!V22 -> 0 | W23: =+Rentabilitätsvorschau!W22 -> 0 | X23: =+Rentabilitätsvorschau!X22 -> 0 | ... AB23: =+Rentabilitätsvorschau!AB22 -> 0 | AC23: =SUM(Q23:AB23) -> 0 | AD23: =+Rentabilitätsvorschau!AD22 -> 0 | AE23: =+Rentabilitätsvorschau!AE22 -> 0 | AF23: =+Rentabilitätsvorschau!AF22 -> 0 | AG23: =+Rentabilitätsvorschau!AG22 -> 0 | AH23: =+Rentabilitätsvorschau!AH22 -> 0 | AI23: =+Rentabilitätsvorschau!AI22 -> 0 | AJ23: =+Rentabilitätsvorschau!AJ22 -> 0 | AK23: =+Rentabilitätsvorschau!AK22 -> 0 | ... AO23: =+Rentabilitätsvorschau!AO22 -> 0 | AP23: =SUM(AD23:AO23) -> 0 | AQ23: =+Rentabilitätsvorschau!AQ22 -> 0 | AR23: =+Rentabilitätsvorschau!AR22 -> 0 | AS23: =+Rentabilitätsvorschau!AS22 -> 0 | AT23: =+Rentabilitätsvorschau!AT22 -> 0 | AU23: =+Rentabilitätsvorschau!AU22 -> 0 | AV23: =+Rentabilitätsvorschau!AV22 -> 0 | AW23: =+Rentabilitätsvorschau!AW22 -> 0 | AX23: =+Rentabilitätsvorschau!AX22 -> 0 | ... BB23: =+Rentabilitätsvorschau!BB22 -> 0 | BC23: =SUM(AQ23:BB23) -> 0
C24: =+Rentabilitätsvorschau!C23 -> Wartung und Reparatur | D24: =+Rentabilitätsvorschau!D23*(1+VSteins) -> 0 | E24: =+Rentabilitätsvorschau!E23*(1+VSteins) -> 0 | F24: =+Rentabilitätsvorschau!F23*(1+VSteins) -> 0 | G24: =+Rentabilitätsvorschau!G23*(1+VSteins) -> 0 | H24: =+Rentabilitätsvorschau!H23*(1+VSteins) -> 0 | I24: =+Rentabilitätsvorschau!I23*(1+VSteins) -> 0 | J24: =+Rentabilitätsvorschau!J23*(1+VSteins) -> 0 | K24: =+Rentabilitätsvorschau!K23*(1+VSteins) -> 0 | ... O24: =+Rentabilitätsvorschau!O23*(1+VSteins) -> 0 | P24: =SUM(D24:O24) -> 0 | Q24: =+Rentabilitätsvorschau!Q23*(1+VSt) -> 0 | R24: =+Rentabilitätsvorschau!R23*(1+VSt) -> 0 | S24: =+Rentabilitätsvorschau!S23*(1+VSt) -> 0 | T24: =+Rentabilitätsvorschau!T23*(1+VSt) -> 0 | U24: =+Rentabilitätsvorschau!U23*(1+VSt) -> 0 | V24: =+Rentabilitätsvorschau!V23*(1+VSt) -> 0 | W24: =+Rentabilitätsvorschau!W23*(1+VSt) -> 0 | X24: =+Rentabilitätsvorschau!X23*(1+VSt) -> 0 | ... AB24: =+Rentabilitätsvorschau!AB23*(1+VSt) -> 0 | AC24: =SUM(Q24:AB24) -> 0 | AD24: =+Rentabilitätsvorschau!AD23*(1+VSt) -> 0 | AE24: =+Rentabilitätsvorschau!AE23*(1+VSt) -> 0 | AF24: =+Rentabilitätsvorschau!AF23*(1+VSt) -> 0 | AG24: =+Rentabilitätsvorschau!AG23*(1+VSt) -> 0 | AH24: =+Rentabilitätsvorschau!AH23*(1+VSt) -> 0 | AI24: =+Rentabilitätsvorschau!AI23*(1+VSt) -> 0 | AJ24: =+Rentabilitätsvorschau!AJ23*(1+VSt) -> 0 | AK24: =+Rentabilitätsvorschau!AK23*(1+VSt) -> 0 | ... AO24: =+Rentabilitätsvorschau!AO23*(1+VSt) -> 0 | AP24: =SUM(AD24:AO24) -> 0 | AQ24: =+Rentabilitätsvorschau!AQ23*(1+VSt) -> 0 | AR24: =+Rentabilitätsvorschau!AR23*(1+VSt) -> 0 | AS24: =+Rentabilitätsvorschau!AS23*(1+VSt) -> 0 | AT24: =+Rentabilitätsvorschau!AT23*(1+VSt) -> 0 | AU24: =+Rentabilitätsvorschau!AU23*(1+VSt) -> 0 | AV24: =+Rentabilitätsvorschau!AV23*(1+VSt) -> 0 | AW24: =+Rentabilitätsvorschau!AW23*(1+VSt) -> 0 | AX24: =+Rentabilitätsvorschau!AX23*(1+VSt) -> 0 | ... BB24: =+Rentabilitätsvorschau!BB23*(1+VSt) -> 0 | BC24: =SUM(AQ24:BB24) -> 0
C25: =+Rentabilitätsvorschau!C24 -> Leasing (nur Kfz) | D25: =+Rentabilitätsvorschau!D24*(1+VSteins) -> 0 | E25: =+Rentabilitätsvorschau!E24*(1+VSteins) -> 0 | F25: =+Rentabilitätsvorschau!F24*(1+VSteins) -> 0 | G25: =+Rentabilitätsvorschau!G24*(1+VSteins) -> 0 | H25: =+Rentabilitätsvorschau!H24*(1+VSteins) -> 0 | I25: =+Rentabilitätsvorschau!I24*(1+VSteins) -> 0 | J25: =+Rentabilitätsvorschau!J24*(1+VSteins) -> 0 | K25: =+Rentabilitätsvorschau!K24*(1+VSteins) -> 0 | ... O25: =+Rentabilitätsvorschau!O24*(1+VSteins) -> 0 | P25: =SUM(D25:O25) -> 0 | Q25: =+Rentabilitätsvorschau!Q24*(1+VSt) -> 0 | R25: =+Rentabilitätsvorschau!R24*(1+VSt) -> 0 | S25: =+Rentabilitätsvorschau!S24*(1+VSt) -> 0 | T25: =+Rentabilitätsvorschau!T24*(1+VSt) -> 0 | U25: =+Rentabilitätsvorschau!U24*(1+VSt) -> 0 | V25: =+Rentabilitätsvorschau!V24*(1+VSt) -> 0 | W25: =+Rentabilitätsvorschau!W24*(1+VSt) -> 0 | X25: =+Rentabilitätsvorschau!X24*(1+VSt) -> 0 | ... AB25: =+Rentabilitätsvorschau!AB24*(1+VSt) -> 0 | AC25: =SUM(Q25:AB25) -> 0 | AD25: =+Rentabilitätsvorschau!AD24*(1+VSt) -> 0 | AE25: =+Rentabilitätsvorschau!AE24*(1+VSt) -> 0 | AF25: =+Rentabilitätsvorschau!AF24*(1+VSt) -> 0 | AG25: =+Rentabilitätsvorschau!AG24*(1+VSt) -> 0 | AH25: =+Rentabilitätsvorschau!AH24*(1+VSt) -> 0 | AI25: =+Rentabilitätsvorschau!AI24*(1+VSt) -> 0 | AJ25: =+Rentabilitätsvorschau!AJ24*(1+VSt) -> 0 | AK25: =+Rentabilitätsvorschau!AK24*(1+VSt) -> 0 | ... AO25: =+Rentabilitätsvorschau!AO24*(1+VSt) -> 0 | AP25: =SUM(AD25:AO25) -> 0 | AQ25: =+Rentabilitätsvorschau!AQ24*(1+VSt) -> 0 | AR25: =+Rentabilitätsvorschau!AR24*(1+VSt) -> 0 | AS25: =+Rentabilitätsvorschau!AS24*(1+VSt) -> 0 | AT25: =+Rentabilitätsvorschau!AT24*(1+VSt) -> 0 | AU25: =+Rentabilitätsvorschau!AU24*(1+VSt) -> 0 | AV25: =+Rentabilitätsvorschau!AV24*(1+VSt) -> 0 | AW25: =+Rentabilitätsvorschau!AW24*(1+VSt) -> 0 | AX25: =+Rentabilitätsvorschau!AX24*(1+VSt) -> 0 | ... BB25: =+Rentabilitätsvorschau!BB24*(1+VSt) -> 0 | BC25: =SUM(AQ25:BB25) -> 0
C26: =+Rentabilitätsvorschau!C25 -> Betriebskosten | D26: =+Rentabilitätsvorschau!D25*(1+VSteins) -> 0 | E26: =+Rentabilitätsvorschau!E25*(1+VSteins) -> 0 | F26: =+Rentabilitätsvorschau!F25*(1+VSteins) -> 0 | G26: =+Rentabilitätsvorschau!G25*(1+VSteins) -> 0 | H26: =+Rentabilitätsvorschau!H25*(1+VSteins) -> 0 | I26: =+Rentabilitätsvorschau!I25*(1+VSteins) -> 0 | J26: =+Rentabilitätsvorschau!J25*(1+VSteins) -> 0 | K26: =+Rentabilitätsvorschau!K25*(1+VSteins) -> 0 | ... O26: =+Rentabilitätsvorschau!O25*(1+VSteins) -> 0 | P26: =SUM(D26:O26) -> 0 | Q26: =+Rentabilitätsvorschau!Q25*(1+VSt) -> 0 | R26: =+Rentabilitätsvorschau!R25*(1+VSt) -> 0 | S26: =+Rentabilitätsvorschau!S25*(1+VSt) -> 0 | T26: =+Rentabilitätsvorschau!T25*(1+VSt) -> 0 | U26: =+Rentabilitätsvorschau!U25*(1+VSt) -> 0 | V26: =+Rentabilitätsvorschau!V25*(1+VSt) -> 0 | W26: =+Rentabilitätsvorschau!W25*(1+VSt) -> 0 | X26: =+Rentabilitätsvorschau!X25*(1+VSt) -> 0 | ... AB26: =+Rentabilitätsvorschau!AB25*(1+VSt) -> 0 | AC26: =SUM(Q26:AB26) -> 0 | AD26: =+Rentabilitätsvorschau!AD25*(1+VSt) -> 0 | AE26: =+Rentabilitätsvorschau!AE25*(1+VSt) -> 0 | AF26: =+Rentabilitätsvorschau!AF25*(1+VSt) -> 0 | AG26: =+Rentabilitätsvorschau!AG25*(1+VSt) -> 0 | AH26: =+Rentabilitätsvorschau!AH25*(1+VSt) -> 0 | AI26: =+Rentabilitätsvorschau!AI25*(1+VSt) -> 0 | AJ26: =+Rentabilitätsvorschau!AJ25*(1+VSt) -> 0 | AK26: =+Rentabilitätsvorschau!AK25*(1+VSt) -> 0 | ... AO26: =+Rentabilitätsvorschau!AO25*(1+VSt) -> 0 | AP26: =SUM(AD26:AO26) -> 0 | AQ26: =+Rentabilitätsvorschau!AQ25*(1+VSt) -> 0 | AR26: =+Rentabilitätsvorschau!AR25*(1+VSt) -> 0 | AS26: =+Rentabilitätsvorschau!AS25*(1+VSt) -> 0 | AT26: =+Rentabilitätsvorschau!AT25*(1+VSt) -> 0 | AU26: =+Rentabilitätsvorschau!AU25*(1+VSt) -> 0 | AV26: =+Rentabilitätsvorschau!AV25*(1+VSt) -> 0 | AW26: =+Rentabilitätsvorschau!AW25*(1+VSt) -> 0 | AX26: =+Rentabilitätsvorschau!AX25*(1+VSt) -> 0 | ... BB26: =+Rentabilitätsvorschau!BB25*(1+VSt) -> 0 | BC26: =SUM(AQ26:BB26) -> 0
B27: =+Rentabilitätsvorschau!B26 -> Reise- und Bewirtungskosten | D27: =+Rentabilitätsvorschau!D26*(1+VSteins) -> 0 | E27: =+Rentabilitätsvorschau!E26*(1+VSteins) -> 0 | F27: =+Rentabilitätsvorschau!F26*(1+VSteins) -> 0 | G27: =+Rentabilitätsvorschau!G26*(1+VSteins) -> 0 | H27: =+Rentabilitätsvorschau!H26*(1+VSteins) -> 0 | I27: =+Rentabilitätsvorschau!I26*(1+VSteins) -> 0 | J27: =+Rentabilitätsvorschau!J26*(1+VSteins) -> 0 | K27: =+Rentabilitätsvorschau!K26*(1+VSteins) -> 0 | ... O27: =+Rentabilitätsvorschau!O26*(1+VSteins) -> 357 | P27: =SUM(D27:O27) -> 1071 | Q27: =+Rentabilitätsvorschau!Q26*(1+VSt) -> 357 | R27: =+Rentabilitätsvorschau!R26*(1+VSt) -> 357 | S27: =+Rentabilitätsvorschau!S26*(1+VSt) -> 357 | T27: =+Rentabilitätsvorschau!T26*(1+VSt) -> 357 | U27: =+Rentabilitätsvorschau!U26*(1+VSt) -> 357 | V27: =+Rentabilitätsvorschau!V26*(1+VSt) -> 357 | W27: =+Rentabilitätsvorschau!W26*(1+VSt) -> 357 | X27: =+Rentabilitätsvorschau!X26*(1+VSt) -> 357 | ... AB27: =+Rentabilitätsvorschau!AB26*(1+VSt) -> 357 | AC27: =SUM(Q27:AB27) -> 4284 | AD27: =+Rentabilitätsvorschau!AD26*(1+VSt) -> 0 | AE27: =+Rentabilitätsvorschau!AE26*(1+VSt) -> 0 | AF27: =+Rentabilitätsvorschau!AF26*(1+VSt) -> 0 | AG27: =+Rentabilitätsvorschau!AG26*(1+VSt) -> 0 | AH27: =+Rentabilitätsvorschau!AH26*(1+VSt) -> 0 | AI27: =+Rentabilitätsvorschau!AI26*(1+VSt) -> 0 | AJ27: =+Rentabilitätsvorschau!AJ26*(1+VSt) -> 0 | AK27: =+Rentabilitätsvorschau!AK26*(1+VSt) -> 0 | ... AO27: =+Rentabilitätsvorschau!AO26*(1+VSt) -> 0 | AP27: =SUM(AD27:AO27) -> 0 | AQ27: =+Rentabilitätsvorschau!AQ26*(1+VSt) -> 0 | AR27: =+Rentabilitätsvorschau!AR26*(1+VSt) -> 0 | AS27: =+Rentabilitätsvorschau!AS26*(1+VSt) -> 0 | AT27: =+Rentabilitätsvorschau!AT26*(1+VSt) -> 0 | AU27: =+Rentabilitätsvorschau!AU26*(1+VSt) -> 0 | AV27: =+Rentabilitätsvorschau!AV26*(1+VSt) -> 0 | AW27: =+Rentabilitätsvorschau!AW26*(1+VSt) -> 0 | AX27: =+Rentabilitätsvorschau!AX26*(1+VSt) -> 0 | ... BB27: =+Rentabilitätsvorschau!BB26*(1+VSt) -> 0 | BC27: =SUM(AQ27:BB27) -> 0
B28: =+Rentabilitätsvorschau!B27 -> Anzeigen- und sonst. Werbung | D28: =+Rentabilitätsvorschau!D27*(1+VSteins) -> 0 | E28: =+Rentabilitätsvorschau!E27*(1+VSteins) -> 0 | F28: =+Rentabilitätsvorschau!F27*(1+VSteins) -> 0 | G28: =+Rentabilitätsvorschau!G27*(1+VSteins) -> 0 | H28: =+Rentabilitätsvorschau!H27*(1+VSteins) -> 0 | I28: =+Rentabilitätsvorschau!I27*(1+VSteins) -> 0 | J28: =+Rentabilitätsvorschau!J27*(1+VSteins) -> 0 | K28: =+Rentabilitätsvorschau!K27*(1+VSteins) -> 0 | ... O28: =+Rentabilitätsvorschau!O27*(1+VSteins) -> 119 | P28: =SUM(D28:O28) -> 357 | Q28: =+Rentabilitätsvorschau!Q27*(1+VSt) -> 119 | R28: =+Rentabilitätsvorschau!R27*(1+VSt) -> 119 | S28: =+Rentabilitätsvorschau!S27*(1+VSt) -> 119 | T28: =+Rentabilitätsvorschau!T27*(1+VSt) -> 119 | U28: =+Rentabilitätsvorschau!U27*(1+VSt) -> 119 | V28: =+Rentabilitätsvorschau!V27*(1+VSt) -> 119 | W28: =+Rentabilitätsvorschau!W27*(1+VSt) -> 119 | X28: =+Rentabilitätsvorschau!X27*(1+VSt) -> 119 | ... AB28: =+Rentabilitätsvorschau!AB27*(1+VSt) -> 119 | AC28: =SUM(Q28:AB28) -> 1428 | AD28: =+Rentabilitätsvorschau!AD27*(1+VSt) -> 0 | AE28: =+Rentabilitätsvorschau!AE27*(1+VSt) -> 0 | AF28: =+Rentabilitätsvorschau!AF27*(1+VSt) -> 0 | AG28: =+Rentabilitätsvorschau!AG27*(1+VSt) -> 0 | AH28: =+Rentabilitätsvorschau!AH27*(1+VSt) -> 0 | AI28: =+Rentabilitätsvorschau!AI27*(1+VSt) -> 0 | AJ28: =+Rentabilitätsvorschau!AJ27*(1+VSt) -> 0 | AK28: =+Rentabilitätsvorschau!AK27*(1+VSt) -> 0 | ... AO28: =+Rentabilitätsvorschau!AO27*(1+VSt) -> 0 | AP28: =SUM(AD28:AO28) -> 0 | AQ28: =+Rentabilitätsvorschau!AQ27*(1+VSt) -> 0 | AR28: =+Rentabilitätsvorschau!AR27*(1+VSt) -> 0 | AS28: =+Rentabilitätsvorschau!AS27*(1+VSt) -> 0 | AT28: =+Rentabilitätsvorschau!AT27*(1+VSt) -> 0 | AU28: =+Rentabilitätsvorschau!AU27*(1+VSt) -> 0 | AV28: =+Rentabilitätsvorschau!AV27*(1+VSt) -> 0 | AW28: =+Rentabilitätsvorschau!AW27*(1+VSt) -> 0 | AX28: =+Rentabilitätsvorschau!AX27*(1+VSt) -> 0 | ... BB28: =+Rentabilitätsvorschau!BB27*(1+VSt) -> 0 | BC28: =SUM(AQ28:BB28) -> 0
B29: =+Rentabilitätsvorschau!B28 -> Kosten der Warenabgabe
C30: =+Rentabilitätsvorschau!C29 -> Verpackung/Ausgangsfrachten | D30: =+Rentabilitätsvorschau!D29*(1+VSteins) -> 0 | E30: =+Rentabilitätsvorschau!E29*(1+VSteins) -> 0 | F30: =+Rentabilitätsvorschau!F29*(1+VSteins) -> 0 | G30: =+Rentabilitätsvorschau!G29*(1+VSteins) -> 0 | H30: =+Rentabilitätsvorschau!H29*(1+VSteins) -> 0 | I30: =+Rentabilitätsvorschau!I29*(1+VSteins) -> 0 | J30: =+Rentabilitätsvorschau!J29*(1+VSteins) -> 0 | K30: =+Rentabilitätsvorschau!K29*(1+VSteins) -> 0 | ... O30: =+Rentabilitätsvorschau!O29*(1+VSteins) -> 0 | P30: =SUM(D30:O30) -> 0 | Q30: =+Rentabilitätsvorschau!Q29*(1+VSt) -> 0 | R30: =+Rentabilitätsvorschau!R29*(1+VSt) -> 0 | S30: =+Rentabilitätsvorschau!S29*(1+VSt) -> 0 | T30: =+Rentabilitätsvorschau!T29*(1+VSt) -> 0 | U30: =+Rentabilitätsvorschau!U29*(1+VSt) -> 0 | V30: =+Rentabilitätsvorschau!V29*(1+VSt) -> 0 | W30: =+Rentabilitätsvorschau!W29*(1+VSt) -> 0 | X30: =+Rentabilitätsvorschau!X29*(1+VSt) -> 0 | ... AB30: =+Rentabilitätsvorschau!AB29*(1+VSt) -> 0 | AC30: =SUM(Q30:AB30) -> 0 | AD30: =+Rentabilitätsvorschau!AD29*(1+VSt) -> 0 | AE30: =+Rentabilitätsvorschau!AE29*(1+VSt) -> 0 | AF30: =+Rentabilitätsvorschau!AF29*(1+VSt) -> 0 | AG30: =+Rentabilitätsvorschau!AG29*(1+VSt) -> 0 | AH30: =+Rentabilitätsvorschau!AH29*(1+VSt) -> 0 | AI30: =+Rentabilitätsvorschau!AI29*(1+VSt) -> 0 | AJ30: =+Rentabilitätsvorschau!AJ29*(1+VSt) -> 0 | AK30: =+Rentabilitätsvorschau!AK29*(1+VSt) -> 0 | ... AO30: =+Rentabilitätsvorschau!AO29*(1+VSt) -> 0 | AP30: =SUM(AD30:AO30) -> 0 | AQ30: =+Rentabilitätsvorschau!AQ29*(1+VSt) -> 0 | AR30: =+Rentabilitätsvorschau!AR29*(1+VSt) -> 0 | AS30: =+Rentabilitätsvorschau!AS29*(1+VSt) -> 0 | AT30: =+Rentabilitätsvorschau!AT29*(1+VSt) -> 0 | AU30: =+Rentabilitätsvorschau!AU29*(1+VSt) -> 0 | AV30: =+Rentabilitätsvorschau!AV29*(1+VSt) -> 0 | AW30: =+Rentabilitätsvorschau!AW29*(1+VSt) -> 0 | AX30: =+Rentabilitätsvorschau!AX29*(1+VSt) -> 0 | ... BB30: =+Rentabilitätsvorschau!BB29*(1+VSt) -> 0 | BC30: =SUM(AQ30:BB30) -> 0
C31: =+Rentabilitätsvorschau!C30 -> Provisionen | D31: =+Rentabilitätsvorschau!D30*(1+VSteins) -> 0 | E31: =+Rentabilitätsvorschau!E30*(1+VSteins) -> 0 | F31: =+Rentabilitätsvorschau!F30*(1+VSteins) -> 0 | G31: =+Rentabilitätsvorschau!G30*(1+VSteins) -> 0 | H31: =+Rentabilitätsvorschau!H30*(1+VSteins) -> 0 | I31: =+Rentabilitätsvorschau!I30*(1+VSteins) -> 0 | J31: =+Rentabilitätsvorschau!J30*(1+VSteins) -> 0 | K31: =+Rentabilitätsvorschau!K30*(1+VSteins) -> 0 | ... O31: =+Rentabilitätsvorschau!O30*(1+VSteins) -> 0 | P31: =SUM(D31:O31) -> 0 | Q31: =+Rentabilitätsvorschau!Q30*(1+VSt) -> 0 | R31: =+Rentabilitätsvorschau!R30*(1+VSt) -> 0 | S31: =+Rentabilitätsvorschau!S30*(1+VSt) -> 0 | T31: =+Rentabilitätsvorschau!T30*(1+VSt) -> 0 | U31: =+Rentabilitätsvorschau!U30*(1+VSt) -> 0 | V31: =+Rentabilitätsvorschau!V30*(1+VSt) -> 0 | W31: =+Rentabilitätsvorschau!W30*(1+VSt) -> 0 | X31: =+Rentabilitätsvorschau!X30*(1+VSt) -> 0 | ... AB31: =+Rentabilitätsvorschau!AB30*(1+VSt) -> 0 | AC31: =SUM(Q31:AB31) -> 0 | AD31: =+Rentabilitätsvorschau!AD30*(1+VSt) -> 0 | AE31: =+Rentabilitätsvorschau!AE30*(1+VSt) -> 0 | AF31: =+Rentabilitätsvorschau!AF30*(1+VSt) -> 0 | AG31: =+Rentabilitätsvorschau!AG30*(1+VSt) -> 0 | AH31: =+Rentabilitätsvorschau!AH30*(1+VSt) -> 0 | AI31: =+Rentabilitätsvorschau!AI30*(1+VSt) -> 0 | AJ31: =+Rentabilitätsvorschau!AJ30*(1+VSt) -> 0 | AK31: =+Rentabilitätsvorschau!AK30*(1+VSt) -> 0 | ... AO31: =+Rentabilitätsvorschau!AO30*(1+VSt) -> 0 | AP31: =SUM(AD31:AO31) -> 0 | AQ31: =+Rentabilitätsvorschau!AQ30*(1+VSt) -> 0 | AR31: =+Rentabilitätsvorschau!AR30*(1+VSt) -> 0 | AS31: =+Rentabilitätsvorschau!AS30*(1+VSt) -> 0 | AT31: =+Rentabilitätsvorschau!AT30*(1+VSt) -> 0 | AU31: =+Rentabilitätsvorschau!AU30*(1+VSt) -> 0 | AV31: =+Rentabilitätsvorschau!AV30*(1+VSt) -> 0 | AW31: =+Rentabilitätsvorschau!AW30*(1+VSt) -> 0 | AX31: =+Rentabilitätsvorschau!AX30*(1+VSt) -> 0 | ... BB31: =+Rentabilitätsvorschau!BB30*(1+VSt) -> 0 | BC31: =SUM(AQ31:BB31) -> 0
B32: =+Rentabilitätsvorschau!B31 -> Instandhaltung Betriebs- und Geschäftsausstattung | D32: =+Rentabilitätsvorschau!D31*(1+VSteins) -> 0 | E32: =+Rentabilitätsvorschau!E31*(1+VSteins) -> 0 | F32: =+Rentabilitätsvorschau!F31*(1+VSteins) -> 0 | G32: =+Rentabilitätsvorschau!G31*(1+VSteins) -> 0 | H32: =+Rentabilitätsvorschau!H31*(1+VSteins) -> 0 | I32: =+Rentabilitätsvorschau!I31*(1+VSteins) -> 0 | J32: =+Rentabilitätsvorschau!J31*(1+VSteins) -> 0 | K32: =+Rentabilitätsvorschau!K31*(1+VSteins) -> 0 | ... O32: =+Rentabilitätsvorschau!O31*(1+VSteins) -> 0 | P32: =SUM(D32:O32) -> 0 | Q32: =+Rentabilitätsvorschau!Q31*(1+VSt) -> 0 | R32: =+Rentabilitätsvorschau!R31*(1+VSt) -> 0 | S32: =+Rentabilitätsvorschau!S31*(1+VSt) -> 0 | T32: =+Rentabilitätsvorschau!T31*(1+VSt) -> 0 | U32: =+Rentabilitätsvorschau!U31*(1+VSt) -> 0 | V32: =+Rentabilitätsvorschau!V31*(1+VSt) -> 0 | W32: =+Rentabilitätsvorschau!W31*(1+VSt) -> 0 | X32: =+Rentabilitätsvorschau!X31*(1+VSt) -> 0 | ... AB32: =+Rentabilitätsvorschau!AB31*(1+VSt) -> 0 | AC32: =SUM(Q32:AB32) -> 0 | AD32: =+Rentabilitätsvorschau!AD31*(1+VSt) -> 0 | AE32: =+Rentabilitätsvorschau!AE31*(1+VSt) -> 0 | AF32: =+Rentabilitätsvorschau!AF31*(1+VSt) -> 0 | AG32: =+Rentabilitätsvorschau!AG31*(1+VSt) -> 0 | AH32: =+Rentabilitätsvorschau!AH31*(1+VSt) -> 0 | AI32: =+Rentabilitätsvorschau!AI31*(1+VSt) -> 0 | AJ32: =+Rentabilitätsvorschau!AJ31*(1+VSt) -> 0 | AK32: =+Rentabilitätsvorschau!AK31*(1+VSt) -> 0 | ... AO32: =+Rentabilitätsvorschau!AO31*(1+VSt) -> 0 | AP32: =SUM(AD32:AO32) -> 0 | AQ32: =+Rentabilitätsvorschau!AQ31*(1+VSt) -> 0 | AR32: =+Rentabilitätsvorschau!AR31*(1+VSt) -> 0 | AS32: =+Rentabilitätsvorschau!AS31*(1+VSt) -> 0 | AT32: =+Rentabilitätsvorschau!AT31*(1+VSt) -> 0 | AU32: =+Rentabilitätsvorschau!AU31*(1+VSt) -> 0 | AV32: =+Rentabilitätsvorschau!AV31*(1+VSt) -> 0 | AW32: =+Rentabilitätsvorschau!AW31*(1+VSt) -> 0 | AX32: =+Rentabilitätsvorschau!AX31*(1+VSt) -> 0 | ... BB32: =+Rentabilitätsvorschau!BB31*(1+VSt) -> 0 | BC32: =SUM(AQ32:BB32) -> 0
B33: =+Rentabilitätsvorschau!B32 -> Leasing (außer Kfz) | D33: =+Rentabilitätsvorschau!D32*(1+VSteins) -> 0 | E33: =+Rentabilitätsvorschau!E32*(1+VSteins) -> 0 | F33: =+Rentabilitätsvorschau!F32*(1+VSteins) -> 0 | G33: =+Rentabilitätsvorschau!G32*(1+VSteins) -> 0 | H33: =+Rentabilitätsvorschau!H32*(1+VSteins) -> 0 | I33: =+Rentabilitätsvorschau!I32*(1+VSteins) -> 0 | J33: =+Rentabilitätsvorschau!J32*(1+VSteins) -> 0 | K33: =+Rentabilitätsvorschau!K32*(1+VSteins) -> 0 | ... O33: =+Rentabilitätsvorschau!O32*(1+VSteins) -> 0 | P33: =SUM(D33:O33) -> 0 | Q33: =+Rentabilitätsvorschau!Q32*(1+VSt) -> 0 | R33: =+Rentabilitätsvorschau!R32*(1+VSt) -> 0 | S33: =+Rentabilitätsvorschau!S32*(1+VSt) -> 0 | T33: =+Rentabilitätsvorschau!T32*(1+VSt) -> 0 | U33: =+Rentabilitätsvorschau!U32*(1+VSt) -> 0 | V33: =+Rentabilitätsvorschau!V32*(1+VSt) -> 0 | W33: =+Rentabilitätsvorschau!W32*(1+VSt) -> 0 | X33: =+Rentabilitätsvorschau!X32*(1+VSt) -> 0 | ... AB33: =+Rentabilitätsvorschau!AB32*(1+VSt) -> 0 | AC33: =SUM(Q33:AB33) -> 0 | AD33: =+Rentabilitätsvorschau!AD32*(1+VSt) -> 0 | AE33: =+Rentabilitätsvorschau!AE32*(1+VSt) -> 0 | AF33: =+Rentabilitätsvorschau!AF32*(1+VSt) -> 0 | AG33: =+Rentabilitätsvorschau!AG32*(1+VSt) -> 0 | AH33: =+Rentabilitätsvorschau!AH32*(1+VSt) -> 0 | AI33: =+Rentabilitätsvorschau!AI32*(1+VSt) -> 0 | AJ33: =+Rentabilitätsvorschau!AJ32*(1+VSt) -> 0 | AK33: =+Rentabilitätsvorschau!AK32*(1+VSt) -> 0 | ... AO33: =+Rentabilitätsvorschau!AO32*(1+VSt) -> 0 | AP33: =SUM(AD33:AO33) -> 0 | AQ33: =+Rentabilitätsvorschau!AQ32*(1+VSt) -> 0 | AR33: =+Rentabilitätsvorschau!AR32*(1+VSt) -> 0 | AS33: =+Rentabilitätsvorschau!AS32*(1+VSt) -> 0 | AT33: =+Rentabilitätsvorschau!AT32*(1+VSt) -> 0 | AU33: =+Rentabilitätsvorschau!AU32*(1+VSt) -> 0 | AV33: =+Rentabilitätsvorschau!AV32*(1+VSt) -> 0 | AW33: =+Rentabilitätsvorschau!AW32*(1+VSt) -> 0 | AX33: =+Rentabilitätsvorschau!AX32*(1+VSt) -> 0 | ... BB33: =+Rentabilitätsvorschau!BB32*(1+VSt) -> 0 | BC33: =SUM(AQ33:BB33) -> 0
B34: =+Rentabilitätsvorschau!B33 -> Software-Updates | D34: =+Rentabilitätsvorschau!D33*(1+VSteins) -> 0 | E34: =+Rentabilitätsvorschau!E33*(1+VSteins) -> 0 | F34: =+Rentabilitätsvorschau!F33*(1+VSteins) -> 0 | G34: =+Rentabilitätsvorschau!G33*(1+VSteins) -> 0 | H34: =+Rentabilitätsvorschau!H33*(1+VSteins) -> 0 | I34: =+Rentabilitätsvorschau!I33*(1+VSteins) -> 0 | J34: =+Rentabilitätsvorschau!J33*(1+VSteins) -> 0 | K34: =+Rentabilitätsvorschau!K33*(1+VSteins) -> 0 | ... O34: =+Rentabilitätsvorschau!O33*(1+VSteins) -> 47.6 | P34: =SUM(D34:O34) -> 142.8 | Q34: =+Rentabilitätsvorschau!Q33*(1+VSt) -> 47.6 | R34: =+Rentabilitätsvorschau!R33*(1+VSt) -> 47.6 | S34: =+Rentabilitätsvorschau!S33*(1+VSt) -> 47.6 | T34: =+Rentabilitätsvorschau!T33*(1+VSt) -> 47.6 | U34: =+Rentabilitätsvorschau!U33*(1+VSt) -> 47.6 | V34: =+Rentabilitätsvorschau!V33*(1+VSt) -> 47.6 | W34: =+Rentabilitätsvorschau!W33*(1+VSt) -> 47.6 | X34: =+Rentabilitätsvorschau!X33*(1+VSt) -> 47.6 | ... AB34: =+Rentabilitätsvorschau!AB33*(1+VSt) -> 47.6 | AC34: =SUM(Q34:AB34) -> 571.2 | AD34: =+Rentabilitätsvorschau!AD33*(1+VSt) -> 0 | AE34: =+Rentabilitätsvorschau!AE33*(1+VSt) -> 0 | AF34: =+Rentabilitätsvorschau!AF33*(1+VSt) -> 0 | AG34: =+Rentabilitätsvorschau!AG33*(1+VSt) -> 0 | AH34: =+Rentabilitätsvorschau!AH33*(1+VSt) -> 0 | AI34: =+Rentabilitätsvorschau!AI33*(1+VSt) -> 0 | AJ34: =+Rentabilitätsvorschau!AJ33*(1+VSt) -> 0 | AK34: =+Rentabilitätsvorschau!AK33*(1+VSt) -> 0 | ... AO34: =+Rentabilitätsvorschau!AO33*(1+VSt) -> 0 | AP34: =SUM(AD34:AO34) -> 0 | AQ34: =+Rentabilitätsvorschau!AQ33*(1+VSt) -> 0 | AR34: =+Rentabilitätsvorschau!AR33*(1+VSt) -> 0 | AS34: =+Rentabilitätsvorschau!AS33*(1+VSt) -> 0 | AT34: =+Rentabilitätsvorschau!AT33*(1+VSt) -> 0 | AU34: =+Rentabilitätsvorschau!AU33*(1+VSt) -> 0 | AV34: =+Rentabilitätsvorschau!AV33*(1+VSt) -> 0 | AW34: =+Rentabilitätsvorschau!AW33*(1+VSt) -> 0 | AX34: =+Rentabilitätsvorschau!AX33*(1+VSt) -> 0 | ... BB34: =+Rentabilitätsvorschau!BB33*(1+VSt) -> 0 | BC34: =SUM(AQ34:BB34) -> 0
B35: =+Rentabilitätsvorschau!B34 -> Versicherungen (ohne Kfz) | D35: =+Rentabilitätsvorschau!D34 -> 0 | E35: =+Rentabilitätsvorschau!E34 -> 0 | F35: =+Rentabilitätsvorschau!F34 -> 0 | G35: =+Rentabilitätsvorschau!G34 -> 0 | H35: =+Rentabilitätsvorschau!H34 -> 0 | I35: =+Rentabilitätsvorschau!I34 -> 0 | J35: =+Rentabilitätsvorschau!J34 -> 0 | K35: =+Rentabilitätsvorschau!K34 -> 0 | ... O35: =+Rentabilitätsvorschau!O34 -> 40 | P35: =SUM(D35:O35) -> 120 | Q35: =+Rentabilitätsvorschau!Q34 -> 40 | R35: =+Rentabilitätsvorschau!R34 -> 40 | S35: =+Rentabilitätsvorschau!S34 -> 40 | T35: =+Rentabilitätsvorschau!T34 -> 40 | U35: =+Rentabilitätsvorschau!U34 -> 40 | V35: =+Rentabilitätsvorschau!V34 -> 40 | W35: =+Rentabilitätsvorschau!W34 -> 40 | X35: =+Rentabilitätsvorschau!X34 -> 40 | ... AB35: =+Rentabilitätsvorschau!AB34 -> 40 | AC35: =SUM(Q35:AB35) -> 480 | AD35: =+Rentabilitätsvorschau!AD34 -> 0 | AE35: =+Rentabilitätsvorschau!AE34 -> 0 | AF35: =+Rentabilitätsvorschau!AF34 -> 0 | AG35: =+Rentabilitätsvorschau!AG34 -> 0 | AH35: =+Rentabilitätsvorschau!AH34 -> 0 | AI35: =+Rentabilitätsvorschau!AI34 -> 0 | AJ35: =+Rentabilitätsvorschau!AJ34 -> 0 | AK35: =+Rentabilitätsvorschau!AK34 -> 0 | ... AO35: =+Rentabilitätsvorschau!AO34 -> 0 | AP35: =SUM(AD35:AO35) -> 0 | AQ35: =+Rentabilitätsvorschau!AQ34 -> 0 | AR35: =+Rentabilitätsvorschau!AR34 -> 0 | AS35: =+Rentabilitätsvorschau!AS34 -> 0 | AT35: =+Rentabilitätsvorschau!AT34 -> 0 | AU35: =+Rentabilitätsvorschau!AU34 -> 0 | AV35: =+Rentabilitätsvorschau!AV34 -> 0 | AW35: =+Rentabilitätsvorschau!AW34 -> 0 | AX35: =+Rentabilitätsvorschau!AX34 -> 0 | ... BB35: =+Rentabilitätsvorschau!BB34 -> 0 | BC35: =SUM(AQ35:BB35) -> 0
B36: =+Rentabilitätsvorschau!B35 -> Beiträge, Gebühren | D36: =+Rentabilitätsvorschau!D35 -> 0 | E36: =+Rentabilitätsvorschau!E35 -> 0 | F36: =+Rentabilitätsvorschau!F35 -> 0 | G36: =+Rentabilitätsvorschau!G35 -> 0 | H36: =+Rentabilitätsvorschau!H35 -> 0 | I36: =+Rentabilitätsvorschau!I35 -> 0 | J36: =+Rentabilitätsvorschau!J35 -> 0 | K36: =+Rentabilitätsvorschau!K35 -> 0 | ... O36: =+Rentabilitätsvorschau!O35 -> 15 | P36: =SUM(D36:O36) -> 45 | Q36: =+Rentabilitätsvorschau!Q35 -> 15 | R36: =+Rentabilitätsvorschau!R35 -> 15 | S36: =+Rentabilitätsvorschau!S35 -> 15 | T36: =+Rentabilitätsvorschau!T35 -> 15 | U36: =+Rentabilitätsvorschau!U35 -> 15 | V36: =+Rentabilitätsvorschau!V35 -> 15 | W36: =+Rentabilitätsvorschau!W35 -> 15 | X36: =+Rentabilitätsvorschau!X35 -> 15 | ... AB36: =+Rentabilitätsvorschau!AB35 -> 15 | AC36: =SUM(Q36:AB36) -> 180 | AD36: =+Rentabilitätsvorschau!AD35 -> 0 | AE36: =+Rentabilitätsvorschau!AE35 -> 0 | AF36: =+Rentabilitätsvorschau!AF35 -> 0 | AG36: =+Rentabilitätsvorschau!AG35 -> 0 | AH36: =+Rentabilitätsvorschau!AH35 -> 0 | AI36: =+Rentabilitätsvorschau!AI35 -> 0 | AJ36: =+Rentabilitätsvorschau!AJ35 -> 0 | AK36: =+Rentabilitätsvorschau!AK35 -> 0 | ... AO36: =+Rentabilitätsvorschau!AO35 -> 0 | AP36: =SUM(AD36:AO36) -> 0 | AQ36: =+Rentabilitätsvorschau!AQ35 -> 0 | AR36: =+Rentabilitätsvorschau!AR35 -> 0 | AS36: =+Rentabilitätsvorschau!AS35 -> 0 | AT36: =+Rentabilitätsvorschau!AT35 -> 0 | AU36: =+Rentabilitätsvorschau!AU35 -> 0 | AV36: =+Rentabilitätsvorschau!AV35 -> 0 | AW36: =+Rentabilitätsvorschau!AW35 -> 0 | AX36: =+Rentabilitätsvorschau!AX35 -> 0 | ... BB36: =+Rentabilitätsvorschau!BB35 -> 0 | BC36: =SUM(AQ36:BB36) -> 0
B37: =+Rentabilitätsvorschau!B36 -> Bürobedarf | D37: =+Rentabilitätsvorschau!D36*(1+VSteins) -> 0 | E37: =+Rentabilitätsvorschau!E36*(1+VSteins) -> 0 | F37: =+Rentabilitätsvorschau!F36*(1+VSteins) -> 0 | G37: =+Rentabilitätsvorschau!G36*(1+VSteins) -> 0 | H37: =+Rentabilitätsvorschau!H36*(1+VSteins) -> 0 | I37: =+Rentabilitätsvorschau!I36*(1+VSteins) -> 0 | J37: =+Rentabilitätsvorschau!J36*(1+VSteins) -> 0 | K37: =+Rentabilitätsvorschau!K36*(1+VSteins) -> 0 | ... O37: =+Rentabilitätsvorschau!O36*(1+VSteins) -> 35.7 | P37: =SUM(D37:O37) -> 107.1 | Q37: =+Rentabilitätsvorschau!Q36*(1+VSt) -> 35.7 | R37: =+Rentabilitätsvorschau!R36*(1+VSt) -> 35.7 | S37: =+Rentabilitätsvorschau!S36*(1+VSt) -> 35.7 | T37: =+Rentabilitätsvorschau!T36*(1+VSt) -> 35.7 | U37: =+Rentabilitätsvorschau!U36*(1+VSt) -> 35.7 | V37: =+Rentabilitätsvorschau!V36*(1+VSt) -> 35.7 | W37: =+Rentabilitätsvorschau!W36*(1+VSt) -> 35.7 | X37: =+Rentabilitätsvorschau!X36*(1+VSt) -> 35.7 | ... AB37: =+Rentabilitätsvorschau!AB36*(1+VSt) -> 35.7 | AC37: =SUM(Q37:AB37) -> 428.4 | AD37: =+Rentabilitätsvorschau!AD36*(1+VSt) -> 0 | AE37: =+Rentabilitätsvorschau!AE36*(1+VSt) -> 0 | AF37: =+Rentabilitätsvorschau!AF36*(1+VSt) -> 0 | AG37: =+Rentabilitätsvorschau!AG36*(1+VSt) -> 0 | AH37: =+Rentabilitätsvorschau!AH36*(1+VSt) -> 0 | AI37: =+Rentabilitätsvorschau!AI36*(1+VSt) -> 0 | AJ37: =+Rentabilitätsvorschau!AJ36*(1+VSt) -> 0 | AK37: =+Rentabilitätsvorschau!AK36*(1+VSt) -> 0 | ... AO37: =+Rentabilitätsvorschau!AO36*(1+VSt) -> 0 | AP37: =SUM(AD37:AO37) -> 0 | AQ37: =+Rentabilitätsvorschau!AQ36*(1+VSt) -> 0 | AR37: =+Rentabilitätsvorschau!AR36*(1+VSt) -> 0 | AS37: =+Rentabilitätsvorschau!AS36*(1+VSt) -> 0 | AT37: =+Rentabilitätsvorschau!AT36*(1+VSt) -> 0 | AU37: =+Rentabilitätsvorschau!AU36*(1+VSt) -> 0 | AV37: =+Rentabilitätsvorschau!AV36*(1+VSt) -> 0 | AW37: =+Rentabilitätsvorschau!AW36*(1+VSt) -> 0 | AX37: =+Rentabilitätsvorschau!AX36*(1+VSt) -> 0 | ... BB37: =+Rentabilitätsvorschau!BB36*(1+VSt) -> 0 | BC37: =SUM(AQ37:BB37) -> 0
B38: =+Rentabilitätsvorschau!B37 -> Postwertzeichen | D38: =+Rentabilitätsvorschau!D37 -> 0 | E38: =+Rentabilitätsvorschau!E37 -> 0 | F38: =+Rentabilitätsvorschau!F37 -> 0 | G38: =+Rentabilitätsvorschau!G37 -> 0 | H38: =+Rentabilitätsvorschau!H37 -> 0 | I38: =+Rentabilitätsvorschau!I37 -> 0 | J38: =+Rentabilitätsvorschau!J37 -> 0 | K38: =+Rentabilitätsvorschau!K37 -> 0 | ... O38: =+Rentabilitätsvorschau!O37 -> 10 | P38: =SUM(D38:O38) -> 30 | Q38: =+Rentabilitätsvorschau!Q37 -> 10 | R38: =+Rentabilitätsvorschau!R37 -> 10 | S38: =+Rentabilitätsvorschau!S37 -> 10 | T38: =+Rentabilitätsvorschau!T37 -> 10 | U38: =+Rentabilitätsvorschau!U37 -> 10 | V38: =+Rentabilitätsvorschau!V37 -> 10 | W38: =+Rentabilitätsvorschau!W37 -> 10 | X38: =+Rentabilitätsvorschau!X37 -> 10 | ... AB38: =+Rentabilitätsvorschau!AB37 -> 10 | AC38: =SUM(Q38:AB38) -> 120 | AD38: =+Rentabilitätsvorschau!AD37 -> 0 | AE38: =+Rentabilitätsvorschau!AE37 -> 0 | AF38: =+Rentabilitätsvorschau!AF37 -> 0 | AG38: =+Rentabilitätsvorschau!AG37 -> 0 | AH38: =+Rentabilitätsvorschau!AH37 -> 0 | AI38: =+Rentabilitätsvorschau!AI37 -> 0 | AJ38: =+Rentabilitätsvorschau!AJ37 -> 0 | AK38: =+Rentabilitätsvorschau!AK37 -> 0 | ... AO38: =+Rentabilitätsvorschau!AO37 -> 0 | AP38: =SUM(AD38:AO38) -> 0 | AQ38: =+Rentabilitätsvorschau!AQ37 -> 0 | AR38: =+Rentabilitätsvorschau!AR37 -> 0 | AS38: =+Rentabilitätsvorschau!AS37 -> 0 | AT38: =+Rentabilitätsvorschau!AT37 -> 0 | AU38: =+Rentabilitätsvorschau!AU37 -> 0 | AV38: =+Rentabilitätsvorschau!AV37 -> 0 | AW38: =+Rentabilitätsvorschau!AW37 -> 0 | AX38: =+Rentabilitätsvorschau!AX37 -> 0 | ... BB38: =+Rentabilitätsvorschau!BB37 -> 0 | BC38: =SUM(AQ38:BB38) -> 0
B39: =+Rentabilitätsvorschau!B38 -> Fachliteratur | D39: =+Rentabilitätsvorschau!D38*(1+VStermeins) -> 0 | E39: =+Rentabilitätsvorschau!E38*(1+VStermeins) -> 0 | F39: =+Rentabilitätsvorschau!F38*(1+VStermeins) -> 0 | G39: =+Rentabilitätsvorschau!G38*(1+VStermeins) -> 0 | H39: =+Rentabilitätsvorschau!H38*(1+VStermeins) -> 0 | I39: =+Rentabilitätsvorschau!I38*(1+VStermeins) -> 0 | J39: =+Rentabilitätsvorschau!J38*(1+VStermeins) -> 0 | K39: =+Rentabilitätsvorschau!K38*(1+VStermeins) -> 0 | ... O39: =+Rentabilitätsvorschau!O38*(1+VStermeins) -> 21.4 | P39: =SUM(D39:O39) -> 64.2 | Q39: =+Rentabilitätsvorschau!Q38*(1+VSterm) -> 21.4 | R39: =+Rentabilitätsvorschau!R38*(1+VSterm) -> 21.4 | S39: =+Rentabilitätsvorschau!S38*(1+VSterm) -> 21.4 | T39: =+Rentabilitätsvorschau!T38*(1+VSterm) -> 21.4 | U39: =+Rentabilitätsvorschau!U38*(1+VSterm) -> 21.4 | V39: =+Rentabilitätsvorschau!V38*(1+VSterm) -> 21.4 | W39: =+Rentabilitätsvorschau!W38*(1+VSterm) -> 21.4 | X39: =+Rentabilitätsvorschau!X38*(1+VSterm) -> 21.4 | ... AB39: =+Rentabilitätsvorschau!AB38*(1+VSterm) -> 21.4 | AC39: =SUM(Q39:AB39) -> 256.8 | AD39: =+Rentabilitätsvorschau!AD38*(1+VSterm) -> 0 | AE39: =+Rentabilitätsvorschau!AE38*(1+VSterm) -> 0 | AF39: =+Rentabilitätsvorschau!AF38*(1+VSterm) -> 0 | AG39: =+Rentabilitätsvorschau!AG38*(1+VSterm) -> 0 | AH39: =+Rentabilitätsvorschau!AH38*(1+VSterm) -> 0 | AI39: =+Rentabilitätsvorschau!AI38*(1+VSterm) -> 0 | AJ39: =+Rentabilitätsvorschau!AJ38*(1+VSterm) -> 0 | AK39: =+Rentabilitätsvorschau!AK38*(1+VSterm) -> 0 | ... AO39: =+Rentabilitätsvorschau!AO38*(1+VSterm) -> 0 | AP39: =SUM(AD39:AO39) -> 0 | AQ39: =+Rentabilitätsvorschau!AQ38*(1+VSterm) -> 0 | AR39: =+Rentabilitätsvorschau!AR38*(1+VSterm) -> 0 | AS39: =+Rentabilitätsvorschau!AS38*(1+VSterm) -> 0 | AT39: =+Rentabilitätsvorschau!AT38*(1+VSterm) -> 0 | AU39: =+Rentabilitätsvorschau!AU38*(1+VSterm) -> 0 | AV39: =+Rentabilitätsvorschau!AV38*(1+VSterm) -> 0 | AW39: =+Rentabilitätsvorschau!AW38*(1+VSterm) -> 0 | AX39: =+Rentabilitätsvorschau!AX38*(1+VSterm) -> 0 | ... BB39: =+Rentabilitätsvorschau!BB38*(1+VSterm) -> 0 | BC39: =SUM(AQ39:BB39) -> 0
B40: =+Rentabilitätsvorschau!B39 -> Fortbildung | D40: =+Rentabilitätsvorschau!D39*(1+VSteins) -> 0 | E40: =+Rentabilitätsvorschau!E39*(1+VSteins) -> 0 | F40: =+Rentabilitätsvorschau!F39*(1+VSteins) -> 0 | G40: =+Rentabilitätsvorschau!G39*(1+VSteins) -> 0 | H40: =+Rentabilitätsvorschau!H39*(1+VSteins) -> 0 | I40: =+Rentabilitätsvorschau!I39*(1+VSteins) -> 0 | J40: =+Rentabilitätsvorschau!J39*(1+VSteins) -> 0 | K40: =+Rentabilitätsvorschau!K39*(1+VSteins) -> 0 | ... O40: =+Rentabilitätsvorschau!O39*(1+VSteins) -> 0 | P40: =SUM(D40:O40) -> 0 | Q40: =+Rentabilitätsvorschau!Q39*(1+VSt) -> 0 | R40: =+Rentabilitätsvorschau!R39*(1+VSt) -> 0 | S40: =+Rentabilitätsvorschau!S39*(1+VSt) -> 0 | T40: =+Rentabilitätsvorschau!T39*(1+VSt) -> 0 | U40: =+Rentabilitätsvorschau!U39*(1+VSt) -> 0 | V40: =+Rentabilitätsvorschau!V39*(1+VSt) -> 0 | W40: =+Rentabilitätsvorschau!W39*(1+VSt) -> 0 | X40: =+Rentabilitätsvorschau!X39*(1+VSt) -> 0 | ... AB40: =+Rentabilitätsvorschau!AB39*(1+VSt) -> 0 | AC40: =SUM(Q40:AB40) -> 0 | AD40: =+Rentabilitätsvorschau!AD39*(1+VSt) -> 0 | AE40: =+Rentabilitätsvorschau!AE39*(1+VSt) -> 0 | AF40: =+Rentabilitätsvorschau!AF39*(1+VSt) -> 0 | AG40: =+Rentabilitätsvorschau!AG39*(1+VSt) -> 0 | AH40: =+Rentabilitätsvorschau!AH39*(1+VSt) -> 0 | AI40: =+Rentabilitätsvorschau!AI39*(1+VSt) -> 0 | AJ40: =+Rentabilitätsvorschau!AJ39*(1+VSt) -> 0 | AK40: =+Rentabilitätsvorschau!AK39*(1+VSt) -> 0 | ... AO40: =+Rentabilitätsvorschau!AO39*(1+VSt) -> 0 | AP40: =SUM(AD40:AO40) -> 0 | AQ40: =+Rentabilitätsvorschau!AQ39*(1+VSt) -> 0 | AR40: =+Rentabilitätsvorschau!AR39*(1+VSt) -> 0 | AS40: =+Rentabilitätsvorschau!AS39*(1+VSt) -> 0 | AT40: =+Rentabilitätsvorschau!AT39*(1+VSt) -> 0 | AU40: =+Rentabilitätsvorschau!AU39*(1+VSt) -> 0 | AV40: =+Rentabilitätsvorschau!AV39*(1+VSt) -> 0 | AW40: =+Rentabilitätsvorschau!AW39*(1+VSt) -> 0 | AX40: =+Rentabilitätsvorschau!AX39*(1+VSt) -> 0 | ... BB40: =+Rentabilitätsvorschau!BB39*(1+VSt) -> 0 | BC40: =SUM(AQ40:BB40) -> 0
B41: =+Rentabilitätsvorschau!B40 -> Messen und Ausstellungen | D41: =+Rentabilitätsvorschau!D40*(1+VSteins) -> 0 | E41: =+Rentabilitätsvorschau!E40*(1+VSteins) -> 0 | F41: =+Rentabilitätsvorschau!F40*(1+VSteins) -> 0 | G41: =+Rentabilitätsvorschau!G40*(1+VSteins) -> 0 | H41: =+Rentabilitätsvorschau!H40*(1+VSteins) -> 0 | I41: =+Rentabilitätsvorschau!I40*(1+VSteins) -> 0 | J41: =+Rentabilitätsvorschau!J40*(1+VSteins) -> 0 | K41: =+Rentabilitätsvorschau!K40*(1+VSteins) -> 0 | ... O41: =+Rentabilitätsvorschau!O40*(1+VSteins) -> 0 | P41: =SUM(D41:O41) -> 0 | Q41: =+Rentabilitätsvorschau!Q40*(1+VSt) -> 0 | R41: =+Rentabilitätsvorschau!R40*(1+VSt) -> 0 | S41: =+Rentabilitätsvorschau!S40*(1+VSt) -> 0 | T41: =+Rentabilitätsvorschau!T40*(1+VSt) -> 0 | U41: =+Rentabilitätsvorschau!U40*(1+VSt) -> 0 | V41: =+Rentabilitätsvorschau!V40*(1+VSt) -> 0 | W41: =+Rentabilitätsvorschau!W40*(1+VSt) -> 0 | X41: =+Rentabilitätsvorschau!X40*(1+VSt) -> 0 | ... AB41: =+Rentabilitätsvorschau!AB40*(1+VSt) -> 0 | AC41: =SUM(Q41:AB41) -> 0 | AD41: =+Rentabilitätsvorschau!AD40*(1+VSt) -> 0 | AE41: =+Rentabilitätsvorschau!AE40*(1+VSt) -> 0 | AF41: =+Rentabilitätsvorschau!AF40*(1+VSt) -> 0 | AG41: =+Rentabilitätsvorschau!AG40*(1+VSt) -> 0 | AH41: =+Rentabilitätsvorschau!AH40*(1+VSt) -> 0 | AI41: =+Rentabilitätsvorschau!AI40*(1+VSt) -> 0 | AJ41: =+Rentabilitätsvorschau!AJ40*(1+VSt) -> 0 | AK41: =+Rentabilitätsvorschau!AK40*(1+VSt) -> 0 | ... AO41: =+Rentabilitätsvorschau!AO40*(1+VSt) -> 0 | AP41: =SUM(AD41:AO41) -> 0 | AQ41: =+Rentabilitätsvorschau!AQ40*(1+VSt) -> 0 | AR41: =+Rentabilitätsvorschau!AR40*(1+VSt) -> 0 | AS41: =+Rentabilitätsvorschau!AS40*(1+VSt) -> 0 | AT41: =+Rentabilitätsvorschau!AT40*(1+VSt) -> 0 | AU41: =+Rentabilitätsvorschau!AU40*(1+VSt) -> 0 | AV41: =+Rentabilitätsvorschau!AV40*(1+VSt) -> 0 | AW41: =+Rentabilitätsvorschau!AW40*(1+VSt) -> 0 | AX41: =+Rentabilitätsvorschau!AX40*(1+VSt) -> 0 | ... BB41: =+Rentabilitätsvorschau!BB40*(1+VSt) -> 0 | BC41: =SUM(AQ41:BB41) -> 0
B42: =+Rentabilitätsvorschau!B41 -> Beratungskosten
C43: =+Rentabilitätsvorschau!C42 -> Steuerberater | D43: =+Rentabilitätsvorschau!D42*(1+VSteins) -> 0 | E43: =+Rentabilitätsvorschau!E42*(1+VSteins) -> 0 | F43: =+Rentabilitätsvorschau!F42*(1+VSteins) -> 0 | G43: =+Rentabilitätsvorschau!G42*(1+VSteins) -> 0 | H43: =+Rentabilitätsvorschau!H42*(1+VSteins) -> 0 | I43: =+Rentabilitätsvorschau!I42*(1+VSteins) -> 0 | J43: =+Rentabilitätsvorschau!J42*(1+VSteins) -> 0 | K43: =+Rentabilitätsvorschau!K42*(1+VSteins) -> 0 | ... O43: =+Rentabilitätsvorschau!O42*(1+VSteins) -> 178.5 | P43: =SUM(D43:O43) -> 535.5 | Q43: =+Rentabilitätsvorschau!Q42*(1+VSt) -> 178.5 | R43: =+Rentabilitätsvorschau!R42*(1+VSt) -> 178.5 | S43: =+Rentabilitätsvorschau!S42*(1+VSt) -> 178.5 | T43: =+Rentabilitätsvorschau!T42*(1+VSt) -> 178.5 | U43: =+Rentabilitätsvorschau!U42*(1+VSt) -> 178.5 | V43: =+Rentabilitätsvorschau!V42*(1+VSt) -> 178.5 | W43: =+Rentabilitätsvorschau!W42*(1+VSt) -> 178.5 | X43: =+Rentabilitätsvorschau!X42*(1+VSt) -> 178.5 | ... AB43: =+Rentabilitätsvorschau!AB42*(1+VSt) -> 178.5 | AC43: =SUM(Q43:AB43) -> 2142 | AD43: =+Rentabilitätsvorschau!AD42*(1+VSt) -> 0 | AE43: =+Rentabilitätsvorschau!AE42*(1+VSt) -> 0 | AF43: =+Rentabilitätsvorschau!AF42*(1+VSt) -> 0 | AG43: =+Rentabilitätsvorschau!AG42*(1+VSt) -> 0 | AH43: =+Rentabilitätsvorschau!AH42*(1+VSt) -> 0 | AI43: =+Rentabilitätsvorschau!AI42*(1+VSt) -> 0 | AJ43: =+Rentabilitätsvorschau!AJ42*(1+VSt) -> 0 | AK43: =+Rentabilitätsvorschau!AK42*(1+VSt) -> 0 | ... AO43: =+Rentabilitätsvorschau!AO42*(1+VSt) -> 0 | AP43: =SUM(AD43:AO43) -> 0 | AQ43: =+Rentabilitätsvorschau!AQ42*(1+VSt) -> 0 | AR43: =+Rentabilitätsvorschau!AR42*(1+VSt) -> 0 | AS43: =+Rentabilitätsvorschau!AS42*(1+VSt) -> 0 | AT43: =+Rentabilitätsvorschau!AT42*(1+VSt) -> 0 | AU43: =+Rentabilitätsvorschau!AU42*(1+VSt) -> 0 | AV43: =+Rentabilitätsvorschau!AV42*(1+VSt) -> 0 | AW43: =+Rentabilitätsvorschau!AW42*(1+VSt) -> 0 | AX43: =+Rentabilitätsvorschau!AX42*(1+VSt) -> 0 | ... BB43: =+Rentabilitätsvorschau!BB42*(1+VSt) -> 0 | BC43: =SUM(AQ43:BB43) -> 0
C44: =+Rentabilitätsvorschau!C43 -> Unternehmensberater | D44: =+Rentabilitätsvorschau!D43*(1+VSteins) -> 0 | E44: =+Rentabilitätsvorschau!E43*(1+VSteins) -> 0 | F44: =+Rentabilitätsvorschau!F43*(1+VSteins) -> 0 | G44: =+Rentabilitätsvorschau!G43*(1+VSteins) -> 0 | H44: =+Rentabilitätsvorschau!H43*(1+VSteins) -> 0 | I44: =+Rentabilitätsvorschau!I43*(1+VSteins) -> 0 | J44: =+Rentabilitätsvorschau!J43*(1+VSteins) -> 0 | K44: =+Rentabilitätsvorschau!K43*(1+VSteins) -> 0 | ... O44: =+Rentabilitätsvorschau!O43*(1+VSteins) -> 0 | P44: =SUM(D44:O44) -> 0 | Q44: =+Rentabilitätsvorschau!Q43*(1+VSt) -> 0 | R44: =+Rentabilitätsvorschau!R43*(1+VSt) -> 0 | S44: =+Rentabilitätsvorschau!S43*(1+VSt) -> 0 | T44: =+Rentabilitätsvorschau!T43*(1+VSt) -> 0 | U44: =+Rentabilitätsvorschau!U43*(1+VSt) -> 0 | V44: =+Rentabilitätsvorschau!V43*(1+VSt) -> 0 | W44: =+Rentabilitätsvorschau!W43*(1+VSt) -> 0 | X44: =+Rentabilitätsvorschau!X43*(1+VSt) -> 0 | ... AB44: =+Rentabilitätsvorschau!AB43*(1+VSt) -> 0 | AC44: =SUM(Q44:AB44) -> 0 | AD44: =+Rentabilitätsvorschau!AD43*(1+VSt) -> 0 | AE44: =+Rentabilitätsvorschau!AE43*(1+VSt) -> 0 | AF44: =+Rentabilitätsvorschau!AF43*(1+VSt) -> 0 | AG44: =+Rentabilitätsvorschau!AG43*(1+VSt) -> 0 | AH44: =+Rentabilitätsvorschau!AH43*(1+VSt) -> 0 | AI44: =+Rentabilitätsvorschau!AI43*(1+VSt) -> 0 | AJ44: =+Rentabilitätsvorschau!AJ43*(1+VSt) -> 0 | AK44: =+Rentabilitätsvorschau!AK43*(1+VSt) -> 0 | ... AO44: =+Rentabilitätsvorschau!AO43*(1+VSt) -> 0 | AP44: =SUM(AD44:AO44) -> 0 | AQ44: =+Rentabilitätsvorschau!AQ43*(1+VSt) -> 0 | AR44: =+Rentabilitätsvorschau!AR43*(1+VSt) -> 0 | AS44: =+Rentabilitätsvorschau!AS43*(1+VSt) -> 0 | AT44: =+Rentabilitätsvorschau!AT43*(1+VSt) -> 0 | AU44: =+Rentabilitätsvorschau!AU43*(1+VSt) -> 0 | AV44: =+Rentabilitätsvorschau!AV43*(1+VSt) -> 0 | AW44: =+Rentabilitätsvorschau!AW43*(1+VSt) -> 0 | AX44: =+Rentabilitätsvorschau!AX43*(1+VSt) -> 0 | ... BB44: =+Rentabilitätsvorschau!BB43*(1+VSt) -> 0 | BC44: =SUM(AQ44:BB44) -> 0
C45: =+Rentabilitätsvorschau!C44 -> Rechtsanwalt | D45: =+Rentabilitätsvorschau!D44*(1+VSteins) -> 0 | E45: =+Rentabilitätsvorschau!E44*(1+VSteins) -> 0 | F45: =+Rentabilitätsvorschau!F44*(1+VSteins) -> 0 | G45: =+Rentabilitätsvorschau!G44*(1+VSteins) -> 0 | H45: =+Rentabilitätsvorschau!H44*(1+VSteins) -> 0 | I45: =+Rentabilitätsvorschau!I44*(1+VSteins) -> 0 | J45: =+Rentabilitätsvorschau!J44*(1+VSteins) -> 0 | K45: =+Rentabilitätsvorschau!K44*(1+VSteins) -> 0 | ... O45: =+Rentabilitätsvorschau!O44*(1+VSteins) -> 0 | P45: =SUM(D45:O45) -> 0 | Q45: =+Rentabilitätsvorschau!Q44*(1+VSt) -> 0 | R45: =+Rentabilitätsvorschau!R44*(1+VSt) -> 0 | S45: =+Rentabilitätsvorschau!S44*(1+VSt) -> 0 | T45: =+Rentabilitätsvorschau!T44*(1+VSt) -> 0 | U45: =+Rentabilitätsvorschau!U44*(1+VSt) -> 0 | V45: =+Rentabilitätsvorschau!V44*(1+VSt) -> 0 | W45: =+Rentabilitätsvorschau!W44*(1+VSt) -> 0 | X45: =+Rentabilitätsvorschau!X44*(1+VSt) -> 0 | ... AB45: =+Rentabilitätsvorschau!AB44*(1+VSt) -> 0 | AC45: =SUM(Q45:AB45) -> 0 | AD45: =+Rentabilitätsvorschau!AD44*(1+VSt) -> 0 | AE45: =+Rentabilitätsvorschau!AE44*(1+VSt) -> 0 | AF45: =+Rentabilitätsvorschau!AF44*(1+VSt) -> 0 | AG45: =+Rentabilitätsvorschau!AG44*(1+VSt) -> 0 | AH45: =+Rentabilitätsvorschau!AH44*(1+VSt) -> 0 | AI45: =+Rentabilitätsvorschau!AI44*(1+VSt) -> 0 | AJ45: =+Rentabilitätsvorschau!AJ44*(1+VSt) -> 0 | AK45: =+Rentabilitätsvorschau!AK44*(1+VSt) -> 0 | ... AO45: =+Rentabilitätsvorschau!AO44*(1+VSt) -> 0 | AP45: =SUM(AD45:AO45) -> 0 | AQ45: =+Rentabilitätsvorschau!AQ44*(1+VSt) -> 0 | AR45: =+Rentabilitätsvorschau!AR44*(1+VSt) -> 0 | AS45: =+Rentabilitätsvorschau!AS44*(1+VSt) -> 0 | AT45: =+Rentabilitätsvorschau!AT44*(1+VSt) -> 0 | AU45: =+Rentabilitätsvorschau!AU44*(1+VSt) -> 0 | AV45: =+Rentabilitätsvorschau!AV44*(1+VSt) -> 0 | AW45: =+Rentabilitätsvorschau!AW44*(1+VSt) -> 0 | AX45: =+Rentabilitätsvorschau!AX44*(1+VSt) -> 0 | ... BB45: =+Rentabilitätsvorschau!BB44*(1+VSt) -> 0 | BC45: =SUM(AQ45:BB45) -> 0
B46: =+Rentabilitätsvorschau!B45 -> Kosten des Geldverkehrs | D46: =+Rentabilitätsvorschau!D45 -> 0 | E46: =+Rentabilitätsvorschau!E45 -> 0 | F46: =+Rentabilitätsvorschau!F45 -> 0 | G46: =+Rentabilitätsvorschau!G45 -> 0 | H46: =+Rentabilitätsvorschau!H45 -> 0 | I46: =+Rentabilitätsvorschau!I45 -> 0 | J46: =+Rentabilitätsvorschau!J45 -> 0 | K46: =+Rentabilitätsvorschau!K45 -> 0 | ... O46: =+Rentabilitätsvorschau!O45 -> 20 | P46: =SUM(D46:O46) -> 60 | Q46: =+Rentabilitätsvorschau!Q45 -> 20 | R46: =+Rentabilitätsvorschau!R45 -> 20 | S46: =+Rentabilitätsvorschau!S45 -> 20 | T46: =+Rentabilitätsvorschau!T45 -> 20 | U46: =+Rentabilitätsvorschau!U45 -> 20 | V46: =+Rentabilitätsvorschau!V45 -> 20 | W46: =+Rentabilitätsvorschau!W45 -> 20 | X46: =+Rentabilitätsvorschau!X45 -> 20 | ... AB46: =+Rentabilitätsvorschau!AB45 -> 20 | AC46: =SUM(Q46:AB46) -> 240 | AD46: =+Rentabilitätsvorschau!AD45 -> 0 | AE46: =+Rentabilitätsvorschau!AE45 -> 0 | AF46: =+Rentabilitätsvorschau!AF45 -> 0 | AG46: =+Rentabilitätsvorschau!AG45 -> 0 | AH46: =+Rentabilitätsvorschau!AH45 -> 0 | AI46: =+Rentabilitätsvorschau!AI45 -> 0 | AJ46: =+Rentabilitätsvorschau!AJ45 -> 0 | AK46: =+Rentabilitätsvorschau!AK45 -> 0 | ... AO46: =+Rentabilitätsvorschau!AO45 -> 0 | AP46: =SUM(AD46:AO46) -> 0 | AQ46: =+Rentabilitätsvorschau!AQ45 -> 0 | AR46: =+Rentabilitätsvorschau!AR45 -> 0 | AS46: =+Rentabilitätsvorschau!AS45 -> 0 | AT46: =+Rentabilitätsvorschau!AT45 -> 0 | AU46: =+Rentabilitätsvorschau!AU45 -> 0 | AV46: =+Rentabilitätsvorschau!AV45 -> 0 | AW46: =+Rentabilitätsvorschau!AW45 -> 0 | AX46: =+Rentabilitätsvorschau!AX45 -> 0 | ... BB46: =+Rentabilitätsvorschau!BB45 -> 0 | BC46: =SUM(AQ46:BB46) -> 0
B47: =+Rentabilitätsvorschau!B46 -> Andere betriebliche Aufwendungen | D47: =+Rentabilitätsvorschau!D46*(1+VSteins) -> 0 | E47: =+Rentabilitätsvorschau!E46*(1+VSteins) -> 0 | F47: =+Rentabilitätsvorschau!F46*(1+VSteins) -> 0 | G47: =+Rentabilitätsvorschau!G46*(1+VSteins) -> 0 | H47: =+Rentabilitätsvorschau!H46*(1+VSteins) -> 0 | I47: =+Rentabilitätsvorschau!I46*(1+VSteins) -> 0 | J47: =+Rentabilitätsvorschau!J46*(1+VSteins) -> 0 | K47: =+Rentabilitätsvorschau!K46*(1+VSteins) -> 0 | ... O47: =+Rentabilitätsvorschau!O46*(1+VSteins) -> 0 | P47: =SUM(D47:O47) -> 0 | Q47: =+Rentabilitätsvorschau!Q46*(1+VSt) -> 0 | R47: =+Rentabilitätsvorschau!R46*(1+VSt) -> 0 | S47: =+Rentabilitätsvorschau!S46*(1+VSt) -> 0 | T47: =+Rentabilitätsvorschau!T46*(1+VSt) -> 0 | U47: =+Rentabilitätsvorschau!U46*(1+VSt) -> 0 | V47: =+Rentabilitätsvorschau!V46*(1+VSt) -> 0 | W47: =+Rentabilitätsvorschau!W46*(1+VSt) -> 0 | X47: =+Rentabilitätsvorschau!X46*(1+VSt) -> 0 | ... AB47: =+Rentabilitätsvorschau!AB46*(1+VSt) -> 0 | AC47: =SUM(Q47:AB47) -> 0 | AD47: =+Rentabilitätsvorschau!AD46*(1+VSt) -> 0 | AE47: =+Rentabilitätsvorschau!AE46*(1+VSt) -> 0 | AF47: =+Rentabilitätsvorschau!AF46*(1+VSt) -> 0 | AG47: =+Rentabilitätsvorschau!AG46*(1+VSt) -> 0 | AH47: =+Rentabilitätsvorschau!AH46*(1+VSt) -> 0 | AI47: =+Rentabilitätsvorschau!AI46*(1+VSt) -> 0 | AJ47: =+Rentabilitätsvorschau!AJ46*(1+VSt) -> 0 | AK47: =+Rentabilitätsvorschau!AK46*(1+VSt) -> 0 | ... AO47: =+Rentabilitätsvorschau!AO46*(1+VSt) -> 0 | AP47: =SUM(AD47:AO47) -> 0 | AQ47: =+Rentabilitätsvorschau!AQ46*(1+VSt) -> 0 | AR47: =+Rentabilitätsvorschau!AR46*(1+VSt) -> 0 | AS47: =+Rentabilitätsvorschau!AS46*(1+VSt) -> 0 | AT47: =+Rentabilitätsvorschau!AT46*(1+VSt) -> 0 | AU47: =+Rentabilitätsvorschau!AU46*(1+VSt) -> 0 | AV47: =+Rentabilitätsvorschau!AV46*(1+VSt) -> 0 | AW47: =+Rentabilitätsvorschau!AW46*(1+VSt) -> 0 | AX47: =+Rentabilitätsvorschau!AX46*(1+VSt) -> 0 | ... BB47: =+Rentabilitätsvorschau!BB46*(1+VSt) -> 0 | BC47: =SUM(AQ47:BB47) -> 0
A48: =+Rentabilitätsvorschau!A47 -> Summe betrieblicher Aufwendungen | D48: =SUM(D15:D47) -> 0 | E48: =SUM(E15:E47) -> 0 | F48: =SUM(F15:F47) -> 0 | G48: =SUM(G15:G47) -> 0 | H48: =SUM(H15:H47) -> 0 | I48: =SUM(I15:I47) -> 0 | J48: =SUM(J15:J47) -> 0 | K48: =SUM(K15:K47) -> 0 | ... BC48: =SUM(BC15:BC47) -> 0
A49: =+Rentabilitätsvorschau!A48 -> Betriebsergebnis | D49: =+D14-D48 -> 0 | E49: =+E14-E48 -> 0 | F49: =+F14-F48 -> 0 | G49: =+G14-G48 -> 0 | H49: =+H14-H48 -> 0 | I49: =+I14-I48 -> 0 | J49: =+J14-J48 -> 0 | K49: =+K14-K48 -> 0 | ... BC49: =+BC14-BC48 -> 0
A50: Zinsaufwendungen | D50: =+Rentabilitätsvorschau!D49 -> 0 | E50: =+Rentabilitätsvorschau!E49 -> 0 | F50: =+Rentabilitätsvorschau!F49 -> 0 | G50: =+Rentabilitätsvorschau!G49 -> 0 | H50: =+Rentabilitätsvorschau!H49 -> 0 | I50: =+Rentabilitätsvorschau!I49 -> 0 | J50: =+Rentabilitätsvorschau!J49 -> 0 | K50: =+Rentabilitätsvorschau!K49 -> 0 | ... O50: =+Rentabilitätsvorschau!O49 -> 0 | P50: =SUM(D50:O50) -> 0 | Q50: =+Rentabilitätsvorschau!Q49 -> 0 | R50: =+Rentabilitätsvorschau!R49 -> 0 | S50: =+Rentabilitätsvorschau!S49 -> 0 | T50: =+Rentabilitätsvorschau!T49 -> 0 | U50: =+Rentabilitätsvorschau!U49 -> 0 | V50: =+Rentabilitätsvorschau!V49 -> 0 | W50: =+Rentabilitätsvorschau!W49 -> 0 | X50: =+Rentabilitätsvorschau!X49 -> 0 | ... AB50: =+Rentabilitätsvorschau!AB49 -> 0 | AC50: =SUM(Q50:AB50) -> 0 | AD50: =+Rentabilitätsvorschau!AD49 -> 0 | AE50: =+Rentabilitätsvorschau!AE49 -> 0 | AF50: =+Rentabilitätsvorschau!AF49 -> 0 | AG50: =+Rentabilitätsvorschau!AG49 -> 0 | AH50: =+Rentabilitätsvorschau!AH49 -> 0 | AI50: =+Rentabilitätsvorschau!AI49 -> 0 | AJ50: =+Rentabilitätsvorschau!AJ49 -> 0 | AK50: =+Rentabilitätsvorschau!AK49 -> 0 | ... AO50: =+Rentabilitätsvorschau!AO49 -> 0 | AP50: =SUM(AD50:AO50) -> 0 | AQ50: =+Rentabilitätsvorschau!AQ49 -> 0 | AR50: =+Rentabilitätsvorschau!AR49 -> 0 | AS50: =+Rentabilitätsvorschau!AS49 -> 0 | AT50: =+Rentabilitätsvorschau!AT49 -> 0 | AU50: =+Rentabilitätsvorschau!AU49 -> 0 | AV50: =+Rentabilitätsvorschau!AV49 -> 0 | AW50: =+Rentabilitätsvorschau!AW49 -> 0 | AX50: =+Rentabilitätsvorschau!AX49 -> 0 | ... BB50: =+Rentabilitätsvorschau!BB49 -> 0 | BC50: =SUM(AQ50:BB50) -> 0
A51: =+Rentabilitätsvorschau!A50 -> Gewinn/Verlust vor Steuern | D51: =+D49-D50 -> 0 | E51: =+E49-E50 -> 0 | F51: =+F49-F50 -> 0 | G51: =+G49-G50 -> 0 | H51: =+H49-H50 -> 0 | I51: =+I49-I50 -> 0 | J51: =+J49-J50 -> 0 | K51: =+K49-K50 -> 0 | ... BC51: =+BC49-BC50 -> 0
A52: =+Rentabilitätsvorschau!A51 -> Sonstige Steuern (betrieblich) | D52: =+Rentabilitätsvorschau!D51 -> 0 | E52: =+Rentabilitätsvorschau!E51 -> 0 | F52: =+Rentabilitätsvorschau!F51 -> 0 | G52: =+Rentabilitätsvorschau!G51 -> 0 | H52: =+Rentabilitätsvorschau!H51 -> 0 | I52: =+Rentabilitätsvorschau!I51 -> 0 | J52: =+Rentabilitätsvorschau!J51 -> 0 | K52: =+Rentabilitätsvorschau!K51 -> 0 | ... O52: =+Rentabilitätsvorschau!O51 -> 0 | P52: =SUM(D52:O52) -> 0 | Q52: =+Rentabilitätsvorschau!Q51 -> 0 | R52: =+Rentabilitätsvorschau!R51 -> 0 | S52: =+Rentabilitätsvorschau!S51 -> 0 | T52: =+Rentabilitätsvorschau!T51 -> 0 | U52: =+Rentabilitätsvorschau!U51 -> 0 | V52: =+Rentabilitätsvorschau!V51 -> 0 | W52: =+Rentabilitätsvorschau!W51 -> 0 | X52: =+Rentabilitätsvorschau!X51 -> 0 | ... AB52: =+Rentabilitätsvorschau!AB51 -> 0 | AC52: =SUM(Q52:AB52) -> 0 | AD52: =+Rentabilitätsvorschau!AD51 -> 0 | AE52: =+Rentabilitätsvorschau!AE51 -> 0 | AF52: =+Rentabilitätsvorschau!AF51 -> 0 | AG52: =+Rentabilitätsvorschau!AG51 -> 0 | AH52: =+Rentabilitätsvorschau!AH51 -> 0 | AI52: =+Rentabilitätsvorschau!AI51 -> 0 | AJ52: =+Rentabilitätsvorschau!AJ51 -> 0 | AK52: =+Rentabilitätsvorschau!AK51 -> 0 | ... AO52: =+Rentabilitätsvorschau!AO51 -> 0 | AP52: =SUM(AD52:AO52) -> 0 | AQ52: =+Rentabilitätsvorschau!AQ51 -> 0 | AR52: =+Rentabilitätsvorschau!AR51 -> 0 | AS52: =+Rentabilitätsvorschau!AS51 -> 0 | AT52: =+Rentabilitätsvorschau!AT51 -> 0 | AU52: =+Rentabilitätsvorschau!AU51 -> 0 | AV52: =+Rentabilitätsvorschau!AV51 -> 0 | AW52: =+Rentabilitätsvorschau!AW51 -> 0 | AX52: =+Rentabilitätsvorschau!AX51 -> 0 | ... BB52: =+Rentabilitätsvorschau!BB51 -> 0 | BC52: =SUM(AQ52:BB52) -> 0
A53: vorläufiger Liquiditätsbedarf (-)/-überschuß (+) | D53: =+D51-D52 -> 0 | E53: =+E51-E52 -> 0 | F53: =+F51-F52 -> 0 | G53: =+G51-G52 -> 0 | H53: =+H51-H52 -> 0 | I53: =+I51-I52 -> 0 | J53: =+J51-J52 -> 0 | K53: =+K51-K52 -> 0 | ... BC53: =+BC51-BC52 -> 0
A54: Umsatzsteuerzahllast (+) bzw. Vorsteuerüberhang (-) | D54: - | E54: =IF('Infos vor dem Start'!$A17="x",(D4+D6-D7+D8)/(1+USteins)*USteins+D5/(1+UStermeins)*UStermeins-SUM(D10:D13)/(1+VStWEeins)*VStWEeins-(SUM(D19:D21)+SUM(D24:D34)+D37+SUM(D40:D45)+D47)/(1+VSteins)*VSteins-D39/(1+VStermeins)*VStermeins-(IF(Monat<=1,(D55)/(1+VSteins)*VSteins,0)),0) -> 0 | F54: =IF('Infos vor dem Start'!$A17="x",(E4+E6-E7+E8)/(1+USteins)*USteins+E5/(1+UStermeins)*UStermeins-SUM(E10:E13)/(1+VStWEeins)*VStWEeins-(SUM(E19:E21)+SUM(E24:E34)+E37+SUM(E40:E45)+E47)/(1+VSteins)*VSteins-E39/(1+VStermeins)*VStermeins-(IF(Monat<=1,(E55)/(1+VSteins)*VSteins,0)),0) -> 0 | G54: =IF('Infos vor dem Start'!$A17="x",(F4+F6-F7+F8)/(1+USteins)*USteins+F5/(1+UStermeins)*UStermeins-SUM(F10:F13)/(1+VStWEeins)*VStWEeins-(SUM(F19:F21)+SUM(F24:F34)+F37+SUM(F40:F45)+F47)/(1+VSteins)*VSteins-F39/(1+VStermeins)*VStermeins-(IF(Monat<=1,(F55)/(1+VSteins)*VSteins,0)),0) -> 0 | H54: =IF('Infos vor dem Start'!$A17="x",(G4+G6-G7+G8)/(1+USteins)*USteins+G5/(1+UStermeins)*UStermeins-SUM(G10:G13)/(1+VStWEeins)*VStWEeins-(SUM(G19:G21)+SUM(G24:G34)+G37+SUM(G40:G45)+G47)/(1+VSteins)*VSteins-G39/(1+VStermeins)*VStermeins-(IF(Monat<=1,(G55)/(1+VSteins)*VSteins,0)),0) -> 0 | I54: =IF('Infos vor dem Start'!$A17="x",(H4+H6-H7+H8)/(1+USteins)*USteins+H5/(1+UStermeins)*UStermeins-SUM(H10:H13)/(1+VStWEeins)*VStWEeins-(SUM(H19:H21)+SUM(H24:H34)+H37+SUM(H40:H45)+H47)/(1+VSteins)*VSteins-H39/(1+VStermeins)*VStermeins-(IF(Monat<=1,(H55)/(1+VSteins)*VSteins,0)),0) -> 0 | J54: =IF('Infos vor dem Start'!$A17="x",(I4+I6-I7+I8)/(1+USteins)*USteins+I5/(1+UStermeins)*UStermeins-SUM(I10:I13)/(1+VStWEeins)*VStWEeins-(SUM(I19:I21)+SUM(I24:I34)+I37+SUM(I40:I45)+I47)/(1+VSteins)*VSteins-I39/(1+VStermeins)*VStermeins-(IF(Monat<=1,(I55)/(1+VSteins)*VSteins,0)),0) -> 0 | K54: =IF('Infos vor dem Start'!$A17="x",(J4+J6-J7+J8)/(1+USteins)*USteins+J5/(1+UStermeins)*UStermeins-SUM(J10:J13)/(1+VStWEeins)*VStWEeins-(SUM(J19:J21)+SUM(J24:J34)+J37+SUM(J40:J45)+J47)/(1+VSteins)*VSteins-J39/(1+VStermeins)*VStermeins-(IF(Monat<=1,(J55)/(1+VSteins)*VSteins,0)),0) -> 0 | L54: =IF('Infos vor dem Start'!$A17="x",(K4+K6-K7+K8)/(1+USteins)*USteins+K5/(1+UStermeins)*UStermeins-SUM(K10:K13)/(1+VStWEeins)*VStWEeins-(SUM(K19:K21)+SUM(K24:K34)+K37+SUM(K40:K45)+K47)/(1+VSteins)*VSteins-K39/(1+VStermeins)*VStermeins-(IF(Monat<=1,(K55)/(1+VSteins)*VSteins,0)),0) -> 0 | ... O54: =IF('Infos vor dem Start'!$A17="x",(N4+N6-N7+N8)/(1+USteins)*USteins+N5/(1+UStermeins)*UStermeins-SUM(N10:N13)/(1+VStWEeins)*VStWEeins-(SUM(N19:N21)+SUM(N24:N34)+N37+SUM(N40:N45)+N47)/(1+VSteins)*VSteins-N39/(1+VStermeins)*VStermeins-(IF(Monat<=1,(N55)/(1+VSteins)*VSteins,0)),0) -> 2398.3 | P54: =SUM(D54:O54) -> 2136.6 | Q54: =IF('Infos vor dem Start'!$A17="x",(O4+O6-O7+O8)/(1+USteins)*USteins+O5/(1+UStermeins)*UStermeins-SUM(O10:O13)/(1+VStWEeins)*VStWEeins-(SUM(O19:O21)+SUM(O24:O34)+O37+SUM(O40:O45)+O47)/(1+VSteins)*VSteins-O39/(1+VStermeins)*VStermeins-(IF(Monat=12,(O55)/(1+VSteins)*VSteins,0)),0) -> -261.7 | R54: =IF('Infos vor dem Start'!$A17="x",(Q4+Q6-Q7+Q8)/(1+USt)*USt+Q5/(1+USterm)*USterm-SUM(Q10:Q13)/(1+VStWE)*VStWE-(SUM(Q19:Q21)+SUM(Q24:Q34)+Q37+SUM(Q40:Q45)+Q47)/(1+VSt)*VSt-Q39/(1+VSterm)*VSterm,0) -> 3158.3 | S54: =IF('Infos vor dem Start'!$A17="x",(R4+R6-R7+R8)/(1+USt)*USt+R5/(1+USterm)*USterm-SUM(R10:R13)/(1+VStWE)*VStWE-(SUM(R19:R21)+SUM(R24:R34)+R37+SUM(R40:R45)+R47)/(1+VSt)*VSt-R39/(1+VSterm)*VSterm,0) -> -261.7 | T54: =IF('Infos vor dem Start'!$A17="x",(S4+S6-S7+S8)/(1+USt)*USt+S5/(1+USterm)*USterm-SUM(S10:S13)/(1+VStWE)*VStWE-(SUM(S19:S21)+SUM(S24:S34)+S37+SUM(S40:S45)+S47)/(1+VSt)*VSt-S39/(1+VSterm)*VSterm,0) -> -261.7 | U54: =IF('Infos vor dem Start'!$A17="x",(T4+T6-T7+T8)/(1+USt)*USt+T5/(1+USterm)*USterm-SUM(T10:T13)/(1+VStWE)*VStWE-(SUM(T19:T21)+SUM(T24:T34)+T37+SUM(T40:T45)+T47)/(1+VSt)*VSt-T39/(1+VSterm)*VSterm,0) -> -261.7 | V54: =IF('Infos vor dem Start'!$A17="x",(U4+U6-U7+U8)/(1+USt)*USt+U5/(1+USterm)*USterm-SUM(U10:U13)/(1+VStWE)*VStWE-(SUM(U19:U21)+SUM(U24:U34)+U37+SUM(U40:U45)+U47)/(1+VSt)*VSt-U39/(1+VSterm)*VSterm,0) -> -261.7 | W54: =IF('Infos vor dem Start'!$A17="x",(V4+V6-V7+V8)/(1+USt)*USt+V5/(1+USterm)*USterm-SUM(V10:V13)/(1+VStWE)*VStWE-(SUM(V19:V21)+SUM(V24:V34)+V37+SUM(V40:V45)+V47)/(1+VSt)*VSt-V39/(1+VSterm)*VSterm,0) -> -261.7 | X54: =IF('Infos vor dem Start'!$A17="x",(W4+W6-W7+W8)/(1+USt)*USt+W5/(1+USterm)*USterm-SUM(W10:W13)/(1+VStWE)*VStWE-(SUM(W19:W21)+SUM(W24:W34)+W37+SUM(W40:W45)+W47)/(1+VSt)*VSt-W39/(1+VSterm)*VSterm,0) -> -261.7 | Y54: =IF('Infos vor dem Start'!$A17="x",(X4+X6-X7+X8)/(1+USt)*USt+X5/(1+USterm)*USterm-SUM(X10:X13)/(1+VStWE)*VStWE-(SUM(X19:X21)+SUM(X24:X34)+X37+SUM(X40:X45)+X47)/(1+VSt)*VSt-X39/(1+VSterm)*VSterm,0) -> -261.7 | ... AB54: =IF('Infos vor dem Start'!$A17="x",(AA4+AA6-AA7+AA8)/(1+USt)*USt+AA5/(1+USterm)*USterm-SUM(AA10:AA13)/(1+VStWE)*VStWE-(SUM(AA19:AA21)+SUM(AA24:AA34)+AA37+SUM(AA40:AA45)+AA47)/(1+VSt)*VSt-AA39/(1+VSterm)*VSterm,0) -> -261.7 | AC54: =SUM(Q54:AB54) -> 279.6 | AD54: =IF('Infos vor dem Start'!$A17="x",(AB4+AB6-AB7+AB8)/(1+USt)*USt+AB5/(1+USterm)*USterm-SUM(AB10:AB13)/(1+VStWE)*VStWE-(SUM(AB19:AB21)+SUM(AB24:AB34)+AB37+SUM(AB40:AB45)+AB47)/(1+VSt)*VSt-AB39/(1+VSterm)*VSterm-(IF(Monat=1,(AB55)/(1+VSt)*VSt,0)),0) -> -261.7 | AE54: =IF('Infos vor dem Start'!$A17="x",(AD4+AD6-AD7+AD8)/(1+USt)*USt+AD5/(1+USterm)*USterm-SUM(AD10:AD13)/(1+VStWE)*VStWE-(SUM(AD19:AD21)+SUM(AD24:AD34)+AD37+SUM(AD40:AD45)+AD47)/(1+VSt)*VSt-AD39/(1+VSterm)*VSterm,0) -> 0 | AF54: =IF('Infos vor dem Start'!$A17="x",(AE4+AE6-AE7+AE8)/(1+USt)*USt+AE5/(1+USterm)*USterm-SUM(AE10:AE13)/(1+VStWE)*VStWE-(SUM(AE19:AE21)+SUM(AE24:AE34)+AE37+SUM(AE40:AE45)+AE47)/(1+VSt)*VSt-AE39/(1+VSterm)*VSterm,0) -> 0 | AG54: =IF('Infos vor dem Start'!$A17="x",(AF4+AF6-AF7+AF8)/(1+USt)*USt+AF5/(1+USterm)*USterm-SUM(AF10:AF13)/(1+VStWE)*VStWE-(SUM(AF19:AF21)+SUM(AF24:AF34)+AF37+SUM(AF40:AF45)+AF47)/(1+VSt)*VSt-AF39/(1+VSterm)*VSterm,0) -> 0 | AH54: =IF('Infos vor dem Start'!$A17="x",(AG4+AG6-AG7+AG8)/(1+USt)*USt+AG5/(1+USterm)*USterm-SUM(AG10:AG13)/(1+VStWE)*VStWE-(SUM(AG19:AG21)+SUM(AG24:AG34)+AG37+SUM(AG40:AG45)+AG47)/(1+VSt)*VSt-AG39/(1+VSterm)*VSterm,0) -> 0 | AI54: =IF('Infos vor dem Start'!$A17="x",(AH4+AH6-AH7+AH8)/(1+USt)*USt+AH5/(1+USterm)*USterm-SUM(AH10:AH13)/(1+VStWE)*VStWE-(SUM(AH19:AH21)+SUM(AH24:AH34)+AH37+SUM(AH40:AH45)+AH47)/(1+VSt)*VSt-AH39/(1+VSterm)*VSterm,0) -> 0 | AJ54: =IF('Infos vor dem Start'!$A17="x",(AI4+AI6-AI7+AI8)/(1+USt)*USt+AI5/(1+USterm)*USterm-SUM(AI10:AI13)/(1+VStWE)*VStWE-(SUM(AI19:AI21)+SUM(AI24:AI34)+AI37+SUM(AI40:AI45)+AI47)/(1+VSt)*VSt-AI39/(1+VSterm)*VSterm,0) -> 0 | AK54: =IF('Infos vor dem Start'!$A17="x",(AJ4+AJ6-AJ7+AJ8)/(1+USt)*USt+AJ5/(1+USterm)*USterm-SUM(AJ10:AJ13)/(1+VStWE)*VStWE-(SUM(AJ19:AJ21)+SUM(AJ24:AJ34)+AJ37+SUM(AJ40:AJ45)+AJ47)/(1+VSt)*VSt-AJ39/(1+VSterm)*VSterm,0) -> 0 | AL54: =IF('Infos vor dem Start'!$A17="x",(AK4+AK6-AK7+AK8)/(1+USt)*USt+AK5/(1+USterm)*USterm-SUM(AK10:AK13)/(1+VStWE)*VStWE-(SUM(AK19:AK21)+SUM(AK24:AK34)+AK37+SUM(AK40:AK45)+AK47)/(1+VSt)*VSt-AK39/(1+VSterm)*VSterm,0) -> 0 | ... AO54: =IF('Infos vor dem Start'!$A17="x",(AN4+AN6-AN7+AN8)/(1+USt)*USt+AN5/(1+USterm)*USterm-SUM(AN10:AN13)/(1+VStWE)*VStWE-(SUM(AN19:AN21)+SUM(AN24:AN34)+AN37+SUM(AN40:AN45)+AN47)/(1+VSt)*VSt-AN39/(1+VSterm)*VSterm,0) -> 0 | AP54: =SUM(AD54:AO54) -> -261.7 | AQ54: =IF('Infos vor dem Start'!$A17="x",(AO4+AO6-AO7+AO8)/(1+USt)*USt+AO5/(1+USterm)*USterm-SUM(AO10:AO13)/(1+VStWE)*VStWE-(SUM(AO19:AO21)+SUM(AO24:AO34)+AO37+SUM(AO40:AO45)+AO47)/(1+VSt)*VSt-AO39/(1+VSterm)*VSterm-(IF(Monat=1,(AO55)/(1+VSt)*VSt,0)),0) -> 0 | AR54: =IF('Infos vor dem Start'!$A17="x",(AQ4+AQ6-AQ7+AQ8)/(1+USt)*USt+AQ5/(1+USterm)*USterm-SUM(AQ10:AQ13)/(1+VStWE)*VStWE-(SUM(AQ19:AQ21)+SUM(AQ24:AQ34)+AQ37+SUM(AQ40:AQ45)+AQ47)/(1+VSt)*VSt-AQ39/(1+VSterm)*VSterm,0) -> 0 | AS54: =IF('Infos vor dem Start'!$A17="x",(AR4+AR6-AR7+AR8)/(1+USt)*USt+AR5/(1+USterm)*USterm-SUM(AR10:AR13)/(1+VStWE)*VStWE-(SUM(AR19:AR21)+SUM(AR24:AR34)+AR37+SUM(AR40:AR45)+AR47)/(1+VSt)*VSt-AR39/(1+VSterm)*VSterm,0) -> 0 | AT54: =IF('Infos vor dem Start'!$A17="x",(AS4+AS6-AS7+AS8)/(1+USt)*USt+AS5/(1+USterm)*USterm-SUM(AS10:AS13)/(1+VStWE)*VStWE-(SUM(AS19:AS21)+SUM(AS24:AS34)+AS37+SUM(AS40:AS45)+AS47)/(1+VSt)*VSt-AS39/(1+VSterm)*VSterm,0) -> 0 | AU54: =IF('Infos vor dem Start'!$A17="x",(AT4+AT6-AT7+AT8)/(1+USt)*USt+AT5/(1+USterm)*USterm-SUM(AT10:AT13)/(1+VStWE)*VStWE-(SUM(AT19:AT21)+SUM(AT24:AT34)+AT37+SUM(AT40:AT45)+AT47)/(1+VSt)*VSt-AT39/(1+VSterm)*VSterm,0) -> 0 | AV54: =IF('Infos vor dem Start'!$A17="x",(AU4+AU6-AU7+AU8)/(1+USt)*USt+AU5/(1+USterm)*USterm-SUM(AU10:AU13)/(1+VStWE)*VStWE-(SUM(AU19:AU21)+SUM(AU24:AU34)+AU37+SUM(AU40:AU45)+AU47)/(1+VSt)*VSt-AU39/(1+VSterm)*VSterm,0) -> 0 | AW54: =IF('Infos vor dem Start'!$A17="x",(AV4+AV6-AV7+AV8)/(1+USt)*USt+AV5/(1+USterm)*USterm-SUM(AV10:AV13)/(1+VStWE)*VStWE-(SUM(AV19:AV21)+SUM(AV24:AV34)+AV37+SUM(AV40:AV45)+AV47)/(1+VSt)*VSt-AV39/(1+VSterm)*VSterm,0) -> 0 | AX54: =IF('Infos vor dem Start'!$A17="x",(AW4+AW6-AW7+AW8)/(1+USt)*USt+AW5/(1+USterm)*USterm-SUM(AW10:AW13)/(1+VStWE)*VStWE-(SUM(AW19:AW21)+SUM(AW24:AW34)+AW37+SUM(AW40:AW45)+AW47)/(1+VSt)*VSt-AW39/(1+VSterm)*VSterm,0) -> 0 | AY54: =IF('Infos vor dem Start'!$A17="x",(AX4+AX6-AX7+AX8)/(1+USt)*USt+AX5/(1+USterm)*USterm-SUM(AX10:AX13)/(1+VStWE)*VStWE-(SUM(AX19:AX21)+SUM(AX24:AX34)+AX37+SUM(AX40:AX45)+AX47)/(1+VSt)*VSt-AX39/(1+VSterm)*VSterm,0) -> 0 | ... BB54: =IF('Infos vor dem Start'!$A17="x",(BA4+BA6-BA7+BA8)/(1+USt)*USt+BA5/(1+USterm)*USterm-SUM(BA10:BA13)/(1+VStWE)*VStWE-(SUM(BA19:BA21)+SUM(BA24:BA34)+BA37+SUM(BA40:BA45)+BA47)/(1+VSt)*VSt-BA39/(1+VSterm)*VSterm,0) -> 0 | BC54: =SUM(AQ54:BB54) -> 0
A55: Investitionen und GWG | D55: =IF(Monat<=1,(Investitionsplan!$C13+Investitionsplan!$C35)*(1+VSteins),0) -> 0 | E55: =IF(Monat=2,(Investitionsplan!$C13+Investitionsplan!$C35)*(1+VSteins),0) -> 0 | F55: =IF(Monat=3,(Investitionsplan!$C13+Investitionsplan!$C35)*(1+VSteins),0) -> 0 | G55: =IF(Monat=4,(Investitionsplan!$C13+Investitionsplan!$C35)*(1+VSteins),0) -> 0 | H55: =IF(Monat=5,(Investitionsplan!$C13+Investitionsplan!$C35)*(1+VSteins),0) -> 0 | I55: =IF(Monat=6,(Investitionsplan!$C13+Investitionsplan!$C35)*(1+VSteins),0) -> 0 | J55: =IF(Monat=7,(Investitionsplan!$C13+Investitionsplan!$C35)*(1+VSteins),0) -> 0 | K55: =IF(Monat=8,(Investitionsplan!$C13+Investitionsplan!$C35)*(1+VSteins),0) -> 0 | L55: =IF(Monat=9,(Investitionsplan!$C13+Investitionsplan!$C35)*(1+VSteins),0) -> 0 | M55: =IF(Monat=10,(Investitionsplan!$C13+Investitionsplan!$C35)*(1+VSteins),0) -> 0 | N55: =IF(Monat=11,(Investitionsplan!$C13+Investitionsplan!$C35)*(1+VSteins),0) -> 0 | O55: =IF(Monat=12,(Investitionsplan!$C13+Investitionsplan!$C35)*(1+VSteins),0) -> 0 | P55: =SUM(D55:O55) -> 0 | Q55: =(+Investitionsplan!E13+Investitionsplan!E35)*(1+VSt) -> 0 | AC55: =SUM(Q55:AB55) -> 0 | AD55: =(+Investitionsplan!G13+Investitionsplan!G35)*(1+VSt) -> 0 | AP55: =SUM(AD55:AO55) -> 0 | AQ55: =(+Investitionsplan!I13+Investitionsplan!I35)*(1+VSt) -> 0 | BC55: =SUM(AQ55:BB55) -> 0
A56: Auszahlung betrieblicher Darlehen (s. "Finanzierungsplan") | P56: =SUM(D56:O56) -> 0 | AC56: =SUM(Q56:AB56) -> 0 | AP56: =SUM(AD56:AO56) -> 0 | BC56: =SUM(AQ56:BB56) -> 0
A57: Tilgung betrieblicher Darlehen | P57: =SUM(D57:O57) -> 0 | AC57: =SUM(Q57:AB57) -> 0 | AP57: =SUM(AD57:AO57) -> 0 | BC57: =SUM(AQ57:BB57) -> 0
A58: Körperschaftsteuer (nur bei Kapitalgesellschaften) | P58: =SUM(D58:O58) -> 0 | AC58: =SUM(Q58:AB58) -> 0 | AP58: =SUM(AD58:AO58) -> 0 | BC58: =SUM(AQ58:BB58) -> 0
A59: Gewerbesteuer | P59: =SUM(D59:O59) -> 0 | AC59: =SUM(Q59:AB59) -> 0 | AP59: =SUM(AD59:AO59) -> 0 | BC59: =SUM(AQ59:BB59) -> 0
A60: =IF(kapges=0,"Gründungszusschuss/Einstiegsgeld","nicht belegt") -> Gründungszusschuss/Einstiegsgeld | D60: 0 | E60: 0 | F60: 0 | G60: 0 | H60: 0 | I60: 0 | P60: =SUM(D60:O60) -> 0 | AC60: =SUM(Q60:AB60) -> 0 | AP60: =SUM(AD60:AO60) -> 0 | BC60: =SUM(AQ60:BB60) -> 0
A61: Privater Finanzbedarf (Unternehmerlohn) | D61: =IF(kapges="x",0,IF(Monat<=1,+'Priv. Finanzbed. Summe'!$C$29,0)) -> 0 | E61: =IF(kapges="x",0,IF(Monat<=2,+'Priv. Finanzbed. Summe'!$C$29,0)) -> 0 | F61: =IF(kapges="x",0,IF(Monat<=3,+'Priv. Finanzbed. Summe'!$C$29,0)) -> 0 | G61: =IF(kapges="x",0,IF(Monat<=4,+'Priv. Finanzbed. Summe'!$C$29,0)) -> 0 | H61: =IF(kapges="x",0,IF(Monat<=5,+'Priv. Finanzbed. Summe'!$C$29,0)) -> 0 | I61: =IF(kapges="x",0,IF(Monat<=6,+'Priv. Finanzbed. Summe'!$C$29,0)) -> 0 | J61: =IF(kapges="x",0,IF(Monat<=7,+'Priv. Finanzbed. Summe'!$C$29,0)) -> 0 | K61: =IF(kapges="x",0,IF(Monat<=8,+'Priv. Finanzbed. Summe'!$C$29,0)) -> 0 | L61: =IF(kapges="x",0,IF(Monat<=9,+'Priv. Finanzbed. Summe'!$C$29,0)) -> 0 | M61: =IF(kapges="x",0,IF(Monat<=10,+'Priv. Finanzbed. Summe'!$C$29,0)) -> 0 | N61: =IF(kapges="x",0,IF(Monat<=11,+'Priv. Finanzbed. Summe'!$C$29,0)) -> 0 | O61: =IF(kapges="x",0,IF(Monat<=12,+'Priv. Finanzbed. Summe'!$C$29,0)) -> 0 | P61: =SUM(D61:O61) -> 0 | Q61: =IF(kapges="x",0,+'Priv. Finanzbed. Summe'!$D$29) -> 0 | R61: =+Q61 -> 0 | S61: =+R61 -> 0 | T61: =+S61 -> 0 | U61: =+T61 -> 0 | V61: =+U61 -> 0 | W61: =+V61 -> 0 | X61: =+W61 -> 0 | Y61: =+X61 -> 0 | ... AB61: =+AA61 -> 0 | AC61: =SUM(Q61:AB61) -> 0 | AD61: =IF(kapges="x",0,+'Priv. Finanzbed. Summe'!$E$29) -> 0 | AE61: =+AD61 -> 0 | AF61: =+AE61 -> 0 | AG61: =+AF61 -> 0 | AH61: =+AG61 -> 0 | AI61: =+AH61 -> 0 | AJ61: =+AI61 -> 0 | AK61: =+AJ61 -> 0 | AL61: =+AK61 -> 0 | ... AO61: =+AN61 -> 0 | AP61: =SUM(AD61:AO61) -> 0 | AQ61: =IF(kapges="x",0,+'Priv. Finanzbed. Summe'!$F$29) -> 0 | AR61: =+AQ61 -> 0 | AS61: =+AR61 -> 0 | AT61: =+AS61 -> 0 | AU61: =+AT61 -> 0 | AV61: =+AU61 -> 0 | AW61: =+AV61 -> 0 | AX61: =+AW61 -> 0 | AY61: =+AX61 -> 0 | ... BB61: =+BA61 -> 0 | BC61: =SUM(AQ61:BB61) -> 0
A62: zusätzlicher Liquiditätsbedarf (-)/-überschuss (+) | D62: =-D55+D56-D57-D58-D59+D60-D61 -> 0 | E62: =-E55+E56-E57-E58-E59+E60-E61 -> 0 | F62: =-F55+F56-F57-F58-F59+F60-F61 -> 0 | G62: =-G55+G56-G57-G58-G59+G60-G61 -> 0 | H62: =-H55+H56-H57-H58-H59+H60-H61 -> 0 | I62: =-I55+I56-I57-I58-I59+I60-I61 -> 0 | J62: =-J55+J56-J57-J58-J59+J60-J61 -> 0 | K62: =-K55+K56-K57-K58-K59+K60-K61 -> 0 | ... BC62: =-BC55+BC56-BC57-BC58-BC59+BC60-BC61 -> 0
A63: totaler Liquiditätsbedarf (-)/-überschuss (+) | D63: =+D53+D62 -> 0 | E63: =+E53+E62 -> 0 | F63: =+F53+F62 -> 0 | G63: =+G53+G62 -> 0 | H63: =+H53+H62 -> 0 | I63: =+I53+I62 -> 0 | J63: =+J53+J62 -> 0 | K63: =+K53+K62 -> 0 | ... BC63: =+BC53+BC62 -> 0
A64: eingebrachtes Eigenkapital - liquide Mittel | D64: =IF(Monat=1,+Finanzierungsplan!$D16,0) -> 0 | E64: =IF(Monat=2,+Finanzierungsplan!$D16,0) -> 0 | F64: =IF(Monat=3,+Finanzierungsplan!$D16,0) -> 0 | G64: =IF(Monat=4,+Finanzierungsplan!$D16,0) -> 0 | H64: =IF(Monat=5,+Finanzierungsplan!$D16,0) -> 0 | I64: =IF(Monat=6,+Finanzierungsplan!$D16,0) -> 0 | J64: =IF(Monat=7,+Finanzierungsplan!$D16,0) -> 0 | K64: =IF(Monat=8,+Finanzierungsplan!$D16,0) -> 0 | L64: =IF(Monat=9,+Finanzierungsplan!$D16,0) -> 3000 | M64: =IF(Monat=10,+Finanzierungsplan!$D16,0) -> 0 | N64: =IF(Monat=11,+Finanzierungsplan!$D16,0) -> 0 | O64: =IF(Monat=12,+Finanzierungsplan!$D16,0) -> 0
A65: Liquiditätsreserve | D65: =+D63+D64 -> 0 | E65: =+D65+E63+E64 -> 0 | F65: =+E65+F63+F64 -> 0 | G65: =+F65+G63+G64 -> 0 | H65: =+G65+H63+H64 -> 0 | I65: =+H65+I63+I64 -> 0 | J65: =+I65+J63+J64 -> 0 | K65: =+J65+K63+K64 -> 0 | L65: =+K65+L63+L64 -> 3000 | ... O65: =+N65+O63+O64 -> 14449.9 | Q65: =+O65+Q63 -> 33413.2 | R65: =+Q65+R63 -> 30956.5 | S65: =+R65+S63 -> 28499.8 | T65: =+S65+T63 -> 26043.1 | U65: =+T65+U63 -> 23586.4 | V65: =+U65+V63 -> 21129.7 | W65: =+V65+W63 -> 18673 | X65: =+W65+X63 -> 16216.3 | Y65: =+X65+Y63 -> 13759.6 | ... AB65: =+AA65+AB63 -> 6389.5 | AD65: =+AB65+AD63 -> 6389.5 | AE65: =+AD65+AE63 -> 6389.5 | AF65: =+AE65+AF63 -> 6389.5 | AG65: =+AF65+AG63 -> 6389.5 | AH65: =+AG65+AH63 -> 6389.5 | AI65: =+AH65+AI63 -> 6389.5 | AJ65: =+AI65+AJ63 -> 6389.5 | AK65: =+AJ65+AK63 -> 6389.5 | AL65: =+AK65+AL63 -> 6389.5 | ... AO65: =+AN65+AO63 -> 6389.5 | AQ65: =+AO65+AQ63 -> 6389.5 | AR65: =+AQ65+AR63 -> 6389.5 | AS65: =+AR65+AS63 -> 6389.5 | AT65: =+AS65+AT63 -> 6389.5 | AU65: =+AT65+AU63 -> 6389.5 | AV65: =+AU65+AV63 -> 6389.5 | AW65: =+AV65+AW63 -> 6389.5 | AX65: =+AW65+AX63 -> 6389.5 | AY65: =+AX65+AY63 -> 6389.5 | ... BB65: =+BA65+BB63 -> 6389.5

Sheet Investitionsplan
A1: Anschaffungen im Gründungsjahr | B1: betriebs-gewöhnliche Nutzungsdauer | C1: =+gj -> 2026 | E1: =+gj+1 -> 2027 | G1: =+gj+2 -> 2028 | I1: =+gj+3 -> 2029
C2: =IF('Infos vor dem Start'!A17="x","Anschaffungs-kosten (netto)","Anschaffungs-kosten (brutto)") -> Anschaffungs-kosten (netto) | D2: AfA (Absetzung für Abnutzung, Abschreibung) | E2: =+C2 -> Anschaffungs-kosten (netto) | F2: AfA (Absetzung für Abnutzung, Abschreibung) | G2: =+C2 -> Anschaffungs-kosten (netto) | H2: AfA (Absetzung für Abnutzung, Abschreibung) | I2: =+C2 -> Anschaffungs-kosten (netto) | J2: AfA (Absetzung für Abnutzung, Abschreibung)
A3: Investitionen (Anschaffungskosten höher als 800 EUR netto)
A4: PKW | C4: 0 | D4: =ROUND(IF($B4=0,0,C4/$B4/12*(12+1-Monat)),0) -> 0 | F4: =ROUND(IF(B4=0,0,IF(AND(C4=0,E4=0),0,(C4+E4)/B4)),0) -> 0 | H4: =ROUND(IF(AND($C4=0,$E4=0,$G4=0),0,($C4+$E4+$G4)/$B4),0) -> 0 | J4: =ROUND(IF(AND($C4=0,$E4=0,$G4=0,$I4=0),0,IF(AND(B4=3,Monat>=1),+$C4/$B4-$D4,($C4+$E4+$G4+$I4)/$B4)),0) -> 0
A5: 0 | C5: 0 | D5: =ROUND(IF($B5=0,0,C5/$B5/12*(12+1-Monat)),0) -> 0 | F5: =ROUND(IF(B5=0,0,IF(AND(C5=0,E5=0),0,(C5+E5)/B5)),0) -> 0 | H5: =ROUND(IF(AND($C5=0,$E5=0,$G5=0),0,($C5+$E5+$G5)/$B5),0) -> 0 | J5: =ROUND(IF(AND($C5=0,$E5=0,$G5=0,$I5=0),0,IF(AND(B5=3,Monat>=1),+$C5/$B5-$D5,($C5+$E5+$G5+$I5)/$B5)),0) -> 0
A6: 0 | C6: 0 | D6: =ROUND(IF($B6=0,0,C6/$B6/12*(12+1-Monat)),0) -> 0 | F6: =ROUND(IF(B6=0,0,IF(AND(C6=0,E6=0),0,(C6+E6)/B6)),0) -> 0 | H6: =ROUND(IF(AND($C6=0,$E6=0,$G6=0),0,($C6+$E6+$G6)/$B6),0) -> 0 | J6: =ROUND(IF(AND($C6=0,$E6=0,$G6=0,$I6=0),0,IF(AND(B6=3,Monat>=1),+$C6/$B6-$D6,($C6+$E6+$G6+$I6)/$B6)),0) -> 0
A7: 0 | C7: 0 | D7: =ROUND(IF($B7=0,0,C7/$B7/12*(12+1-Monat)),0) -> 0 | F7: =ROUND(IF(B7=0,0,IF(AND(C7=0,E7=0),0,(C7+E7)/B7)),0) -> 0 | H7: =ROUND(IF(AND($C7=0,$E7=0,$G7=0),0,($C7+$E7+$G7)/$B7),0) -> 0 | J7: =ROUND(IF(AND($C7=0,$E7=0,$G7=0,$I7=0),0,IF(AND(B7=3,Monat>=1),+$C7/$B7-$D7,($C7+$E7+$G7+$I7)/$B7)),0) -> 0
D8: =ROUND(IF($B8=0,0,C8/$B8/12*(12+1-Monat)),0) -> 0 | F8: =ROUND(IF(B8=0,0,IF(AND(C8=0,E8=0),0,(C8+E8)/B8)),0) -> 0 | H8: =ROUND(IF(AND($C8=0,$E8=0,$G8=0),0,($C8+$E8+$G8)/$B8),0) -> 0 | J8: =ROUND(IF(AND($C8=0,$E8=0,$G8=0,$I8=0),0,IF(AND(B8=3,Monat>=1),+$C8/$B8-$D8,($C8+$E8+$G8+$I8)/$B8)),0) -> 0
D9: =ROUND(IF($B9=0,0,C9/$B9/12*(12+1-Monat)),0) -> 0 | F9: =ROUND(IF(B9=0,0,IF(AND(C9=0,E9=0),0,(C9+E9)/B9)),0) -> 0 | H9: =ROUND(IF(AND($C9=0,$E9=0,$G9=0),0,($C9+$E9+$G9)/$B9),0) -> 0 | J9: =ROUND(IF(AND($C9=0,$E9=0,$G9=0,$I9=0),0,IF(AND(B9=3,Monat>=1),+$C9/$B9-$D9,($C9+$E9+$G9+$I9)/$B9)),0) -> 0
D10: =ROUND(IF($B10=0,0,C10/$B10/12*(12+1-Monat)),0) -> 0 | F10: =ROUND(IF(B10=0,0,IF(AND(C10=0,E10=0),0,(C10+E10)/B10)),0) -> 0 | H10: =ROUND(IF(AND($C10=0,$E10=0,$G10=0),0,($C10+$E10+$G10)/$B10),0) -> 0 | J10: =ROUND(IF(AND($C10=0,$E10=0,$G10=0,$I10=0),0,IF(AND(B10=3,Monat>=1),+$C10/$B10-$D10,($C10+$E10+$G10+$I10)/$B10)),0) -> 0
D11: =ROUND(IF($B11=0,0,C11/$B11/12*(12+1-Monat)),0) -> 0 | F11: =ROUND(IF(B11=0,0,IF(AND(C11=0,E11=0),0,(C11+E11)/B11)),0) -> 0 | H11: =ROUND(IF(AND($C11=0,$E11=0,$G11=0),0,($C11+$E11+$G11)/$B11),0) -> 0 | J11: =ROUND(IF(AND($C11=0,$E11=0,$G11=0,$I11=0),0,IF(AND(B11=3,Monat>=1),+$C11/$B11-$D11,($C11+$E11+$G11+$I11)/$B11)),0) -> 0
D12: =ROUND(IF($B12=0,0,C12/$B12/12*(12+1-Monat)),0) -> 0 | F12: =ROUND(IF(B12=0,0,IF(AND(C12=0,E12=0),0,(C12+E12)/B12)),0) -> 0 | H12: =ROUND(IF(AND($C12=0,$E12=0,$G12=0),0,($C12+$E12+$G12)/$B12),0) -> 0 | J12: =ROUND(IF(AND($C12=0,$E12=0,$G12=0,$I12=0),0,IF(AND(B12=3,Monat>=1),+$C12/$B12-$D12,($C12+$E12+$G12+$I12)/$B12)),0) -> 0
C13: =SUM(C4:C12) -> 0 | D13: =SUM(D4:D12) -> 0 | E13: =SUM(E4:E12) -> 0 | F13: =SUM(F4:F12) -> 0 | G13: =SUM(G4:G12) -> 0 | H13: =SUM(H4:H12) -> 0 | I13: =SUM(I4:I12) -> 0 | J13: =SUM(J4:J12) -> 0
A14: Sacheinlagen
D15: =ROUND(IF($B15=0,0,C15/$B15/12*(12+1-Monat)),0) -> 0 | F15: =ROUND(IF(B15=0,0,IF(AND(C15=0,E15=0),0,(C15+E15)/B15)),0) -> 0 | H15: =ROUND(IF(AND($C15=0,$E15=0,$G15=0),0,($C15+$E15+$G15)/$B15),0) -> 0 | J15: =ROUND(IF(AND($C15=0,$E15=0,$G15=0,$I15=0),0,IF(AND(B15=3,Monat>=1),+$C15/$B15-$D15,($C15+$E15+$G15+$I15)/$B15)),0) -> 0
D16: =ROUND(IF($B16=0,0,C16/$B16/12*(12+1-Monat)),0) -> 0 | F16: =ROUND(IF(B16=0,0,IF(AND(C16=0,E16=0),0,(C16+E16)/B16)),0) -> 0 | H16: =ROUND(IF(AND($C16=0,$E16=0,$G16=0),0,($C16+$E16+$G16)/$B16),0) -> 0 | J16: =ROUND(IF(AND($C16=0,$E16=0,$G16=0,$I16=0),0,IF(AND(B16=3,Monat>=1),+$C16/$B16-$D16,($C16+$E16+$G16+$I16)/$B16)),0) -> 0
D17: =ROUND(IF($B17=0,0,C17/$B17/12*(12+1-Monat)),0) -> 0 | F17: =ROUND(IF(B17=0,0,IF(AND(C17=0,E17=0),0,(C17+E17)/B17)),0) -> 0 | H17: =ROUND(IF(AND($C17=0,$E17=0,$G17=0),0,($C17+$E17+$G17)/$B17),0) -> 0 | J17: =ROUND(IF(AND($C17=0,$E17=0,$G17=0,$I17=0),0,IF(AND(B17=3,Monat>=1),+$C17/$B17-$D17,($C17+$E17+$G17+$I17)/$B17)),0) -> 0
D18: =ROUND(IF($B18=0,0,C18/$B18/12*(12+1-Monat)),0) -> 0 | F18: =ROUND(IF(B18=0,0,IF(AND(C18=0,E18=0),0,(C18+E18)/B18)),0) -> 0 | H18: =ROUND(IF(AND($C18=0,$E18=0,$G18=0),0,($C18+$E18+$G18)/$B18),0) -> 0 | J18: =ROUND(IF(AND($C18=0,$E18=0,$G18=0,$I18=0),0,IF(AND(B18=3,Monat>=1),+$C18/$B18-$D18,($C18+$E18+$G18+$I18)/$B18)),0) -> 0
D19: =ROUND(IF($B19=0,0,C19/$B19/12*(12+1-Monat)),0) -> 0 | F19: =ROUND(IF(B19=0,0,IF(AND(C19=0,E19=0),0,(C19+E19)/B19)),0) -> 0 | H19: =ROUND(IF(AND($C19=0,$E19=0,$G19=0),0,($C19+$E19+$G19)/$B19),0) -> 0 | J19: =ROUND(IF(AND($C19=0,$E19=0,$G19=0,$I19=0),0,IF(AND(B19=3,Monat>=1),+$C19/$B19-$D19,($C19+$E19+$G19+$I19)/$B19)),0) -> 0
D20: =ROUND(IF($B20=0,0,C20/$B20/12*(12+1-Monat)),0) -> 0 | F20: =ROUND(IF(B20=0,0,IF(AND(C20=0,E20=0),0,(C20+E20)/B20)),0) -> 0 | H20: =ROUND(IF(AND($C20=0,$E20=0,$G20=0),0,($C20+$E20+$G20)/$B20),0) -> 0 | J20: =ROUND(IF(AND($C20=0,$E20=0,$G20=0,$I20=0),0,IF(AND(B20=3,Monat>=1),+$C20/$B20-$D20,($C20+$E20+$G20+$I20)/$B20)),0) -> 0
D21: =ROUND(IF($B21=0,0,C21/$B21/12*(12+1-Monat)),0) -> 0 | F21: =ROUND(IF(B21=0,0,IF(AND(C21=0,E21=0),0,(C21+E21)/B21)),0) -> 0 | H21: =ROUND(IF(AND($C21=0,$E21=0,$G21=0),0,($C21+$E21+$G21)/$B21),0) -> 0 | J21: =ROUND(IF(AND($C21=0,$E21=0,$G21=0,$I21=0),0,IF(AND(B21=3,Monat>=1),+$C21/$B21-$D21,($C21+$E21+$G21+$I21)/$B21)),0) -> 0
C22: =SUM(C15:C21) -> 0 | D22: =SUM(D15:D21) -> 0 | E22: =SUM(E15:E21) -> 0 | F22: =SUM(F15:F21) -> 0 | G22: =SUM(G15:G21) -> 0 | H22: =SUM(H15:H21) -> 0 | I22: =SUM(I15:I21) -> 0 | J22: =SUM(J15:J21) -> 0
A23: Geringwertige Wirtschaftsgüter (Anschaffungskosten bis 800 EUR netto)
D24: =IF(C24=0,0,IF(+C24>gwg,"Anschaffungskosten zu hoch für ein Geringwertiges Wirtschaftsgut - Ansatz unter Investitionen",C24)) -> 0 | F24: =IF(E24=0,0,IF(+E24>gwg,"Anschaffungskosten zu hoch für ein Geringwertiges Wirtschaftsgut - Ansatz unter Investitionen",E24)) -> 0 | H24: =IF(G24=0,0,IF(+G24>gwg,"Anschaffungskosten zu hoch für ein Geringwertiges Wirtschaftsgut - Ansatz unter Investitionen",G24)) -> 0 | J24: =IF(I24=0,0,IF(+I24>gwg,"Anschaffungskosten zu hoch für ein Geringwertiges Wirtschaftsgut - Ansatz unter Investitionen",I24)) -> 0
D25: =IF(C25=0,0,IF(+C25>gwg,"Anschaffungskosten zu hoch für ein Geringwertiges Wirtschaftsgut - Ansatz unter Investitionen",C25)) -> 0 | F25: =IF(E25=0,0,IF(+E25>gwg,"Anschaffungskosten zu hoch für ein Geringwertiges Wirtschaftsgut - Ansatz unter Investitionen",E25)) -> 0 | H25: =IF(G25=0,0,IF(+G25>gwg,"Anschaffungskosten zu hoch für ein Geringwertiges Wirtschaftsgut - Ansatz unter Investitionen",G25)) -> 0 | J25: =IF(I25=0,0,IF(+I25>gwg,"Anschaffungskosten zu hoch für ein Geringwertiges Wirtschaftsgut - Ansatz unter Investitionen",I25)) -> 0
D26: =IF(C26=0,0,IF(+C26>gwg,"Anschaffungskosten zu hoch für ein Geringwertiges Wirtschaftsgut - Ansatz unter Investitionen",C26)) -> 0 | F26: =IF(E26=0,0,IF(+E26>gwg,"Anschaffungskosten zu hoch für ein Geringwertiges Wirtschaftsgut - Ansatz unter Investitionen",E26)) -> 0 | H26: =IF(G26=0,0,IF(+G26>gwg,"Anschaffungskosten zu hoch für ein Geringwertiges Wirtschaftsgut - Ansatz unter Investitionen",G26)) -> 0 | J26: =IF(I26=0,0,IF(+I26>gwg,"Anschaffungskosten zu hoch für ein Geringwertiges Wirtschaftsgut - Ansatz unter Investitionen",I26)) -> 0
D27: =IF(C27=0,0,IF(+C27>gwg,"Anschaffungskosten zu hoch für ein Geringwertiges Wirtschaftsgut - Ansatz unter Investitionen",C27)) -> 0 | F27: =IF(E27=0,0,IF(+E27>gwg,"Anschaffungskosten zu hoch für ein Geringwertiges Wirtschaftsgut - Ansatz unter Investitionen",E27)) -> 0 | H27: =IF(G27=0,0,IF(+G27>gwg,"Anschaffungskosten zu hoch für ein Geringwertiges Wirtschaftsgut - Ansatz unter Investitionen",G27)) -> 0 | J27: =IF(I27=0,0,IF(+I27>gwg,"Anschaffungskosten zu hoch für ein Geringwertiges Wirtschaftsgut - Ansatz unter Investitionen",I27)) -> 0
D28: =IF(C28=0,0,IF(+C28>gwg,"Anschaffungskosten zu hoch für ein Geringwertiges Wirtschaftsgut - Ansatz unter Investitionen",C28)) -> 0 | F28: =IF(E28=0,0,IF(+E28>gwg,"Anschaffungskosten zu hoch für ein Geringwertiges Wirtschaftsgut - Ansatz unter Investitionen",E28)) -> 0 | H28: =IF(G28=0,0,IF(+G28>gwg,"Anschaffungskosten zu hoch für ein Geringwertiges Wirtschaftsgut - Ansatz unter Investitionen",G28)) -> 0 | J28: =IF(I28=0,0,IF(+I28>gwg,"Anschaffungskosten zu hoch für ein Geringwertiges Wirtschaftsgut - Ansatz unter Investitionen",I28)) -> 0
D29: =IF(C29=0,0,IF(+C29>gwg,"Anschaffungskosten zu hoch für ein Geringwertiges Wirtschaftsgut - Ansatz unter Investitionen",C29)) -> 0 | F29: =IF(E29=0,0,IF(+E29>gwg,"Anschaffungskosten zu hoch für ein Geringwertiges Wirtschaftsgut - Ansatz unter Investitionen",E29)) -> 0 | H29: =IF(G29=0,0,IF(+G29>gwg,"Anschaffungskosten zu hoch für ein Geringwertiges Wirtschaftsgut - Ansatz unter Investitionen",G29)) -> 0 | J29: =IF(I29=0,0,IF(+I29>gwg,"Anschaffungskosten zu hoch für ein Geringwertiges Wirtschaftsgut - Ansatz unter Investitionen",I29)) -> 0
D30: =IF(C30=0,0,IF(+C30>gwg,"Anschaffungskosten zu hoch für ein Geringwertiges Wirtschaftsgut - Ansatz unter Investitionen",C30)) -> 0 | F30: =IF(E30=0,0,IF(+E30>gwg,"Anschaffungskosten zu hoch für ein Geringwertiges Wirtschaftsgut - Ansatz unter Investitionen",E30)) -> 0 | H30: =IF(G30=0,0,IF(+G30>gwg,"Anschaffungskosten zu hoch für ein Geringwertiges Wirtschaftsgut - Ansatz unter Investitionen",G30)) -> 0 | J30: =IF(I30=0,0,IF(+I30>gwg,"Anschaffungskosten zu hoch für ein Geringwertiges Wirtschaftsgut - Ansatz unter Investitionen",I30)) -> 0
D31: =IF(C31=0,0,IF(+C31>gwg,"Anschaffungskosten zu hoch für ein Geringwertiges Wirtschaftsgut - Ansatz unter Investitionen",C31)) -> 0 | F31: =IF(E31=0,0,IF(+E31>gwg,"Anschaffungskosten zu hoch für ein Geringwertiges Wirtschaftsgut - Ansatz unter Investitionen",E31)) -> 0 | H31: =IF(G31=0,0,IF(+G31>gwg,"Anschaffungskosten zu hoch für ein Geringwertiges Wirtschaftsgut - Ansatz unter Investitionen",G31)) -> 0 | J31: =IF(I31=0,0,IF(+I31>gwg,"Anschaffungskosten zu hoch für ein Geringwertiges Wirtschaftsgut - Ansatz unter Investitionen",I31)) -> 0
D32: =IF(C32=0,0,IF(+C32>gwg,"Anschaffungskosten zu hoch für ein Geringwertiges Wirtschaftsgut - Ansatz unter Investitionen",C32)) -> 0 | F32: =IF(E32=0,0,IF(+E32>gwg,"Anschaffungskosten zu hoch für ein Geringwertiges Wirtschaftsgut - Ansatz unter Investitionen",E32)) -> 0 | H32: =IF(G32=0,0,IF(+G32>gwg,"Anschaffungskosten zu hoch für ein Geringwertiges Wirtschaftsgut - Ansatz unter Investitionen",G32)) -> 0 | J32: =IF(I32=0,0,IF(+I32>gwg,"Anschaffungskosten zu hoch für ein Geringwertiges Wirtschaftsgut - Ansatz unter Investitionen",I32)) -> 0
D33: =IF(C33=0,0,IF(+C33>gwg,"Anschaffungskosten zu hoch für ein Geringwertiges Wirtschaftsgut - Ansatz unter Investitionen",C33)) -> 0 | F33: =IF(E33=0,0,IF(+E33>gwg,"Anschaffungskosten zu hoch für ein Geringwertiges Wirtschaftsgut - Ansatz unter Investitionen",E33)) -> 0 | H33: =IF(G33=0,0,IF(+G33>gwg,"Anschaffungskosten zu hoch für ein Geringwertiges Wirtschaftsgut - Ansatz unter Investitionen",G33)) -> 0 | J33: =IF(I33=0,0,IF(+I33>gwg,"Anschaffungskosten zu hoch für ein Geringwertiges Wirtschaftsgut - Ansatz unter Investitionen",I33)) -> 0
D34: =IF(C34=0,0,IF(+C34>gwg,"Anschaffungskosten zu hoch für ein Geringwertiges Wirtschaftsgut - Ansatz unter Investitionen",C34)) -> 0 | F34: =IF(E34=0,0,IF(+E34>gwg,"Anschaffungskosten zu hoch für ein Geringwertiges Wirtschaftsgut - Ansatz unter Investitionen",E34)) -> 0 | H34: =IF(G34=0,0,IF(+G34>gwg,"Anschaffungskosten zu hoch für ein Geringwertiges Wirtschaftsgut - Ansatz unter Investitionen",G34)) -> 0 | J34: =IF(I34=0,0,IF(+I34>gwg,"Anschaffungskosten zu hoch für ein Geringwertiges Wirtschaftsgut - Ansatz unter Investitionen",I34)) -> 0
C35: =SUM(C24:C34) -> 0 | D35: =SUM(D24:D34) -> 0 | E35: =SUM(E24:E34) -> 0 | F35: =SUM(F24:F34) -> 0 | G35: =SUM(G24:G34) -> 0 | H35: =SUM(H24:H34) -> 0 | I35: =SUM(I24:I34) -> 0 | J35: =SUM(J24:J34) -> 0
A37: Summe | C37: =+C13+C22+C35 -> 0 | D37: =+D13+D22+D35 -> 0 | E37: =+E13+E22+E35 -> 0 | F37: =+F13+F22+F35 -> 0 | G37: =+G13+G22+G35 -> 0 | H37: =+H13+H22+H35 -> 0 | I37: =+I13+I22+I35 -> 0 | J37: =+J13+J22+J35 -> 0
A38: monatlich im Anschaffungsjahr (einschl. GWG) | D38: =ROUND((+D13+D22+gwgeins)/(12+1-Monat),0) -> 0 | F38: =ROUND((F13+F22+F35)/12,0) -> 0 | H38: =ROUND((H13+H22+H35)/12,0) -> 0 | J38: =ROUND((J13+J22+J35)/12,0) -> 0
A40: Warenlager-Erstausstattung und -aufstockung (Betriebsausgaben)
C46: =SUM(C41:C45) -> 0 | E46: =SUM(E41:E45) -> 0 | G46: =SUM(G41:G45) -> 0 | I46: =SUM(I41:I45) -> 0

Sheet Finanzierungsplan
A1: Kapitalbedarfsplan
E2: EUR
A3: Anschaffungen im Jahr der Gründung
B4: Investitionen
C5: Neuanschaffungen | D5: =IF('Infos vor dem Start'!A$17="x",+Investitionsplan!C13,+Investitionsplan!C13*(1+VSt)) -> 0
C6: Sacheinlagen | D6: =+Investitionsplan!C22 -> 0
B7: geringwertige Wirtschaftsgüter | D7: =IF('Infos vor dem Start'!A$17="x",+Investitionsplan!C35,+Investitionsplan!C35*(1+VSt)) -> 0
B8: Warenlager-Erstausstattung | D8: =IF('Infos vor dem Start'!A$17="x",+Investitionsplan!C46,+Investitionsplan!C46*(1+VSt)) -> 0 | E8: =SUM(D5:D8) -> 0
A10: Betriebsmittel
A11: Kapitalbedarf | E11: =SUM(E4:E10) -> 0
A13: Finanzierungsplan
E14: EUR
A15: Eigenkapital
B16: liquide Mittel | D16: 3000
B17: Sacheinlagen | D17: =+D6 -> 0 | E17: =SUM(D16:D17) -> 3000
A19: Fremdkapital (Auszahlungsbetrag)
A20: Hausbankdarlehen
A21: Startgeld
A22: KfW Kapital für Gründer
D23: 0
A26: Privatdarlehen | D26: 0 | E26: =SUM(D20:D26) -> 0
E27: =SUM(E16:E26) -> 3000
A29: =IF(E29>=0,"Überdeckung","Unterdeckung") -> Überdeckung | E29: =+E27-E11 -> 3000
A30: =IF(MIN(Liquiditätsplan!B65:M65,Liquiditätsplan!O65:Z65,Liquiditätsplan!AB65:AM65,Liquiditätsplan!AO65:AZ65)<0,"Liquiditätsunterdeckung - bitte überprüfen Sie Ihre Finanzierungsstrategie!","") | E30: =IF(MIN(Liquiditätsplan!D65:O65,Liquiditätsplan!Q65:AB65,Liquiditätsplan!AD65:AO65,Liquiditätsplan!AQ65:BB65)<0,MIN(Liquiditätsplan!D65:O65,Liquiditätsplan!Q65:AB65,Liquiditätsplan!AD65:AO65,Liquiditätsplan!AQ65:BB65),"")

Sheet Daten Liquiditätskurve
A1: 1. Jahr | M1: 2. Jahr | Y1: 3. Jahr | AK1: 4. Jahr
A2: Jan | B2: Feb | C2: Mrz | D2: Apr | E2: Mai | F2: Jun | G2: Jul | H2: Aug | I2: Sep | J2: Okt | K2: Nov | L2: Dez | M2: Jan | N2: Feb | O2: Mrz | P2: Apr | Q2: Mai | R2: Jun | S2: Jul | T2: Aug | U2: Sep | V2: Okt | W2: Nov | X2: Dez | Y2: Jan | Z2: Feb | AA2: Mrz | AB2: Apr | AC2: Mai | AD2: Jun | AE2: Jul | AF2: Aug | AG2: Sep | AH2: Okt | AI2: Nov | AJ2: Dez | AK2: Jan | AL2: Feb | AM2: Mrz | AN2: Apr | AO2: Mai | AP2: Jun | AQ2: Jul | AR2: Aug | AS2: Sep | AT2: Okt | AU2: Nov | AV2: Dez
A3: =+Liquiditätsplan!D65 -> 0 | B3: =+Liquiditätsplan!E65 -> 0 | C3: =+Liquiditätsplan!F65 -> 0 | D3: =+Liquiditätsplan!G65 -> 0 | E3: =+Liquiditätsplan!H65 -> 0 | F3: =+Liquiditätsplan!I65 -> 0 | G3: =+Liquiditätsplan!J65 -> 0 | H3: =+Liquiditätsplan!K65 -> 0 | ... L3: =+Liquiditätsplan!O65 -> 14449.9 | M3: =+Liquiditätsplan!Q65 -> 33413.2 | N3: =+Liquiditätsplan!R65 -> 30956.5 | O3: =+Liquiditätsplan!S65 -> 28499.8 | P3: =+Liquiditätsplan!T65 -> 26043.1 | Q3: =+Liquiditätsplan!U65 -> 23586.4 | R3: =+Liquiditätsplan!V65 -> 21129.7 | S3: =+Liquiditätsplan!W65 -> 18673 | T3: =+Liquiditätsplan!X65 -> 16216.3 | ... X3: =+Liquiditätsplan!AB65 -> 6389.5 | Y3: =+Liquiditätsplan!AD65 -> 6389.5 | Z3: =+Liquiditätsplan!AE65 -> 6389.5 | AA3: =+Liquiditätsplan!AF65 -> 6389.5 | AB3: =+Liquiditätsplan!AG65 -> 6389.5 | AC3: =+Liquiditätsplan!AH65 -> 6389.5 | AD3: =+Liquiditätsplan!AI65 -> 6389.5 | AE3: =+Liquiditätsplan!AJ65 -> 6389.5 | AF3: =+Liquiditätsplan!AK65 -> 6389.5 | ... AJ3: =+Liquiditätsplan!AO65 -> 6389.5 | AK3: =+Liquiditätsplan!AQ65 -> 6389.5 | AL3: =+Liquiditätsplan!AR65 -> 6389.5 | AM3: =+Liquiditätsplan!AS65 -> 6389.5 | AN3: =+Liquiditätsplan!AT65 -> 6389.5 | AO3: =+Liquiditätsplan!AU65 -> 6389.5 | AP3: =+Liquiditätsplan!AV65 -> 6389.5 | AQ3: =+Liquiditätsplan!AW65 -> 6389.5 | AR3: =+Liquiditätsplan!AX65 -> 6389.5 | ... AV3: =+Liquiditätsplan!BB65 -> 6389.5

Sheet Privater Finanzbedarf
C1: =+gj -> 2026 | D1: =+gj+1 -> 2027 | E1: =+gj+2 -> 2028 | F1: =+gj+3 -> 2029
C2: monatlich | D2: monatlich | E2: monatlich | F2: monatlich
A3: Private Einnahmen (außerhalb der Selbstständigkeit)
A4: Nettogehalt Lebenspartner/in
A5: Kindergeld
A6: Erziehungsgeld
A7: Unterhaltsanspruch
A8: Einkommen aus Vermietung und Verpachtung
A9: Einkommen aus Kapitalvermögen
A10: Sonstige Einkünfte
A11: =IF(kapges=0,"","Gründungszuschuss/Einstiegsgeld")
A12: =IF(kapges=0,"","Gründungszuschuss/Einstiegsgeld")
A13: =IF(kapges=0,"","Gründungszuschuss/Einstiegsgeld")
A14: =IF(kapges=0,"","Gründungszuschuss/Einstiegsgeld")
A15: =IF(kapges=0,"","Gründungszuschuss/Einstiegsgeld")
A16: Summe der privaten Einnahmen | C16: =SUM(C4:C15) -> 0 | D16: =SUM(D4:D15) -> 0 | E16: =SUM(E4:E15) -> 0 | F16: =SUM(F4:F15) -> 0
A17: Private Ausgaben
A18: Private Miete (einschließlich Nebenkosten) | C18: 0 | D18: 0 | E18: 0
A19: Krankenversicherung | C19: 0 | D19: 0 | E19: 0
A20: Rentenversicherung/Altersvorsorge | C20: 0 | D20: 0 | E20: 0
A21: Sonstige Versicherungen | C21: 0 | D21: 0 | E21: 0
A22: Zinsen und Tilgung privater Darlehen | C22: 0 | D22: 0 | E22: 0
A23: Rücklagen für Einkommensteuer | C23: 0 | D23: 0 | E23: 0
A24: Rücklagen für Neuanschaffungen | C24: 0 | D24: 0 | E24: 0
A25: Unterhaltsverpflichtung | C25: 0 | D25: 0 | E25: 0
A26: Lebensunterhalt 1) | C26: 0 | D26: 0 | E26: 0
A27: Summe der privaten Ausgaben | C27: =SUM(C18:C26) -> 0 | D27: =SUM(D18:D26) -> 0 | E27: =SUM(E18:E26) -> 0 | F27: =SUM(F18:F26) -> 0
A29: Privater Finanzbedarf = erforderlicher Unternehmerlohn | C29: =-C16+C27 -> 0 | D29: =-D16+D27 -> 0 | E29: =-E16+E27 -> 0 | F29: =-F16+F27 -> 0
A31: 1) Richtwerte - ohne Miete, Versicherungen, Kosten privater Darlehen, Steuern, Rücklagen und Unterhaltsverpflichtungen (s.o.)
A32: 900 EUR | B32: 1 Erwachsener
A33: 1.025 EUR | B33: 2 Erwachsene
A34: 235 EUR | B34: je Kind
A36: =IF('Infos vor dem Start'!A19=0,"Ein eventueller Gründungszuschuss oder Einstiegsgeld wird nicht hier, sondern in der Liquiditätsplanung eingetragen.","") -> Ein eventueller Gründungszuschuss oder Einstiegsgeld wird nicht hier, sondern in der Liquiditätsplanung eingetragen.

Sheet Priv. Finanzb. 2. Gründ.
C1: =+Rentabilitätsvorschau!P1 -> 2026 | D1: =+Rentabilitätsvorschau!AC1 -> 2027 | E1: =+Rentabilitätsvorschau!AP1 -> 2028 | F1: =+Rentabilitätsvorschau!BC1 -> 2029
C2: monatlich | D2: monatlich | E2: monatlich | F2: monatlich
A3: Private Einnahmen (außerhalb der Selbstständigkeit)
A4: Nettogehalt Lebenspartner/in
A5: Kindergeld
A6: Erziehungsgeld
A7: Unterhaltsanspruch
A8: Einkommen aus Vermietung und Verpachtung
A9: Einkommen aus Kapitalvermögen
A10: Sonstige Einkünfte
A11: =IF(kapges=0,"","Gründungszuschuss/Einstiegsgeld")
A12: =IF(kapges=0,"","Gründungszuschuss/Einstiegsgeld")
A13: =IF(kapges=0,"","Gründungszuschuss/Einstiegsgeld")
A14: =IF(kapges=0,"","Gründungszuschuss/Einstiegsgeld")
A15: =IF(kapges=0,"","Gründungszuschuss/Einstiegsgeld")
A16: Summe der privaten Einnahmen | C16: =SUM(C4:C15) -> 0 | D16: =SUM(D4:D15) -> 0 | E16: =SUM(E4:E15) -> 0 | F16: =SUM(F4:F15) -> 0
A17: Private Ausgaben
A18: Private Miete (einschließlich Nebenkosten)
A19: Krankenversicherung
A20: Rentenversicherung/Altersvorsorge
A21: Sonstige Versicherungen
A22: Zinsen und Tilgung privater Darlehen
A23: Rücklagen für Einkommensteuer
A24: Rücklagen für Neuanschaffungen
A25: Unterhaltsverpflichtung
A26: Lebensunterhalt 1)
A27: Summe der privaten Ausgaben | C27: =SUM(C18:C26) -> 0 | D27: =SUM(D18:D26) -> 0 | E27: =SUM(E18:E26) -> 0 | F27: =SUM(F18:F26) -> 0
A29: Privater Finanzbedarf = erforderlicher Unternehmerlohn | C29: =-C16+C27 -> 0 | D29: =-D16+D27 -> 0 | E29: =-E16+E27 -> 0 | F29: =-F16+F27 -> 0
A31: 1) Richtwerte - ohne Miete, Versicherungen, Kosten privater Darlehen, Steuern, Rücklagen und Unterhaltsverpflichtungen (s.o.)
A32: 900 EUR | B32: 1 Erwachsener
A33: 1.025 EUR | B33: 2 Erwachsene
A34: 235 EUR | B34: je Kind
A36: =IF('Infos vor dem Start'!A19=0,"Ein eventueller Gründungszuschuss oder Einstiegsgeld wird nicht hier, sondern in der Liquiditätsplanung eingetragen.","") -> Ein eventueller Gründungszuschuss oder Einstiegsgeld wird nicht hier, sondern in der Liquiditätsplanung eingetragen.

Sheet Priv. Finanzb. 3. Gründ
C1: =+Rentabilitätsvorschau!P1 -> 2026 | D1: =+Rentabilitätsvorschau!AC1 -> 2027 | E1: =+Rentabilitätsvorschau!AP1 -> 2028 | F1: =+Rentabilitätsvorschau!BC1 -> 2029
C2: monatlich | D2: monatlich | E2: monatlich | F2: monatlich
A3: Private Einnahmen (außerhalb der Selbstständigkeit)
A4: Nettogehalt Lebenspartner/in
A5: Kindergeld
A6: Erziehungsgeld
A7: Unterhaltsanspruch
A8: Einkommen aus Vermietung und Verpachtung
A9: Einkommen aus Kapitalvermögen
A10: Sonstige Einkünfte
A11: =IF(kapges=0,"","Gründungszuschuss/Einstiegsgeld")
A12: =IF(kapges=0,"","Gründungszuschuss/Einstiegsgeld")
A13: =IF(kapges=0,"","Gründungszuschuss/Einstiegsgeld")
A14: =IF(kapges=0,"","Gründungszuschuss/Einstiegsgeld")
A15: =IF(kapges=0,"","Gründungszuschuss/Einstiegsgeld")
A16: Summe der privaten Einnahmen | C16: =SUM(C4:C15) -> 0 | D16: =SUM(D4:D15) -> 0 | E16: =SUM(E4:E15) -> 0 | F16: =SUM(F4:F15) -> 0
A17: Private Ausgaben
A18: Private Miete (einschließlich Nebenkosten)
A19: Krankenversicherung
A20: Rentenversicherung/Altersvorsorge
A21: Sonstige Versicherungen
A22: Zinsen und Tilgung privater Darlehen
A23: Rücklagen für Einkommensteuer
A24: Rücklagen für Neuanschaffungen
A25: Unterhaltsverpflichtung
A26: Lebensunterhalt 1)
A27: Summe der privaten Ausgaben | C27: =SUM(C18:C26) -> 0 | D27: =SUM(D18:D26) -> 0 | E27: =SUM(E18:E26) -> 0 | F27: =SUM(F18:F26) -> 0
A29: Privater Finanzbedarf = erforderlicher Unternehmerlohn | C29: =-C16+C27 -> 0 | D29: =-D16+D27 -> 0 | E29: =-E16+E27 -> 0 | F29: =-F16+F27 -> 0
A31: 1) Richtwerte - ohne Miete, Versicherungen, Kosten privater Darlehen, Steuern, Rücklagen und Unterhaltsverpflichtungen (s.o.)
A32: 900 EUR | B32: 1 Erwachsener
A33: 1.025 EUR | B33: 2 Erwachsene
A34: 235 EUR | B34: je Kind
A36: =IF('Infos vor dem Start'!A19=0,"Ein eventueller Gründungszuschuss oder Einstiegsgeld wird nicht hier, sondern in der Liquiditätsplanung eingetragen.","") -> Ein eventueller Gründungszuschuss oder Einstiegsgeld wird nicht hier, sondern in der Liquiditätsplanung eingetragen.

Sheet Priv. Finanzbed. Summe
A1: =+'Privater Finanzbedarf'!C4+'Priv. Finanzb. 2. Gründ.'!C4+'Priv. Finanzb. 3. Gründ'!C4 -> 0 | C1: =+Rentabilitätsvorschau!P1 -> 2026 | D1: =+Rentabilitätsvorschau!AC1 -> 2027 | E1: =+Rentabilitätsvorschau!AP1 -> 2028 | F1: =+Rentabilitätsvorschau!BC1 -> 2029
C2: monatlich | D2: monatlich | E2: monatlich | F2: monatlich
A3: Private Einnahmen (außerhalb der Selbstständigkeit)
A4: Nettogehalt Lebenspartner/in | C4: =+'Privater Finanzbedarf'!C4+'Priv. Finanzb. 2. Gründ.'!C4+'Priv. Finanzb. 3. Gründ'!C4 -> 0 | D4: =+'Privater Finanzbedarf'!D4+'Priv. Finanzb. 2. Gründ.'!D4+'Priv. Finanzb. 3. Gründ'!D4 -> 0 | E4: =+'Privater Finanzbedarf'!E4+'Priv. Finanzb. 2. Gründ.'!E4+'Priv. Finanzb. 3. Gründ'!E4 -> 0 | F4: =+'Privater Finanzbedarf'!F4+'Priv. Finanzb. 2. Gründ.'!F4+'Priv. Finanzb. 3. Gründ'!F4 -> 0
A5: Kindergeld | C5: =+'Privater Finanzbedarf'!C5+'Priv. Finanzb. 2. Gründ.'!C5+'Priv. Finanzb. 3. Gründ'!C5 -> 0 | D5: =+'Privater Finanzbedarf'!D5+'Priv. Finanzb. 2. Gründ.'!D5+'Priv. Finanzb. 3. Gründ'!D5 -> 0 | E5: =+'Privater Finanzbedarf'!E5+'Priv. Finanzb. 2. Gründ.'!E5+'Priv. Finanzb. 3. Gründ'!E5 -> 0 | F5: =+'Privater Finanzbedarf'!F5+'Priv. Finanzb. 2. Gründ.'!F5+'Priv. Finanzb. 3. Gründ'!F5 -> 0
A6: Erziehungsgeld | C6: =+'Privater Finanzbedarf'!C6+'Priv. Finanzb. 2. Gründ.'!C6+'Priv. Finanzb. 3. Gründ'!C6 -> 0 | D6: =+'Privater Finanzbedarf'!D6+'Priv. Finanzb. 2. Gründ.'!D6+'Priv. Finanzb. 3. Gründ'!D6 -> 0 | E6: =+'Privater Finanzbedarf'!E6+'Priv. Finanzb. 2. Gründ.'!E6+'Priv. Finanzb. 3. Gründ'!E6 -> 0 | F6: =+'Privater Finanzbedarf'!F6+'Priv. Finanzb. 2. Gründ.'!F6+'Priv. Finanzb. 3. Gründ'!F6 -> 0
A7: Unterhaltsanspruch | C7: =+'Privater Finanzbedarf'!C7+'Priv. Finanzb. 2. Gründ.'!C7+'Priv. Finanzb. 3. Gründ'!C7 -> 0 | D7: =+'Privater Finanzbedarf'!D7+'Priv. Finanzb. 2. Gründ.'!D7+'Priv. Finanzb. 3. Gründ'!D7 -> 0 | E7: =+'Privater Finanzbedarf'!E7+'Priv. Finanzb. 2. Gründ.'!E7+'Priv. Finanzb. 3. Gründ'!E7 -> 0 | F7: =+'Privater Finanzbedarf'!F7+'Priv. Finanzb. 2. Gründ.'!F7+'Priv. Finanzb. 3. Gründ'!F7 -> 0
A8: Einkommen aus Vermietung und Verpachtung | C8: =+'Privater Finanzbedarf'!C8+'Priv. Finanzb. 2. Gründ.'!C8+'Priv. Finanzb. 3. Gründ'!C8 -> 0 | D8: =+'Privater Finanzbedarf'!D8+'Priv. Finanzb. 2. Gründ.'!D8+'Priv. Finanzb. 3. Gründ'!D8 -> 0 | E8: =+'Privater Finanzbedarf'!E8+'Priv. Finanzb. 2. Gründ.'!E8+'Priv. Finanzb. 3. Gründ'!E8 -> 0 | F8: =+'Privater Finanzbedarf'!F8+'Priv. Finanzb. 2. Gründ.'!F8+'Priv. Finanzb. 3. Gründ'!F8 -> 0
A9: Einkommen aus Kapitalvermögen | C9: =+'Privater Finanzbedarf'!C9+'Priv. Finanzb. 2. Gründ.'!C9+'Priv. Finanzb. 3. Gründ'!C9 -> 0 | D9: =+'Privater Finanzbedarf'!D9+'Priv. Finanzb. 2. Gründ.'!D9+'Priv. Finanzb. 3. Gründ'!D9 -> 0 | E9: =+'Privater Finanzbedarf'!E9+'Priv. Finanzb. 2. Gründ.'!E9+'Priv. Finanzb. 3. Gründ'!E9 -> 0 | F9: =+'Privater Finanzbedarf'!F9+'Priv. Finanzb. 2. Gründ.'!F9+'Priv. Finanzb. 3. Gründ'!F9 -> 0
A10: Sonstige Einkünfte | C10: =+'Privater Finanzbedarf'!C10+'Priv. Finanzb. 2. Gründ.'!C10+'Priv. Finanzb. 3. Gründ'!C10 -> 0 | D10: =+'Privater Finanzbedarf'!D10+'Priv. Finanzb. 2. Gründ.'!D10+'Priv. Finanzb. 3. Gründ'!D10 -> 0 | E10: =+'Privater Finanzbedarf'!E10+'Priv. Finanzb. 2. Gründ.'!E10+'Priv. Finanzb. 3. Gründ'!E10 -> 0 | F10: =+'Privater Finanzbedarf'!F10+'Priv. Finanzb. 2. Gründ.'!F10+'Priv. Finanzb. 3. Gründ'!F10 -> 0
A11: vgl. Einzelaufstellungen des Privaten Finanzbedarfs | C11: =+'Privater Finanzbedarf'!C11+'Priv. Finanzb. 2. Gründ.'!C11+'Priv. Finanzb. 3. Gründ'!C11 -> 0 | D11: =+'Privater Finanzbedarf'!D11+'Priv. Finanzb. 2. Gründ.'!D11+'Priv. Finanzb. 3. Gründ'!D11 -> 0 | E11: =+'Privater Finanzbedarf'!E11+'Priv. Finanzb. 2. Gründ.'!E11+'Priv. Finanzb. 3. Gründ'!E11 -> 0 | F11: =+'Privater Finanzbedarf'!F11+'Priv. Finanzb. 2. Gründ.'!F11+'Priv. Finanzb. 3. Gründ'!F11 -> 0
A12: vgl. Einzelaufstellungen des Privaten Finanzbedarfs | C12: =+'Privater Finanzbedarf'!C12+'Priv. Finanzb. 2. Gründ.'!C12+'Priv. Finanzb. 3. Gründ'!C12 -> 0 | D12: =+'Privater Finanzbedarf'!D12+'Priv. Finanzb. 2. Gründ.'!D12+'Priv. Finanzb. 3. Gründ'!D12 -> 0 | E12: =+'Privater Finanzbedarf'!E12+'Priv. Finanzb. 2. Gründ.'!E12+'Priv. Finanzb. 3. Gründ'!E12 -> 0 | F12: =+'Privater Finanzbedarf'!F12+'Priv. Finanzb. 2. Gründ.'!F12+'Priv. Finanzb. 3. Gründ'!F12 -> 0
A13: vgl. Einzelaufstellungen des Privaten Finanzbedarfs | C13: =+'Privater Finanzbedarf'!C13+'Priv. Finanzb. 2. Gründ.'!C13+'Priv. Finanzb. 3. Gründ'!C13 -> 0 | D13: =+'Privater Finanzbedarf'!D13+'Priv. Finanzb. 2. Gründ.'!D13+'Priv. Finanzb. 3. Gründ'!D13 -> 0 | E13: =+'Privater Finanzbedarf'!E13+'Priv. Finanzb. 2. Gründ.'!E13+'Priv. Finanzb. 3. Gründ'!E13 -> 0 | F13: =+'Privater Finanzbedarf'!F13+'Priv. Finanzb. 2. Gründ.'!F13+'Priv. Finanzb. 3. Gründ'!F13 -> 0
A14: vgl. Einzelaufstellungen des Privaten Finanzbedarfs | C14: =+'Privater Finanzbedarf'!C14+'Priv. Finanzb. 2. Gründ.'!C14+'Priv. Finanzb. 3. Gründ'!C14 -> 0 | D14: =+'Privater Finanzbedarf'!D14+'Priv. Finanzb. 2. Gründ.'!D14+'Priv. Finanzb. 3. Gründ'!D14 -> 0 | E14: =+'Privater Finanzbedarf'!E14+'Priv. Finanzb. 2. Gründ.'!E14+'Priv. Finanzb. 3. Gründ'!E14 -> 0 | F14: =+'Privater Finanzbedarf'!F14+'Priv. Finanzb. 2. Gründ.'!F14+'Priv. Finanzb. 3. Gründ'!F14 -> 0
A15: vgl. Einzelaufstellungen des Privaten Finanzbedarfs | C15: =+'Privater Finanzbedarf'!C15+'Priv. Finanzb. 2. Gründ.'!C15+'Priv. Finanzb. 3. Gründ'!C15 -> 0 | D15: =+'Privater Finanzbedarf'!D15+'Priv. Finanzb. 2. Gründ.'!D15+'Priv. Finanzb. 3. Gründ'!D15 -> 0 | E15: =+'Privater Finanzbedarf'!E15+'Priv. Finanzb. 2. Gründ.'!E15+'Priv. Finanzb. 3. Gründ'!E15 -> 0 | F15: =+'Privater Finanzbedarf'!F15+'Priv. Finanzb. 2. Gründ.'!F15+'Priv. Finanzb. 3. Gründ'!F15 -> 0
A16: Summe der privaten Einnahmen | C16: =SUM(C4:C15) -> 0 | D16: =SUM(D4:D15) -> 0 | E16: =SUM(E4:E15) -> 0 | F16: =SUM(F4:F15) -> 0
A17: Private Ausgaben
A18: Private Miete (einschließlich Nebenkosten) | C18: =+'Privater Finanzbedarf'!C18+'Priv. Finanzb. 2. Gründ.'!C18+'Priv. Finanzb. 3. Gründ'!C18 -> 0 | D18: =+'Privater Finanzbedarf'!D18+'Priv. Finanzb. 2. Gründ.'!D18+'Priv. Finanzb. 3. Gründ'!D18 -> 0 | E18: =+'Privater Finanzbedarf'!E18+'Priv. Finanzb. 2. Gründ.'!E18+'Priv. Finanzb. 3. Gründ'!E18 -> 0 | F18: =+'Privater Finanzbedarf'!F18+'Priv. Finanzb. 2. Gründ.'!F18+'Priv. Finanzb. 3. Gründ'!F18 -> 0
A19: Krankenversicherung | C19: =+'Privater Finanzbedarf'!C19+'Priv. Finanzb. 2. Gründ.'!C19+'Priv. Finanzb. 3. Gründ'!C19 -> 0 | D19: =+'Privater Finanzbedarf'!D19+'Priv. Finanzb. 2. Gründ.'!D19+'Priv. Finanzb. 3. Gründ'!D19 -> 0 | E19: =+'Privater Finanzbedarf'!E19+'Priv. Finanzb. 2. Gründ.'!E19+'Priv. Finanzb. 3. Gründ'!E19 -> 0 | F19: =+'Privater Finanzbedarf'!F19+'Priv. Finanzb. 2. Gründ.'!F19+'Priv. Finanzb. 3. Gründ'!F19 -> 0
A20: Rentenversicherung/Altersvorsorge | C20: =+'Privater Finanzbedarf'!C20+'Priv. Finanzb. 2. Gründ.'!C20+'Priv. Finanzb. 3. Gründ'!C20 -> 0 | D20: =+'Privater Finanzbedarf'!D20+'Priv. Finanzb. 2. Gründ.'!D20+'Priv. Finanzb. 3. Gründ'!D20 -> 0 | E20: =+'Privater Finanzbedarf'!E20+'Priv. Finanzb. 2. Gründ.'!E20+'Priv. Finanzb. 3. Gründ'!E20 -> 0 | F20: =+'Privater Finanzbedarf'!F20+'Priv. Finanzb. 2. Gründ.'!F20+'Priv. Finanzb. 3. Gründ'!F20 -> 0
A21: Sonstige Versicherungen | C21: =+'Privater Finanzbedarf'!C21+'Priv. Finanzb. 2. Gründ.'!C21+'Priv. Finanzb. 3. Gründ'!C21 -> 0 | D21: =+'Privater Finanzbedarf'!D21+'Priv. Finanzb. 2. Gründ.'!D21+'Priv. Finanzb. 3. Gründ'!D21 -> 0 | E21: =+'Privater Finanzbedarf'!E21+'Priv. Finanzb. 2. Gründ.'!E21+'Priv. Finanzb. 3. Gründ'!E21 -> 0 | F21: =+'Privater Finanzbedarf'!F21+'Priv. Finanzb. 2. Gründ.'!F21+'Priv. Finanzb. 3. Gründ'!F21 -> 0
A22: Zinsen und Tilgung privater Darlehen | C22: =+'Privater Finanzbedarf'!C22+'Priv. Finanzb. 2. Gründ.'!C22+'Priv. Finanzb. 3. Gründ'!C22 -> 0 | D22: =+'Privater Finanzbedarf'!D22+'Priv. Finanzb. 2. Gründ.'!D22+'Priv. Finanzb. 3. Gründ'!D22 -> 0 | E22: =+'Privater Finanzbedarf'!E22+'Priv. Finanzb. 2. Gründ.'!E22+'Priv. Finanzb. 3. Gründ'!E22 -> 0 | F22: =+'Privater Finanzbedarf'!F22+'Priv. Finanzb. 2. Gründ.'!F22+'Priv. Finanzb. 3. Gründ'!F22 -> 0
A23: Rücklagen für Einkommensteuer | C23: =+'Privater Finanzbedarf'!C23+'Priv. Finanzb. 2. Gründ.'!C23+'Priv. Finanzb. 3. Gründ'!C23 -> 0 | D23: =+'Privater Finanzbedarf'!D23+'Priv. Finanzb. 2. Gründ.'!D23+'Priv. Finanzb. 3. Gründ'!D23 -> 0 | E23: =+'Privater Finanzbedarf'!E23+'Priv. Finanzb. 2. Gründ.'!E23+'Priv. Finanzb. 3. Gründ'!E23 -> 0 | F23: =+'Privater Finanzbedarf'!F23+'Priv. Finanzb. 2. Gründ.'!F23+'Priv. Finanzb. 3. Gründ'!F23 -> 0
A24: Rücklagen für Neuanschaffungen | C24: =+'Privater Finanzbedarf'!C24+'Priv. Finanzb. 2. Gründ.'!C24+'Priv. Finanzb. 3. Gründ'!C24 -> 0 | D24: =+'Privater Finanzbedarf'!D24+'Priv. Finanzb. 2. Gründ.'!D24+'Priv. Finanzb. 3. Gründ'!D24 -> 0 | E24: =+'Privater Finanzbedarf'!E24+'Priv. Finanzb. 2. Gründ.'!E24+'Priv. Finanzb. 3. Gründ'!E24 -> 0 | F24: =+'Privater Finanzbedarf'!F24+'Priv. Finanzb. 2. Gründ.'!F24+'Priv. Finanzb. 3. Gründ'!F24 -> 0
A25: Unterhaltsverpflichtung | C25: =+'Privater Finanzbedarf'!C25+'Priv. Finanzb. 2. Gründ.'!C25+'Priv. Finanzb. 3. Gründ'!C25 -> 0 | D25: =+'Privater Finanzbedarf'!D25+'Priv. Finanzb. 2. Gründ.'!D25+'Priv. Finanzb. 3. Gründ'!D25 -> 0 | E25: =+'Privater Finanzbedarf'!E25+'Priv. Finanzb. 2. Gründ.'!E25+'Priv. Finanzb. 3. Gründ'!E25 -> 0 | F25: =+'Privater Finanzbedarf'!F25+'Priv. Finanzb. 2. Gründ.'!F25+'Priv. Finanzb. 3. Gründ'!F25 -> 0
A26: Lebensunterhalt 1) | C26: =+'Privater Finanzbedarf'!C26+'Priv. Finanzb. 2. Gründ.'!C26+'Priv. Finanzb. 3. Gründ'!C26 -> 0 | D26: =+'Privater Finanzbedarf'!D26+'Priv. Finanzb. 2. Gründ.'!D26+'Priv. Finanzb. 3. Gründ'!D26 -> 0 | E26: =+'Privater Finanzbedarf'!E26+'Priv. Finanzb. 2. Gründ.'!E26+'Priv. Finanzb. 3. Gründ'!E26 -> 0 | F26: =+'Privater Finanzbedarf'!F26+'Priv. Finanzb. 2. Gründ.'!F26+'Priv. Finanzb. 3. Gründ'!F26 -> 0
A27: Summe der privaten Ausgaben | C27: =SUM(C18:C26) -> 0 | D27: =SUM(D18:D26) -> 0 | E27: =SUM(E18:E26) -> 0 | F27: =SUM(F18:F26) -> 0
A29: Privater Finanzbedarf = erforderlicher Unternehmerlohn | C29: =-C16+C27 -> 0 | D29: =-D16+D27 -> 0 | E29: =-E16+E27 -> 0 | F29: =-F16+F27 -> 0
A31: Hier sind die Summen der Werte von bis zu drei Gründungspersonen addiert.
A32: Details sind den einzelnen Tabellen über den Privaten Finanzbedarf zu entnehmen.

Sheet Übersicht Rentabilitätsvorschau
A1: Mit Klicken auf "+"-Symbole können Sie später Eingabefelder für die Ist-Zahlen öffnen. So ist der Vergleich von Plan- zu Ist-Zahlen möglich. Heben Sie dazu den Passwortschutz unter "Überprüfen/Blattschutz aufheben" auf (kein Passwort nötig). | D1: =+gj -> 2026 | I1: =+gj+1 -> 2027 | O1: =+gj+2 -> 2028 | U1: =+gj+3 -> 2029
D2: Plan | F2: Ist | I2: Plan | L2: Ist | O2: Plan | R2: Ist | U2: Plan | X2: Ist
D3: EUR | E3: Anteil an Gesamt-leistung in % | F3: EUR | G3: Differenz in EUR | H3: Differenz in % | I3: =+D3 -> EUR | J3: =+E3 -> Anteil an Gesamt-leistung in % | K3: Veränderung gegenüber Vorjahr in % | L3: EUR | M3: Differenz in EUR | N3: Differenz in % | O3: =+D3 -> EUR | P3: =+E3 -> Anteil an Gesamt-leistung in % | Q3: =+K3 -> Veränderung gegenüber Vorjahr in % | R3: EUR | S3: Differenz in EUR | T3: Differenz in % | U3: =+D3 -> EUR | V3: =+E3 -> Anteil an Gesamt-leistung in % | W3: =+K3 -> Veränderung gegenüber Vorjahr in % | X3: EUR | Y3: Differenz in EUR | Z3: Differenz in %
A4: =+Rentabilitätsvorschau!A2 -> Umsatz Handel/Produktion
B5: =+Rentabilitätsvorschau!B3 -> Umsatz 19% | D5: =+Rentabilitätsvorschau!P3 -> 0 | E5: =(IF(D$9=0,"-",+D5/D$9)) -> 0 | G5: =IF(+F5-D5=0,0,+F5-D5) -> 0 | H5: =IF(+D5=0,"-",+G5/D5) -> - | I5: =+Rentabilitätsvorschau!AC3 -> 0 | J5: =(IF(I$9=0,"",+I5/I$9)) | K5: =IF(D5=0,"",(I5-D5)/D5) | M5: =IF(+L5-I5=0,0,+L5-I5) -> 0 | N5: =IF(+I5=0,"-",+M5/I5) -> - | O5: =+Rentabilitätsvorschau!AP3 -> 0 | P5: =(IF(O$9=0,"",+O5/O$9)) | Q5: =IF(I5=0,"",(O5-I5)/I5) | S5: =IF(+R5-O5=0,0,+R5-O5) -> 0 | T5: =IF(+O5=0,"-",+S5/O5) -> - | U5: =+Rentabilitätsvorschau!BC3 -> 0 | V5: =(IF(U$9=0,"",+U5/U$9)) | W5: =IF(O5=0,"",(U5-O5)/O5) | Y5: =IF(+X5-U5=0,0,+X5-U5) -> 0 | Z5: =IF(+U5=0,"-",+Y5/U5) -> -
B6: =+Rentabilitätsvorschau!B4 -> Umsatz 7% | D6: =+Rentabilitätsvorschau!P4 -> 0 | E6: =(IF(D$9=0,"-",+D6/D$9)) -> 0 | G6: =IF(+F6-D6=0,0,+F6-D6) -> 0 | H6: =IF(+D6=0,"-",+G6/D6) -> - | I6: =+Rentabilitätsvorschau!AC4 -> 0 | J6: =(IF(I$9=0,"",+I6/I$9)) | K6: =IF(D6=0,"",(I6-D6)/D6) | M6: =IF(+L6-I6=0,0,+L6-I6) -> 0 | N6: =IF(+I6=0,"-",+M6/I6) -> - | O6: =+Rentabilitätsvorschau!AP4 -> 0 | P6: =(IF(O$9=0,"",+O6/O$9)) | Q6: =IF(I6=0,"",(O6-I6)/I6) | S6: =IF(+R6-O6=0,0,+R6-O6) -> 0 | T6: =IF(+O6=0,"-",+S6/O6) -> - | U6: =+Rentabilitätsvorschau!BC4 -> 0 | V6: =(IF(U$9=0,"",+U6/U$9)) | W6: =IF(O6=0,"",(U6-O6)/O6) | Y6: =IF(+X6-U6=0,0,+X6-U6) -> 0 | Z6: =IF(+U6=0,"-",+Y6/U6) -> -
A7: =+Rentabilitätsvorschau!A5 -> Umsatz Dienstleistungen 19% | D7: =+Rentabilitätsvorschau!P5 -> 32000 | E7: =(IF(D$9=0,"-",+D7/D$9)) -> 1 | G7: =IF(+F7-D7=0,0,+F7-D7) -> -32000 | H7: =IF(+D7=0,"-",+G7/D7) -> -1 | I7: =+Rentabilitätsvorschau!AC5 -> 0 | J7: =(IF(I$9=0,"",+I7/I$9)) | K7: =IF(D7=0,"",(I7-D7)/D7) -> -1 | M7: =IF(+L7-I7=0,0,+L7-I7) -> 0 | N7: =IF(+I7=0,"-",+M7/I7) -> - | O7: =+Rentabilitätsvorschau!AP5 -> 0 | P7: =(IF(O$9=0,"",+O7/O$9)) | Q7: =IF(I7=0,"",(O7-I7)/I7) | S7: =IF(+R7-O7=0,0,+R7-O7) -> 0 | T7: =IF(+O7=0,"-",+S7/O7) -> - | U7: =+Rentabilitätsvorschau!BC5 -> 0 | V7: =(IF(U$9=0,"",+U7/U$9)) | W7: =IF(O7=0,"",(U7-O7)/O7) | Y7: =IF(+X7-U7=0,0,+X7-U7) -> 0 | Z7: =IF(+U7=0,"-",+Y7/U7) -> -
A8: =+Rentabilitätsvorschau!C6 -> Erlösschmälerungen (Skonto) | D8: =+Rentabilitätsvorschau!P6 -> 0 | E8: =(IF(D$9=0,"-",+D8/D$9)) -> 0 | G8: =IF(+F8-D8=0,0,+F8-D8) -> 0 | H8: =IF(+D8=0,"-",+G8/D8) -> - | I8: =+Rentabilitätsvorschau!AC6 -> 0 | J8: =(IF(I$9=0,"",+I8/I$9)) | K8: =IF(D8=0,"",(I8-D8)/D8) | M8: =IF(+L8-I8=0,0,+L8-I8) -> 0 | N8: =IF(+I8=0,"-",+M8/I8) -> - | O8: =+Rentabilitätsvorschau!AP6 -> 0 | P8: =(IF(O$9=0,"",+O8/O$9)) | Q8: =IF(I8=0,"",(O8-I8)/I8) | S8: =IF(+R8-O8=0,0,+R8-O8) -> 0 | T8: =IF(+O8=0,"-",+S8/O8) -> - | U8: =+Rentabilitätsvorschau!BC6 -> 0 | V8: =(IF(U$9=0,"",+U8/U$9)) | W8: =IF(O8=0,"",(U8-O8)/O8) | Y8: =IF(+X8-U8=0,0,+X8-U8) -> 0 | Z8: =IF(+U8=0,"-",+Y8/U8) -> -
A9: Gesamtleistung | D9: =+D5+D6+D7-D8 -> 32000 | E9: =(IF(D$9=0,"",+D9/D$9)) -> 1 | F9: =+F5+F6+F7-F8 -> 0 | G9: =+G5+G6+G7-G8 -> -32000 | H9: =IF(+D9=0,"-",+G9/D9) -> -1 | I9: =+I5+I6+I7-I8 -> 0 | J9: =(IF(I$9=0,"",+I9/I$9)) | K9: =IF(D9=0,"",(I9-D9)/D9) -> -1 | L9: =+L5+L6+L7-L8 -> 0 | M9: =+M5+M6+M7-M8 -> 0 | N9: =IF(+I9=0,"-",+M9/I9) -> - | O9: =+O5+O6+O7-O8 -> 0 | P9: =(IF(O$9=0,"",+O9/O$9)) | Q9: =IF(I9=0,"",(O9-I9)/I9) | R9: =+R5+R6+R7-R8 -> 0 | S9: =+S5+S6+S7-S8 -> 0 | T9: =IF(+O9=0,"-",+S9/O9) -> - | U9: =+U5+U6+U7-U8 -> 0 | V9: =(IF(U$9=0,"",+U9/U$9)) | W9: =IF(O9=0,"",(U9-O9)/O9) | X9: =+X5+X6+X7-X8 -> 0 | Y9: =+Y5+Y6+Y7-Y8 -> 0 | Z9: =IF(+U9=0,"-",+Y9/U9) -> -
A10: =+Rentabilitätsvorschau!A7 -> sonstige betriebliche Erträge | D10: =+Rentabilitätsvorschau!P7 -> 0 | E10: =(IF(D$9=0,"",+D10/D$9)) -> 0 | G10: =IF(+F10-D10=0,0,+F10-D10) -> 0 | H10: =IF(+D10=0,"-",+G10/D10) -> - | I10: =+Rentabilitätsvorschau!AC7 -> 0 | J10: =(IF(I$9=0,"",+I10/I$9)) | K10: =IF(D10=0,"",(I10-D10)/D10) | M10: =IF(+L10-I10=0,0,+L10-I10) -> 0 | N10: =IF(+I10=0,"-",+M10/I10) -> - | O10: =+Rentabilitätsvorschau!AP7 -> 0 | P10: =(IF(O$9=0,"",+O10/O$9)) | Q10: =IF(I10=0,"",(O10-I10)/I10) | S10: =IF(+R10-O10=0,0,+R10-O10) -> 0 | T10: =IF(+O10=0,"-",+S10/O10) -> - | U10: =+Rentabilitätsvorschau!BC7 -> 0 | V10: =(IF(U$9=0,"",+U10/U$9)) | W10: =IF(O10=0,"",(U10-O10)/O10) | Y10: =IF(+X10-U10=0,0,+X10-U10) -> 0 | Z10: =IF(+U10=0,"-",+Y10/U10) -> -
A11: =+Rentabilitätsvorschau!A8 -> Wareneinkauf/Materialaufwand
B12: =+Rentabilitätsvorschau!C9 -> pauschaler Wareneinsatz | D12: =+Rentabilitätsvorschau!P9 -> 0 | E12: =(IF(D$9=0,"",+D12/D$9)) -> 0 | G12: =IF(+F12-D12=0,0,+F12-D12) -> 0 | H12: =IF(+D12=0,"-",+G12/D12) -> - | I12: =+Rentabilitätsvorschau!AC9 -> 0 | J12: =(IF(I$9=0,"",+I12/I$9)) | K12: =IF(D12=0,"",(I12-D12)/D12) | M12: =IF(+L12-I12=0,0,+L12-I12) -> 0 | N12: =IF(+I12=0,"-",+M12/I12) -> - | O12: =+Rentabilitätsvorschau!AP9 -> 0 | P12: =(IF(O$9=0,"",+O12/O$9)) | Q12: =IF(I12=0,"",(O12-I12)/I12) | S12: =IF(+R12-O12=0,0,+R12-O12) -> 0 | T12: =IF(+O12=0,"-",+S12/O12) -> - | U12: =+Rentabilitätsvorschau!BC9 -> 0 | V12: =(IF(U$9=0,"",+U12/U$9)) | W12: =IF(O12=0,"",(U12-O12)/O12) | Y12: =IF(+X12-U12=0,0,+X12-U12) -> 0 | Z12: =IF(+U12=0,"-",+Y12/U12) -> -
B13: =+Rentabilitätsvorschau!B10 -> Fremdleistungen | D13: =+Rentabilitätsvorschau!P10 -> 0 | E13: =(IF(D$9=0,"",+D13/D$9)) -> 0 | G13: =IF(+F13-D13=0,0,+F13-D13) -> 0 | H13: =IF(+D13=0,"-",+G13/D13) -> - | I13: =+Rentabilitätsvorschau!AC10 -> 0 | J13: =(IF(I$9=0,"",+I13/I$9)) | K13: =IF(D13=0,"",(I13-D13)/D13) | M13: =IF(+L13-I13=0,0,+L13-I13) -> 0 | N13: =IF(+I13=0,"-",+M13/I13) -> - | O13: =+Rentabilitätsvorschau!AP10 -> 0 | P13: =(IF(O$9=0,"",+O13/O$9)) | Q13: =IF(I13=0,"",(O13-I13)/I13) | S13: =IF(+R13-O13=0,0,+R13-O13) -> 0 | T13: =IF(+O13=0,"-",+S13/O13) -> - | U13: =+Rentabilitätsvorschau!BC10 -> 0 | V13: =(IF(U$9=0,"",+U13/U$9)) | W13: =IF(O13=0,"",(U13-O13)/O13) | Y13: =IF(+X13-U13=0,0,+X13-U13) -> 0 | Z13: =IF(+U13=0,"-",+Y13/U13) -> -
B14: =+Rentabilitätsvorschau!B11 -> Wareneinkauf Saisongeschäft | D14: =+Rentabilitätsvorschau!P11 -> 0 | E14: =(IF(D$9=0,"",+D14/D$9)) -> 0 | G14: =IF(+F14-D14=0,0,+F14-D14) -> 0 | H14: =IF(+D14=0,"-",+G14/D14) -> - | I14: =+Rentabilitätsvorschau!AC11 -> 0 | J14: =(IF(I$9=0,"",+I14/I$9)) | K14: =IF(D14=0,"",(I14-D14)/D14) | M14: =IF(+L14-I14=0,0,+L14-I14) -> 0 | N14: =IF(+I14=0,"-",+M14/I14) -> - | O14: =+Rentabilitätsvorschau!AP11 -> 0 | P14: =(IF(O$9=0,"",+O14/O$9)) | Q14: =IF(I14=0,"",(O14-I14)/I14) | S14: =IF(+R14-O14=0,0,+R14-O14) -> 0 | T14: =IF(+O14=0,"-",+S14/O14) -> - | U14: =+Rentabilitätsvorschau!BC11 -> 0 | V14: =(IF(U$9=0,"",+U14/U$9)) | W14: =IF(O14=0,"",(U14-O14)/O14) | Y14: =IF(+X14-U14=0,0,+X14-U14) -> 0 | Z14: =IF(+U14=0,"-",+Y14/U14) -> -
