Workbook

Sheet Cover
A1: AMAVIO | Finanzmodell 36 Monate v1.6
A2: P0-Remediation: Cash Collection, VAT timing, unified capital logic, corrected scenarios and checks
B3: Version 1.7 · AMAVIO Living · commercial pricing aligned 28 July 2026
A4: Status | B4: P0 CONDITIONAL – no external market clearance
A5: Model purpose | B5: Plan P&L and cash collections for a capital-light service business
A6: Capital convention | B6: €25,000 total planned start funding: €500 share capital + €24,500 separately documented contribution/loan
A7: Cash convention | B7: Cash receipts follow planned package instalments; P&L revenue is separate. VAT is a timing reserve, not profit.
A8: Limit | B8: No object operation, tenant deposits, customer funds, receivables financing or input-VAT recovery modelled.
A9: Gate | B9: Replace planned funding by documented received funding before live cash decision.
A10: Source | B10: P0 pricing: Blueprint 40/40/20; Launch 30/30/30/10; Office setup 50/50; retainer monthly in advance.
A11: Owner | B11: Zaki Amawi / finance review required before use for commitments
A12: Version date | B12: 28 July 2026

Sheet Assumptions
A1: AMAVIO | Inputs – edit blue cells only
A3: Parameter | B3: Year 1 | C3: Year 2 | D3: Year 3 | E3: Unit | F3: Note
A4: Planned total start funding | B4: 25000 | C4: 0 | D4: 0 | E4: EUR | F4: €500 share capital + €24,500 documented contribution/loan; do not double count
A5: Documented received start funding | B5: 0 | C5: 0 | D5: 0 | E5: EUR | F5: Set to actual received amount before live use
A6: VAT rate | B6: 0.19 | C6: 0.19 | D6: 0.19 | E6: % | F6: VAT timing only; input VAT excluded
A7: Variable external cost rate | B7: 0.1 | C7: 0.12 | D7: 0.15 | E7: % revenue | F7: Non-recharged service external costs
A8: Monthly overhead | B8: 1600 | C8: 2200 | D8: 3200 | E8: EUR/month | F8: Software, insurance, marketing, advisers
A9: Founder gross compensation | B9: 2500 | C9: 3500 | D9: 5000 | E9: EUR/month | F9: Only after GF agreement + resolution + cash gate. HINWEIS: Gründungszuschuss BA prüfen (ggf. +€1.200-2.000/Monat persönlich für 6 Monate).
A10: Project coordination staff | B10: 0 | C10: 4000 | D10: 9000 | E10: EUR/month | F10: Only after personnel gate
A11: Depreciation | B11: 2000 | C11: 3000 | D11: 5000 | E11: EUR/year | F11: P&L only
A12: Capex | B12: 2000 | C12: 8000 | D12: 15000 | E12: EUR/year | F12: Cash use
A13: Minimum liquidity | B13: 10000 | C13: 15000 | D13: 25000 | E13: EUR | F13: Management threshold
A14: Downside revenue factor | B14: 0.45 | C14: 0.45 | D14: 0.45 | E14: % of Base | F14: Corrected to 45%
A15: Growth revenue factor | B15: 1.25 | C15: 1.25 | D15: 1.25 | E15: % of Base | F15: Planning sensitivity
... A17: Standard day rate | B17: 1100 | C17: 1100 | D17: 1100 | E17: EUR/day | F17: Internal calibration; packages are client-facing
A18: P0 finance status | B18: CONDITIONAL | C18: CONDITIONAL | D18: CONDITIONAL | E18: status | F18: Requires documented funding + legal/data/brand gates before commitments. Gate §34c GewO: Maklertätigkeit vor erstem Launch rechtlich klären.

Sheet Contract_Cash
A1: AMAVIO | Contract value and planned cash collection schedule
A3: Contract / package | B3: Year | C3: Net contract value | D3: Payment logic | E3: M1 | F3: M2 | G3: M3 | H3: M4 | I3: M5 | J3: M6 | K3: M7 | L3: M8 | M3: M9 | N3: M10 | O3: M11 | P3: M12 | Q3: M13 | R3: M14 | S3: M15 | T3: M16 | U3: M17 | V3: M18 | W3: M19 | X3: M20 | Y3: M21 | Z3: M22 | AA3: M23 | AB3: M24 | AC3: M25 | AD3: M26 | AE3: M27 | AF3: M28 | AG3: M29 | AH3: M30 | AI3: M31 | AJ3: M32 | AK3: M33 | AL3: M34 | AM3: M35 | AN3: M36
A4: Blueprint 01 | B4: 1 | C4: 12500 | D4: 40 / 40 / 20 | E4: 0 | F4: 0 | G4: =12500*0.4 | H4: =12500*0.4 | I4: =12500*0.2 | J4: 0 | K4: 0 | L4: 0 | M4: 0 | N4: 0 | O4: 0 | P4: 0 | Q4: 0 | R4: 0 | S4: 0 | T4: 0 | U4: 0 | V4: 0 | W4: 0 | X4: 0 | Y4: 0 | Z4: 0 | AA4: 0 | AB4: 0 | AC4: 0 | AD4: 0 | AE4: 0 | AF4: 0 | AG4: 0 | AH4: 0 | AI4: 0 | AJ4: 0 | AK4: 0 | AL4: 0 | AM4: 0 | AN4: 0
A5: Blueprint 02 | B5: 1 | C5: 12500 | D5: 40 / 40 / 20 | E5: 0 | F5: 0 | G5: 0 | H5: 0 | I5: 0 | J5: =12500*0.4 | K5: =12500*0.4 | L5: =12500*0.2 | M5: 0 | N5: 0 | O5: 0 | P5: 0 | Q5: 0 | R5: 0 | S5: 0 | T5: 0 | U5: 0 | V5: 0 | W5: 0 | X5: 0 | Y5: 0 | Z5: 0 | AA5: 0 | AB5: 0 | AC5: 0 | AD5: 0 | AE5: 0 | AF5: 0 | AG5: 0 | AH5: 0 | AI5: 0 | AJ5: 0 | AK5: 0 | AL5: 0 | AM5: 0 | AN5: 0
A6: Launch 01 | B6: 1 | C6: 29500 | D6: 30 / 30 / 30 / 10 | E6: 0 | F6: 0 | G6: 0 | H6: 0 | I6: 0 | J6: 0 | K6: 8850 | L6: 8850 | M6: 8850 | N6: 2950 | O6: 0 | P6: 0 | Q6: 0 | R6: 0 | S6: 0 | T6: 0 | U6: 0 | V6: 0 | W6: 0 | X6: 0 | Y6: 0 | Z6: 0 | AA6: 0 | AB6: 0 | AC6: 0 | AD6: 0 | AE6: 0 | AF6: 0 | AG6: 0 | AH6: 0 | AI6: 0 | AJ6: 0 | AK6: 0 | AL6: 0 | AM6: 0 | AN6: 0
A7: Office Setup 01 | B7: 1 | C7: 15000 | D7: 50 / 50 | E7: 0 | F7: 0 | G7: 0 | H7: 0 | I7: 0 | J7: 0 | K7: 0 | L7: 0 | M7: 0 | N7: =15000*0.5 | O7: =15000*0.5 | P7: 0 | Q7: 0 | R7: 0 | S7: 0 | T7: 0 | U7: 0 | V7: 0 | W7: 0 | X7: 0 | Y7: 0 | Z7: 0 | AA7: 0 | AB7: 0 | AC7: 0 | AD7: 0 | AE7: 0 | AF7: 0 | AG7: 0 | AH7: 0 | AI7: 0 | AJ7: 0 | AK7: 0 | AL7: 0 | AM7: 0 | AN7: 0
A8: Retainer 01 | B8: 1 | C8: 13500 | D8: monthly in advance | E8: 0 | F8: 0 | G8: 0 | H8: 0 | I8: 0 | J8: 0 | K8: 0 | L8: 0 | M8: 0 | N8: =13500*0.3333333333333333 | O8: =13500*0.3333333333333333 | P8: =13500*0.3333333333333333 | Q8: 0 | R8: 0 | S8: 0 | T8: 0 | U8: 0 | V8: 0 | W8: 0 | X8: 0 | Y8: 0 | Z8: 0 | AA8: 0 | AB8: 0 | AC8: 0 | AD8: 0 | AE8: 0 | AF8: 0 | AG8: 0 | AH8: 0 | AI8: 0 | AJ8: 0 | AK8: 0 | AL8: 0 | AM8: 0 | AN8: 0
A9: Add-ons 01 | B9: 1 | C9: 10500 | D9: approved scope | E9: 0 | F9: 0 | G9: 0 | H9: 0 | I9: 0 | J9: 0 | K9: 0 | L9: 0 | M9: 0 | N9: =10500*0.3333333333333333 | O9: =10500*0.3333333333333333 | P9: =10500*0.3333333333333333 | Q9: 0 | R9: 0 | S9: 0 | T9: 0 | U9: 0 | V9: 0 | W9: 0 | X9: 0 | Y9: 0 | Z9: 0 | AA9: 0 | AB9: 0 | AC9: 0 | AD9: 0 | AE9: 0 | AF9: 0 | AG9: 0 | AH9: 0 | AI9: 0 | AJ9: 0 | AK9: 0 | AL9: 0 | AM9: 0 | AN9: 0
A10: Blueprint 03 | B10: 2 | C10: 21000 | D10: 40 / 40 / 20 | E10: 0 | F10: 0 | G10: 0 | H10: 0 | I10: 0 | J10: 0 | K10: 0 | L10: 0 | M10: 0 | N10: 0 | O10: 0 | P10: 0 | Q10: =21000*0.4 | R10: =21000*0.4 | S10: =21000*0.2 | T10: 0 | U10: 0 | V10: 0 | W10: 0 | X10: 0 | Y10: 0 | Z10: 0 | AA10: 0 | AB10: 0 | AC10: 0 | AD10: 0 | AE10: 0 | AF10: 0 | AG10: 0 | AH10: 0 | AI10: 0 | AJ10: 0 | AK10: 0 | AL10: 0 | AM10: 0 | AN10: 0
A11: Blueprint 04 | B11: 2 | C11: 21000 | D11: 40 / 40 / 20 | E11: 0 | F11: 0 | G11: 0 | H11: 0 | I11: 0 | J11: 0 | K11: 0 | L11: 0 | M11: 0 | N11: 0 | O11: 0 | P11: 0 | Q11: 0 | R11: 0 | S11: 0 | T11: =21000*0.4 | U11: =21000*0.4 | V11: =21000*0.2 | W11: 0 | X11: 0 | Y11: 0 | Z11: 0 | AA11: 0 | AB11: 0 | AC11: 0 | AD11: 0 | AE11: 0 | AF11: 0 | AG11: 0 | AH11: 0 | AI11: 0 | AJ11: 0 | AK11: 0 | AL11: 0 | AM11: 0 | AN11: 0
A12: Blueprint 05 | B12: 2 | C12: 21000 | D12: 40 / 40 / 20 | E12: 0 | F12: 0 | G12: 0 | H12: 0 | I12: 0 | J12: 0 | K12: 0 | L12: 0 | M12: 0 | N12: 0 | O12: 0 | P12: 0 | Q12: 0 | R12: 0 | S12: 0 | T12: 0 | U12: 0 | V12: 0 | W12: =21000*0.4 | X12: =21000*0.4 | Y12: =21000*0.2 | Z12: 0 | AA12: 0 | AB12: 0 | AC12: 0 | AD12: 0 | AE12: 0 | AF12: 0 | AG12: 0 | AH12: 0 | AI12: 0 | AJ12: 0 | AK12: 0 | AL12: 0 | AM12: 0 | AN12: 0
A13: Launch 02 | B13: 2 | C13: 50000 | D13: 30 / 30 / 30 / 10 | E13: 0 | F13: 0 | G13: 0 | H13: 0 | I13: 0 | J13: 0 | K13: 0 | L13: 0 | M13: 0 | N13: 0 | O13: 0 | P13: 0 | Q13: 0 | R13: =50000*0.3 | S13: =50000*0.3 | T13: =50000*0.3 | U13: =50000*0.1 | V13: 0 | W13: 0 | X13: 0 | Y13: 0 | Z13: 0 | AA13: 0 | AB13: 0 | AC13: 0 | AD13: 0 | AE13: 0 | AF13: 0 | AG13: 0 | AH13: 0 | AI13: 0 | AJ13: 0 | AK13: 0 | AL13: 0 | AM13: 0 | AN13: 0
A14: Launch 03 | B14: 2 | C14: 50000 | D14: 30 / 30 / 30 / 10 | E14: 0 | F14: 0 | G14: 0 | H14: 0 | I14: 0 | J14: 0 | K14: 0 | L14: 0 | M14: 0 | N14: 0 | O14: 0 | P14: 0 | Q14: 0 | R14: 0 | S14: 0 | T14: 0 | U14: 0 | V14: =50000*0.3 | W14: =50000*0.3 | X14: =50000*0.3 | Y14: =50000*0.1 | Z14: 0 | AA14: 0 | AB14: 0 | AC14: 0 | AD14: 0 | AE14: 0 | AF14: 0 | AG14: 0 | AH14: 0 | AI14: 0 | AJ14: 0 | AK14: 0 | AL14: 0 | AM14: 0 | AN14: 0
A15: Office Setup 02 | B15: 2 | C15: 25000 | D15: 50 / 50 | E15: 0 | F15: 0 | G15: 0 | H15: 0 | I15: 0 | J15: 0 | K15: 0 | L15: 0 | M15: 0 | N15: 0 | O15: 0 | P15: 0 | Q15: 0 | R15: 0 | S15: 0 | T15: 0 | U15: 0 | V15: =25000*0.5 | W15: =25000*0.5 | X15: 0 | Y15: 0 | Z15: 0 | AA15: 0 | AB15: 0 | AC15: 0 | AD15: 0 | AE15: 0 | AF15: 0 | AG15: 0 | AH15: 0 | AI15: 0 | AJ15: 0 | AK15: 0 | AL15: 0 | AM15: 0 | AN15: 0
A16: Retainer 02 | B16: 2 | C16: 72000 | D16: monthly in advance | E16: 0 | F16: 0 | G16: 0 | H16: 0 | I16: 0 | J16: 0 | K16: 0 | L16: 0 | M16: 0 | N16: 0 | O16: 0 | P16: 0 | Q16: =72000*0.08333333333333333 | R16: =72000*0.08333333333333333 | S16: =72000*0.08333333333333333 | T16: =72000*0.08333333333333333 | U16: =72000*0.08333333333333333 | V16: =72000*0.08333333333333333 | W16: =72000*0.08333333333333333 | X16: =72000*0.08333333333333333 | ... AB16: =72000*0.08333333333333333 | AC16: 0 | AD16: 0 | AE16: 0 | AF16: 0 | AG16: 0 | AH16: 0 | AI16: 0 | AJ16: 0 | AK16: 0 | AL16: 0 | AM16: 0 | AN16: 0
A17: Add-ons 02 | B17: 2 | C17: 9000 | D17: approved scope | E17: 0 | F17: 0 | G17: 0 | H17: 0 | I17: 0 | J17: 0 | K17: 0 | L17: 0 | M17: 0 | N17: 0 | O17: 0 | P17: 0 | Q17: 0 | R17: 0 | S17: 0 | T17: 0 | U17: =9000*0.3333333333333333 | V17: 0 | W17: 0 | X17: =9000*0.3333333333333333 | Y17: 0 | Z17: 0 | AA17: =9000*0.3333333333333333 | AB17: 0 | AC17: 0 | AD17: 0 | AE17: 0 | AF17: 0 | AG17: 0 | AH17: 0 | AI17: 0 | AJ17: 0 | AK17: 0 | AL17: 0 | AM17: 0 | AN17: 0
A18: Blueprint 06 | B18: 3 | C18: 21000 | D18: 40 / 40 / 20 | E18: 0 | F18: 0 | G18: 0 | H18: 0 | I18: 0 | J18: 0 | K18: 0 | L18: 0 | M18: 0 | N18: 0 | O18: 0 | P18: 0 | Q18: 0 | R18: 0 | S18: 0 | T18: 0 | U18: 0 | V18: 0 | W18: 0 | X18: 0 | Y18: 0 | Z18: 0 | AA18: 0 | AB18: 0 | AC18: =21000*0.4 | AD18: =21000*0.4 | AE18: =21000*0.2 | AF18: 0 | AG18: 0 | AH18: 0 | AI18: 0 | AJ18: 0 | AK18: 0 | AL18: 0 | AM18: 0 | AN18: 0
A19: Blueprint 07 | B19: 3 | C19: 21000 | D19: 40 / 40 / 20 | E19: 0 | F19: 0 | G19: 0 | H19: 0 | I19: 0 | J19: 0 | K19: 0 | L19: 0 | M19: 0 | N19: 0 | O19: 0 | P19: 0 | Q19: 0 | R19: 0 | S19: 0 | T19: 0 | U19: 0 | V19: 0 | W19: 0 | X19: 0 | Y19: 0 | Z19: 0 | AA19: 0 | AB19: 0 | AC19: 0 | AD19: 0 | AE19: =21000*0.4 | AF19: =21000*0.4 | AG19: =21000*0.2 | AH19: 0 | AI19: 0 | AJ19: 0 | AK19: 0 | AL19: 0 | AM19: 0 | AN19: 0
A20: Blueprint 08 | B20: 3 | C20: 21000 | D20: 40 / 40 / 20 | E20: 0 | F20: 0 | G20: 0 | H20: 0 | I20: 0 | J20: 0 | K20: 0 | L20: 0 | M20: 0 | N20: 0 | O20: 0 | P20: 0 | Q20: 0 | R20: 0 | S20: 0 | T20: 0 | U20: 0 | V20: 0 | W20: 0 | X20: 0 | Y20: 0 | Z20: 0 | AA20: 0 | AB20: 0 | AC20: 0 | AD20: 0 | AE20: 0 | AF20: 0 | AG20: =21000*0.4 | AH20: =21000*0.4 | AI20: =21000*0.2 | AJ20: 0 | AK20: 0 | AL20: 0 | AM20: 0 | AN20: 0
A21: Blueprint 09 | B21: 3 | C21: 21000 | D21: 40 / 40 / 20 | E21: 0 | F21: 0 | G21: 0 | H21: 0 | I21: 0 | J21: 0 | K21: 0 | L21: 0 | M21: 0 | N21: 0 | O21: 0 | P21: 0 | Q21: 0 | R21: 0 | S21: 0 | T21: 0 | U21: 0 | V21: 0 | W21: 0 | X21: 0 | Y21: 0 | Z21: 0 | AA21: 0 | AB21: 0 | AC21: 0 | AD21: 0 | AE21: 0 | AF21: 0 | AG21: 0 | AH21: 0 | AI21: =21000*0.4 | AJ21: =21000*0.4 | AK21: =21000*0.2 | AL21: 0 | AM21: 0 | AN21: 0
A22: Launch 04 | B22: 3 | C22: 55000 | D22: 30 / 30 / 30 / 10 | E22: 0 | F22: 0 | G22: 0 | H22: 0 | I22: 0 | J22: 0 | K22: 0 | L22: 0 | M22: 0 | N22: 0 | O22: 0 | P22: 0 | Q22: 0 | R22: 0 | S22: 0 | T22: 0 | U22: 0 | V22: 0 | W22: 0 | X22: 0 | Y22: 0 | Z22: 0 | AA22: 0 | AB22: 0 | AC22: =55000*0.3 | AD22: =55000*0.3 | AE22: =55000*0.3 | AF22: =55000*0.1 | AG22: 0 | AH22: 0 | AI22: 0 | AJ22: 0 | AK22: 0 | AL22: 0 | AM22: 0 | AN22: 0
A23: Launch 05 | B23: 3 | C23: 55000 | D23: 30 / 30 / 30 / 10 | E23: 0 | F23: 0 | G23: 0 | H23: 0 | I23: 0 | J23: 0 | K23: 0 | L23: 0 | M23: 0 | N23: 0 | O23: 0 | P23: 0 | Q23: 0 | R23: 0 | S23: 0 | T23: 0 | U23: 0 | V23: 0 | W23: 0 | X23: 0 | Y23: 0 | Z23: 0 | AA23: 0 | AB23: 0 | AC23: 0 | AD23: 0 | AE23: 0 | AF23: 0 | AG23: 0 | AH23: =55000*0.3 | AI23: =55000*0.3 | AJ23: =55000*0.3 | AK23: =55000*0.1 | AL23: 0 | AM23: 0 | AN23: 0
A24: Office Setup 03 | B24: 3 | C24: 28000 | D24: 50 / 50 | E24: 0 | F24: 0 | G24: 0 | H24: 0 | I24: 0 | J24: 0 | K24: 0 | L24: 0 | M24: 0 | N24: 0 | O24: 0 | P24: 0 | Q24: 0 | R24: 0 | S24: 0 | T24: 0 | U24: 0 | V24: 0 | W24: 0 | X24: 0 | Y24: 0 | Z24: 0 | AA24: 0 | AB24: 0 | AC24: 0 | AD24: 0 | AE24: =28000*0.5 | AF24: =28000*0.5 | AG24: 0 | AH24: 0 | AI24: 0 | AJ24: 0 | AK24: 0 | AL24: 0 | AM24: 0 | AN24: 0
A25: Office Setup 04 | B25: 3 | C25: 28000 | D25: 50 / 50 | E25: 0 | F25: 0 | G25: 0 | H25: 0 | I25: 0 | J25: 0 | K25: 0 | L25: 0 | M25: 0 | N25: 0 | O25: 0 | P25: 0 | Q25: 0 | R25: 0 | S25: 0 | T25: 0 | U25: 0 | V25: 0 | W25: 0 | X25: 0 | Y25: 0 | Z25: 0 | AA25: 0 | AB25: 0 | AC25: 0 | AD25: 0 | AE25: 0 | AF25: 0 | AG25: 0 | AH25: 0 | AI25: 0 | AJ25: =28000*0.5 | AK25: =28000*0.5 | AL25: 0 | AM25: 0 | AN25: 0
A26: Retainer 03 | B26: 3 | C26: 144000 | D26: monthly in advance | E26: 0 | F26: 0 | G26: 0 | H26: 0 | I26: 0 | J26: 0 | K26: 0 | L26: 0 | M26: 0 | N26: 0 | O26: 0 | P26: 0 | Q26: 0 | R26: 0 | S26: 0 | T26: 0 | U26: 0 | V26: 0 | W26: 0 | X26: 0 | Y26: 0 | Z26: 0 | AA26: 0 | AB26: 0 | AC26: =144000*0.08333333333333333 | AD26: =144000*0.08333333333333333 | AE26: =144000*0.08333333333333333 | AF26: =144000*0.08333333333333333 | AG26: =144000*0.08333333333333333 | AH26: =144000*0.08333333333333333 | AI26: =144000*0.08333333333333333 | AJ26: =144000*0.08333333333333333 | ... AN26: =144000*0.08333333333333333
A27: Add-ons 03 | B27: 3 | C27: 48000 | D27: approved scope | E27: 0 | F27: 0 | G27: 0 | H27: 0 | I27: 0 | J27: 0 | K27: 0 | L27: 0 | M27: 0 | N27: 0 | O27: 0 | P27: 0 | Q27: 0 | R27: 0 | S27: 0 | T27: 0 | U27: 0 | V27: 0 | W27: 0 | X27: 0 | Y27: 0 | Z27: 0 | AA27: 0 | AB27: 0 | AC27: =48000*0.08333333333333333 | AD27: =48000*0.08333333333333333 | AE27: =48000*0.08333333333333333 | AF27: =48000*0.08333333333333333 | AG27: =48000*0.08333333333333333 | AH27: =48000*0.08333333333333333 | AI27: =48000*0.08333333333333333 | AJ27: =48000*0.08333333333333333 | ... AN27: =48000*0.08333333333333333
A28: TOTAL NET CASH COLLECTION | C28: =SUM(C4:C27) | E28: =SUM(E4:E27) | F28: =SUM(F4:F27) | G28: =SUM(G4:G27) | H28: =SUM(H4:H27) | I28: =SUM(I4:I27) | J28: =SUM(J4:J27) | K28: =SUM(K4:K27) | L28: =SUM(L4:L27) | ... AN28: =SUM(AN4:AN27)

Sheet Monthly_Cash
A1: AMAVIO | 36-month cash plan – collections, VAT timing and liquidity
A3: Position | B3: M1 | C3: M2 | D3: M3 | E3: M4 | F3: M5 | G3: M6 | H3: M7 | I3: M8 | J3: M9 | K3: M10 | L3: M11 | M3: M12 | N3: M13 | O3: M14 | P3: M15 | Q3: M16 | R3: M17 | S3: M18 | T3: M19 | U3: M20 | V3: M21 | W3: M22 | X3: M23 | Y3: M24 | Z3: M25 | AA3: M26 | AB3: M27 | AC3: M28 | AD3: M29 | AE3: M30 | AF3: M31 | AG3: M32 | AH3: M33 | AI3: M34 | AJ3: M35 | AK3: M36
A4: Net cash collections | B4: ='Contract_Cash'!E28 | C4: ='Contract_Cash'!F28 | D4: ='Contract_Cash'!G28 | E4: ='Contract_Cash'!H28 | F4: ='Contract_Cash'!I28 | G4: ='Contract_Cash'!J28 | H4: ='Contract_Cash'!K28 | I4: ='Contract_Cash'!L28 | ... AK4: ='Contract_Cash'!AN28
A5: VAT collected | B5: =B4*'Assumptions'!B6 | C5: =C4*'Assumptions'!B6 | D5: =D4*'Assumptions'!B6 | E5: =E4*'Assumptions'!B6 | F5: =F4*'Assumptions'!B6 | G5: =G4*'Assumptions'!B6 | H5: =H4*'Assumptions'!B6 | I5: =I4*'Assumptions'!B6 | J5: =J4*'Assumptions'!B6 | K5: =K4*'Assumptions'!B6 | L5: =L4*'Assumptions'!B6 | M5: =M4*'Assumptions'!B6 | N5: =N4*'Assumptions'!C6 | O5: =O4*'Assumptions'!C6 | P5: =P4*'Assumptions'!C6 | Q5: =Q4*'Assumptions'!C6 | R5: =R4*'Assumptions'!C6 | S5: =S4*'Assumptions'!C6 | T5: =T4*'Assumptions'!C6 | U5: =U4*'Assumptions'!C6 | V5: =V4*'Assumptions'!C6 | W5: =W4*'Assumptions'!C6 | X5: =X4*'Assumptions'!C6 | Y5: =Y4*'Assumptions'!C6 | Z5: =Z4*'Assumptions'!D6 | AA5: =AA4*'Assumptions'!D6 | AB5: =AB4*'Assumptions'!D6 | AC5: =AC4*'Assumptions'!D6 | AD5: =AD4*'Assumptions'!D6 | AE5: =AE4*'Assumptions'!D6 | AF5: =AF4*'Assumptions'!D6 | AG5: =AG4*'Assumptions'!D6 | AH5: =AH4*'Assumptions'!D6 | AI5: =AI4*'Assumptions'!D6 | AJ5: =AJ4*'Assumptions'!D6 | AK5: =AK4*'Assumptions'!D6
A6: VAT paid from prior-month reserve | B6: =0 | C6: =B5 | D6: =C5 | E6: =D5 | F6: =E5 | G6: =F5 | H6: =G5 | I6: =H5 | J6: =I5 | ... AK6: =AJ5
A7: Gross cash receipts | B7: =B4+B5-B6 | C7: =C4+C5-C6 | D7: =D4+D5-D6 | E7: =E4+E5-E6 | F7: =F4+F5-F6 | G7: =G4+G5-G6 | H7: =H4+H5-H6 | I7: =I4+I5-I6 | ... AK7: =AK4+AK5-AK6
A8: Variable external cash costs | B8: =B4*'Assumptions'!B7 | C8: =C4*'Assumptions'!B7 | D8: =D4*'Assumptions'!B7 | E8: =E4*'Assumptions'!B7 | F8: =F4*'Assumptions'!B7 | G8: =G4*'Assumptions'!B7 | H8: =H4*'Assumptions'!B7 | I8: =I4*'Assumptions'!B7 | J8: =J4*'Assumptions'!B7 | K8: =K4*'Assumptions'!B7 | L8: =L4*'Assumptions'!B7 | M8: =M4*'Assumptions'!B7 | N8: =N4*'Assumptions'!C7 | O8: =O4*'Assumptions'!C7 | P8: =P4*'Assumptions'!C7 | Q8: =Q4*'Assumptions'!C7 | R8: =R4*'Assumptions'!C7 | S8: =S4*'Assumptions'!C7 | T8: =T4*'Assumptions'!C7 | U8: =U4*'Assumptions'!C7 | V8: =V4*'Assumptions'!C7 | W8: =W4*'Assumptions'!C7 | X8: =X4*'Assumptions'!C7 | Y8: =Y4*'Assumptions'!C7 | Z8: =Z4*'Assumptions'!D7 | AA8: =AA4*'Assumptions'!D7 | AB8: =AB4*'Assumptions'!D7 | AC8: =AC4*'Assumptions'!D7 | AD8: =AD4*'Assumptions'!D7 | AE8: =AE4*'Assumptions'!D7 | AF8: =AF4*'Assumptions'!D7 | AG8: =AG4*'Assumptions'!D7 | AH8: =AH4*'Assumptions'!D7 | AI8: =AI4*'Assumptions'!D7 | AJ8: =AJ4*'Assumptions'!D7 | AK8: =AK4*'Assumptions'!D7
A9: Overhead | B9: ='Assumptions'!B8 | C9: ='Assumptions'!B8 | D9: ='Assumptions'!B8 | E9: ='Assumptions'!B8 | F9: ='Assumptions'!B8 | G9: ='Assumptions'!B8 | H9: ='Assumptions'!B8 | I9: ='Assumptions'!B8 | J9: ='Assumptions'!B8 | K9: ='Assumptions'!B8 | L9: ='Assumptions'!B8 | M9: ='Assumptions'!B8 | N9: ='Assumptions'!C8 | O9: ='Assumptions'!C8 | P9: ='Assumptions'!C8 | Q9: ='Assumptions'!C8 | R9: ='Assumptions'!C8 | S9: ='Assumptions'!C8 | T9: ='Assumptions'!C8 | U9: ='Assumptions'!C8 | V9: ='Assumptions'!C8 | W9: ='Assumptions'!C8 | X9: ='Assumptions'!C8 | Y9: ='Assumptions'!C8 | Z9: ='Assumptions'!D8 | AA9: ='Assumptions'!D8 | AB9: ='Assumptions'!D8 | AC9: ='Assumptions'!D8 | AD9: ='Assumptions'!D8 | AE9: ='Assumptions'!D8 | AF9: ='Assumptions'!D8 | AG9: ='Assumptions'!D8 | AH9: ='Assumptions'!D8 | AI9: ='Assumptions'!D8 | AJ9: ='Assumptions'!D8 | AK9: ='Assumptions'!D8
A10: Founder compensation | B10: ='Assumptions'!B9 | C10: ='Assumptions'!B9 | D10: ='Assumptions'!B9 | E10: ='Assumptions'!B9 | F10: ='Assumptions'!B9 | G10: ='Assumptions'!B9 | H10: ='Assumptions'!B9 | I10: ='Assumptions'!B9 | J10: ='Assumptions'!B9 | K10: ='Assumptions'!B9 | L10: ='Assumptions'!B9 | M10: ='Assumptions'!B9 | N10: ='Assumptions'!C9 | O10: ='Assumptions'!C9 | P10: ='Assumptions'!C9 | Q10: ='Assumptions'!C9 | R10: ='Assumptions'!C9 | S10: ='Assumptions'!C9 | T10: ='Assumptions'!C9 | U10: ='Assumptions'!C9 | V10: ='Assumptions'!C9 | W10: ='Assumptions'!C9 | X10: ='Assumptions'!C9 | Y10: ='Assumptions'!C9 | Z10: ='Assumptions'!D9 | AA10: ='Assumptions'!D9 | AB10: ='Assumptions'!D9 | AC10: ='Assumptions'!D9 | AD10: ='Assumptions'!D9 | AE10: ='Assumptions'!D9 | AF10: ='Assumptions'!D9 | AG10: ='Assumptions'!D9 | AH10: ='Assumptions'!D9 | AI10: ='Assumptions'!D9 | AJ10: ='Assumptions'!D9 | AK10: ='Assumptions'!D9
A11: Project coordination | B11: ='Assumptions'!B10 | C11: ='Assumptions'!B10 | D11: ='Assumptions'!B10 | E11: ='Assumptions'!B10 | F11: ='Assumptions'!B10 | G11: ='Assumptions'!B10 | H11: ='Assumptions'!B10 | I11: ='Assumptions'!B10 | J11: ='Assumptions'!B10 | K11: ='Assumptions'!B10 | L11: ='Assumptions'!B10 | M11: ='Assumptions'!B10 | N11: ='Assumptions'!C10 | O11: ='Assumptions'!C10 | P11: ='Assumptions'!C10 | Q11: ='Assumptions'!C10 | R11: ='Assumptions'!C10 | S11: ='Assumptions'!C10 | T11: ='Assumptions'!C10 | U11: ='Assumptions'!C10 | V11: ='Assumptions'!C10 | W11: ='Assumptions'!C10 | X11: ='Assumptions'!C10 | Y11: ='Assumptions'!C10 | Z11: ='Assumptions'!D10 | AA11: ='Assumptions'!D10 | AB11: ='Assumptions'!D10 | AC11: ='Assumptions'!D10 | AD11: ='Assumptions'!D10 | AE11: ='Assumptions'!D10 | AF11: ='Assumptions'!D10 | AG11: ='Assumptions'!D10 | AH11: ='Assumptions'!D10 | AI11: ='Assumptions'!D10 | AJ11: ='Assumptions'!D10 | AK11: ='Assumptions'!D10
A12: Capex | B12: 1500 | C12: 500 | D12: 0 | E12: 0 | F12: 0 | G12: 0 | H12: 0 | I12: 0 | J12: 0 | K12: 0 | L12: 0 | M12: 0 | N12: 4000 | O12: 2000 | P12: 2000 | Q12: 0 | R12: 0 | S12: 0 | T12: 0 | U12: 0 | V12: 0 | W12: 0 | X12: 0 | Y12: 0 | Z12: 5000 | AA12: 5000 | AB12: 5000 | AC12: 0 | AD12: 0 | AE12: 0 | AF12: 0 | AG12: 0 | AH12: 0 | AI12: 0 | AJ12: 0 | AK12: 0
A13: Net cashflow | B13: =B7-B8-B9-B10-B11-B12 | C13: =C7-C8-C9-C10-C11-C12 | D13: =D7-D8-D9-D10-D11-D12 | E13: =E7-E8-E9-E10-E11-E12 | F13: =F7-F8-F9-F10-F11-F12 | G13: =G7-G8-G9-G10-G11-G12 | H13: =H7-H8-H9-H10-H11-H12 | I13: =I7-I8-I9-I10-I11-I12 | ... AK13: =AK7-AK8-AK9-AK10-AK11-AK12
A14: Opening cash | B14: ='Assumptions'!B5 | C14: =B15 | D14: =C15 | E14: =D15 | F14: =E15 | G14: =F15 | H14: =G15 | I14: =H15 | J14: =I15 | ... AK14: =AJ15
A15: Closing cash | B15: =B14+B13 | C15: =C14+C13 | D15: =D14+D13 | E15: =E14+E13 | F15: =F14+F13 | G15: =G14+G13 | H15: =H14+H13 | I15: =I14+I13 | ... AK15: =AK14+AK13
A16: Minimum liquidity | B16: ='Assumptions'!B13 | C16: ='Assumptions'!B13 | D16: ='Assumptions'!B13 | E16: ='Assumptions'!B13 | F16: ='Assumptions'!B13 | G16: ='Assumptions'!B13 | H16: ='Assumptions'!B13 | I16: ='Assumptions'!B13 | J16: ='Assumptions'!B13 | K16: ='Assumptions'!B13 | L16: ='Assumptions'!B13 | M16: ='Assumptions'!B13 | N16: ='Assumptions'!C13 | O16: ='Assumptions'!C13 | P16: ='Assumptions'!C13 | Q16: ='Assumptions'!C13 | R16: ='Assumptions'!C13 | S16: ='Assumptions'!C13 | T16: ='Assumptions'!C13 | U16: ='Assumptions'!C13 | V16: ='Assumptions'!C13 | W16: ='Assumptions'!C13 | X16: ='Assumptions'!C13 | Y16: ='Assumptions'!C13 | Z16: ='Assumptions'!D13 | AA16: ='Assumptions'!D13 | AB16: ='Assumptions'!D13 | AC16: ='Assumptions'!D13 | AD16: ='Assumptions'!D13 | AE16: ='Assumptions'!D13 | AF16: ='Assumptions'!D13 | AG16: ='Assumptions'!D13 | AH16: ='Assumptions'!D13 | AI16: ='Assumptions'!D13 | AJ16: ='Assumptions'!D13 | AK16: ='Assumptions'!D13
A17: Liquidity buffer | B17: =B15-B16 | C17: =C15-C16 | D17: =D15-D16 | E17: =E15-E16 | F17: =F15-F16 | G17: =G15-G16 | H17: =H15-H16 | I17: =I15-I16 | ... AK17: =AK15-AK16
A18: Cash status | B18: =IF(B17>=0,"OK","BELOW MIN") | C18: =IF(C17>=0,"OK","BELOW MIN") | D18: =IF(D17>=0,"OK","BELOW MIN") | E18: =IF(E17>=0,"OK","BELOW MIN") | F18: =IF(F17>=0,"OK","BELOW MIN") | G18: =IF(G17>=0,"OK","BELOW MIN") | H18: =IF(H17>=0,"OK","BELOW MIN") | I18: =IF(I17>=0,"OK","BELOW MIN") | ... AK18: =IF(AK17>=0,"OK","BELOW MIN")

Sheet Annual_P&L
A1: AMAVIO | Annual P&L (net service revenue)
A3: Position | B3: Year 1 | C3: Year 2 | D3: Year 3
A4: Net revenue | B4: =SUMIF('Contract_Cash'!$B$4:$B$27,1,'Contract_Cash'!$C$4:$C$27) | C4: =SUMIF('Contract_Cash'!$B$4:$B$27,2,'Contract_Cash'!$C$4:$C$27) | D4: =SUMIF('Contract_Cash'!$B$4:$B$27,3,'Contract_Cash'!$C$4:$C$27)
A5: Variable external costs | B5: =B4*'Assumptions'!B7 | C5: =C4*'Assumptions'!C7 | D5: =D4*'Assumptions'!D7
A6: Overhead | B6: ='Assumptions'!B8*12 | C6: ='Assumptions'!C8*12 | D6: ='Assumptions'!D8*12
A7: Founder compensation | B7: ='Assumptions'!B9*12 | C7: ='Assumptions'!C9*12 | D7: ='Assumptions'!D9*12
A8: Project coordination | B8: ='Assumptions'!B10*12 | C8: ='Assumptions'!C10*12 | D8: ='Assumptions'!D10*12
A9: EBITDA | B9: =B4-B5-B6-B7-B8 | C9: =C4-C5-C6-C7-C8 | D9: =D4-D5-D6-D7-D8
A10: Depreciation | B10: ='Assumptions'!B11 | C10: ='Assumptions'!C11 | D10: ='Assumptions'!D11
A11: EBT | B11: =B9-B10 | C11: =C9-C10 | D11: =D9-D10
A12: Tax reserve | B12: =MAX(0,B11*0.30) | C12: =MAX(0,C11*0.30) | D12: =MAX(0,D11*0.30)
A13: Net income after reserve | B13: =B11-B12 | C13: =C11-C12 | D13: =D11-D12
A14: Note | B14: P&L revenues are net contract values; cash is separately scheduled.

Sheet Scenarios
A1: AMAVIO | Corrected annual scenarios
A3: Scenario | B3: Year | C3: Revenue | D3: Variable costs | E3: Fixed costs incl. founder/staff/depr. | F3: EBT
A4: Downside | B4: 1 | C4: ='Annual_P&L'!B4*0.45 | D4: =C4*'Assumptions'!B7 | E4: ='Annual_P&L'!B6+'Annual_P&L'!B7+'Annual_P&L'!B8+'Annual_P&L'!B10 | F4: =C4-D4-E4
A5: Downside | B5: 2 | C5: ='Annual_P&L'!C4*0.45 | D5: =C5*'Assumptions'!C7 | E5: ='Annual_P&L'!C6+'Annual_P&L'!C7+'Annual_P&L'!C8+'Annual_P&L'!C10 | F5: =C5-D5-E5
A6: Downside | B6: 3 | C6: ='Annual_P&L'!D4*0.45 | D6: =C6*'Assumptions'!D7 | E6: ='Annual_P&L'!D6+'Annual_P&L'!D7+'Annual_P&L'!D8+'Annual_P&L'!D10 | F6: =C6-D6-E6
A7: Base | B7: 1 | C7: ='Annual_P&L'!B4*1 | D7: =C7*'Assumptions'!B7 | E7: ='Annual_P&L'!B6+'Annual_P&L'!B7+'Annual_P&L'!B8+'Annual_P&L'!B10 | F7: =C7-D7-E7
A8: Base | B8: 2 | C8: ='Annual_P&L'!C4*1 | D8: =C8*'Assumptions'!C7 | E8: ='Annual_P&L'!C6+'Annual_P&L'!C7+'Annual_P&L'!C8+'Annual_P&L'!C10 | F8: =C8-D8-E8
A9: Base | B9: 3 | C9: ='Annual_P&L'!D4*1 | D9: =C9*'Assumptions'!D7 | E9: ='Annual_P&L'!D6+'Annual_P&L'!D7+'Annual_P&L'!D8+'Annual_P&L'!D10 | F9: =C9-D9-E9
A10: Growth | B10: 1 | C10: ='Annual_P&L'!B4*1.25 | D10: =C10*'Assumptions'!B7 | E10: ='Annual_P&L'!B6+'Annual_P&L'!B7+'Annual_P&L'!B8+'Annual_P&L'!B10 | F10: =C10-D10-E10
A11: Growth | B11: 2 | C11: ='Annual_P&L'!C4*1.25 | D11: =C11*'Assumptions'!C7 | E11: ='Annual_P&L'!C6+'Annual_P&L'!C7+'Annual_P&L'!C8+'Annual_P&L'!C10 | F11: =C11-D11-E11
A12: Growth | B12: 3 | C12: ='Annual_P&L'!D4*1.25 | D12: =C12*'Assumptions'!D7 | E12: ='Annual_P&L'!D6+'Annual_P&L'!D7+'Annual_P&L'!D8+'Annual_P&L'!D10 | F12: =C12-D12-E12

Sheet Checks
A1: AMAVIO | P0 model checks
A3: Check | B3: Actual | C3: Expected | D3: Difference | E3: Status | F3: Note
A4: Y1 revenue | B4: ='Annual_P&L'!B4 | C4: 93500 | D4: =B4-C4 | E4: =IF(ABS(D4)<0.01,"OK","FAIL") | F4: Contract values
A5: Y2 revenue | B5: ='Annual_P&L'!C4 | C5: 269000 | D5: =B5-C5 | E5: =IF(ABS(D5)<0.01,"OK","FAIL") | F5: Contract values
A6: Y3 revenue | B6: ='Annual_P&L'!D4 | C6: 442000 | D6: =B6-C6 | E6: =IF(ABS(D6)<0.01,"OK","FAIL") | F6: Contract values
A7: Y1 cash collections | B7: =SUM('Monthly_Cash'!B4:M4) | C7: 93500 | D7: =B7-C7 | E7: =IF(ABS(D7)<0.01,"OK","FAIL") | F7: Instalments total
A8: Y2 cash collections | B8: =SUM('Monthly_Cash'!N4:Y4) | C8: 269000 | D8: =B8-C8 | E8: =IF(ABS(D8)<0.01,"OK","FAIL") | F8: Instalments total
A9: Y3 cash collections | B9: =SUM('Monthly_Cash'!Z4:AK4) | C9: 442000 | D9: =B9-C9 | E9: =IF(ABS(D9)<0.01,"OK","FAIL") | F9: Instalments total
A10: Start funding planned | B10: ='Assumptions'!B4 | C10: 25000 | D10: =B10-C10 | E10: =IF(ABS(D10)<0.01,"OK","FAIL") | F10: Single total; no double count
A11: Start funding received | B11: ='Assumptions'!B5 | C11: 0 | D11: =B11-C11 | E11: =IF(B11>=0,"INPUT","FAIL") | F11: Update before live use
A12: Downside factor | B12: ='Assumptions'!B14 | C12: 0.45 | D12: =B12-C12 | E12: =IF(ABS(D12)<0.0001,"OK","FAIL") | F12: Corrected
A13: Model release | B13: CONDITIONAL | C13: CONDITIONAL | D13: =IF(B13=C13,0,1) | E13: =IF(D13=0,"CONDITIONAL","FAIL") | F13: G0–G5 evidence remains external
